Workbook
Name _1B.05.M.010.0010: #REF!
Name _1B.05.M.010.0010: #REF!
Name _1B.05.M.010.0010: #REF!
Name _1B.05.M.010.0050: #REF!
Name _1B.05.M.010.0050: #REF!
Name _1B.05.M.010.0050: #REF!
Name _1B.05.M.0100.0010: #REF!
Name _1B.05.M.0100.0010: #REF!
Name _1B.05.M.020.0010: #REF!
Name _1B.05.M.020.0010: #REF!
Name _1B.05.M.020.0020: #REF!
Name _1B.05.M.020.0020: #REF!
Name _1B.05.M.020.0030: #REF!
Name _1B.05.M.020.0030: #REF!
Name _1B.05.M.020.0040: #REF!
Name _1B.05.M.020.0040: #REF!
Name _1B.05.M.030.0010: #REF!
Name _1B.05.M.030.0010: #REF!
Name _1B.05.M.030.0020: #REF!
Name _1B.05.M.030.0020: #REF!
Name _1B.05.M.040.0010: #REF!
Name _1B.05.M.040.0010: #REF!
Name _1B.05.M.050.0010: #REF!
Name _1B.05.M.050.0010: #REF!
Name _1B.05.M.050.0020: #REF!
Name _1B.05.M.050.0020: #REF!
Name _1B.05.M.050.0030: #REF!
Name _1B.05.M.050.0030: #REF!
Name _1B.05.M.060.0020: #REF!
Name _1B.05.M.060.0020: #REF!
Name _1B.05.M.060.0100: #REF!
Name _1B.05.M.060.0100: #REF!
Name _1B.05.M.070.0010: #REF!
Name _1B.05.M.070.0010: #REF!
Name _1B.05.M.070.0020: #REF!
Name _1B.05.M.070.0020: #REF!
Name _1B.05.M.070.0030: #REF!
Name _1B.05.M.070.0030: #REF!
Name _1B.05.M.070.0040: #REF!
Name _1B.05.M.070.0040: #REF!
Name _1B.05.M.070.0050: #REF!
Name _1B.05.M.070.0050: #REF!
Name _1B.05.M.080.0010: #REF!
Name _1B.05.M.080.0010: #REF!
Name _1B.05.M.090.0010: #REF!
Name _1B.05.M.090.0010: #REF!
Name _1B.09.P.010.0010: #REF!
Name _1B.09.P.010.0010: #REF!
Name _1B.09.P.010.0020: #REF!
Name _1B.09.P.010.0020: #REF!
Name _1B.09.P.010.0030: #REF!
Name _1B.09.P.010.0030: #REF!
Name _1B.09.P.010.0040: #REF!
Name _1B.09.P.010.0040: #REF!
Name _1B.09.P.010.0050: #REF!
Name _1B.09.P.010.0050: #REF!
Name _1B.09.P.010.0060: #REF!
Name _1B.09.P.010.0060: #REF!
Name _1B.09.P.010.0070: #REF!
Name _1B.09.P.010.0070: #REF!

Sheet DB
A1: ='Weekly Progress Report'!$A$1 -> MODON - Weekly Progress Report - Construction Projects
B2: ='Weekly Progress Report'!$A$2 -> Contract General Information | J2: ='Weekly Progress Report'!G2 -> Key Dates | U2: ='Weekly Progress Report'!$M$2 -> Cost Summary (SR) | AD2: ='Weekly Progress Report'!$U$2 -> Performance Summary | AP2: ='Weekly Progress Report'!A61 -> Shop Drawings | AT2: ='Weekly Progress Report'!A70 -> Material Approval | AW2: ='Weekly Progress Report'!A79 -> Procurement Summary | BD2: ='Weekly Progress Report'!L61 -> Quality Reports | BT2: ='Weekly Progress Report'!L69 -> Key Submittals Approval Status | CD2: ='Weekly Progress Report'!L75 -> Invoices Summary | CR2: ='Weekly Progress Report'!L83 -> Resources at Site | CY2: ='Weekly Progress Report'!W61 -> Safety Statistics | FK2: ='Weekly Progress Report'!A88 -> Primavera P6 Schedule Status | FS2: ='Weekly Progress Report'!A97 -> Weekly Prgoress Photos
A3: ='Weekly Progress Report'!AF1 -> Data Date | B3: ='Weekly Progress Report'!A3 -> Project Name | C3: ='Weekly Progress Report'!A4 -> Project ID | D3: ='Weekly Progress Report'!A5 -> Contractor | E3: ='Weekly Progress Report'!A6 -> Consultant | F3: ='Weekly Progress Report'!D4 -> Stage | G3: ='Weekly Progress Report'!D5 -> Status | H3: ='Weekly Progress Report'!D6 -> Modon PM | I3: ='Weekly Progress Report'!AA2 -> Project Scope | J3: ='Weekly Progress Report'!G3 -> Contract Award | K3: ='Weekly Progress Report'!G4 -> Contract Sign | L3: ='Weekly Progress Report'!G5 -> Site Handover | M3: ='Weekly Progress Report'!G6 -> Original Completion | N3: ='Weekly Progress Report'!$I$3 -> Contract Award (Hijri) | O3: ='Weekly Progress Report'!$I$4 -> Contract Sign (Hijri) | P3: ='Weekly Progress Report'!$I$5 -> Site Handover (Hijri) | Q3: ='Weekly Progress Report'!$I$6 -> Original Completion (Hijri) | R3: ='Weekly Progress Report'!$K$3 -> Revised Completion | S3: ='Weekly Progress Report'!$K$4 -> Committed Completion | T3: ='Weekly Progress Report'!$K$5 -> Forecast Completion | U3: ='Weekly Progress Report'!$M$3 -> Original Contract Value | V3: ='Weekly Progress Report'!$M$4 -> Revised Contract Value | W3: ='Weekly Progress Report'!$M$5 -> Estimate At Completion Value | X3: ='Weekly Progress Report'!$M$6 -> Potential Changes | Y3: ='Weekly Progress Report'!$Q$3 -> O&M Value (if any) | Z3: ='Weekly Progress Report'!$Q$4 -> Submitted Invoices (Gross Value) | AA3: ='Weekly Progress Report'!$Q$5 -> Penalities | AB3: ='Weekly Progress Report'!$Q$6 -> FIR Value (Todate) | AC3: Original Plan Value | AD3: ='Weekly Progress Report'!$U$3 -> Plan Value | AE3: ='Weekly Progress Report'!$U$4 -> Earn Value | AF3: ='Weekly Progress Report'!$W$3 -> Phys. Plan Value | AG3: ='Weekly Progress Report'!$W$4 -> Phys. Earn Value | AH3: ='Weekly Progress Report'!$Y$3 -> Quality Score | AI3: ='Weekly Progress Report'!$Y$5 -> Safety Score | AJ3: Weekly PV (SAR) | AK3: Weekly EV (SAR) | AL3: Weekly PV % | AM3: Weekly PV % | AN3: Weekly Phys PV% | AO3: Weekly Phys PV% | AP3: Total SD Planned | AQ3: SD Remaining | AR3: SD Pending | AS3: Total SD Submittals | AT3: Planned Materials Approv | AU3: Material Pending Approval | AV3: Materila Total Submittals | AW3: ='Weekly Progress Report'!C80 -> Total Materials | AX3: ='Weekly Progress Report'!D80 -> Total Number of P.O. | AY3: ='Weekly Progress Report'!E80 -> Actual P.O. To Date | AZ3: ='Weekly Progress Report'!F80 -> Remaining P.O | BA3: ='Weekly Progress Report'!G80 -> Material on Site | BB3: ='Weekly Progress Report'!H80 -> Remaining Materials | BC3: ='Weekly Progress Report'!I80 -> Material Delivery Completion (Date) | BD3: ="NCR "&'Weekly Progress Report'!N62 -> NCR Issued | BE3: ="NCR "&'Weekly Progress Report'!O62 -> NCR Closed | BF3: ="NCR "&'Weekly Progress Report'!P62 -> NCR Pending | BG3: ="NCR "&'Weekly Progress Report'!Q62 -> NCR Avg. Closing (Days) | BH3: ="SIR "&'Weekly Progress Report'!N62 -> SIR Issued | BI3: ="SIR "&'Weekly Progress Report'!O62 -> SIR Closed | BJ3: ="SIR "&'Weekly Progress Report'!P62 -> SIR Pending | BK3: ="SIR "&'Weekly Progress Report'!Q62 -> SIR Avg. Closing (Days) | BL3: ="MIR "&'Weekly Progress Report'!N62 -> MIR Issued | BM3: ="MIR "&'Weekly Progress Report'!O62 -> MIR Closed | BN3: ="MIR "&'Weekly Progress Report'!P62 -> MIR Pending | BO3: ="MIR "&'Weekly Progress Report'!Q62 -> MIR Avg. Closing (Days) | BP3: ="FIR "&'Weekly Progress Report'!N62 -> FIR Issued | BQ3: ="FIR "&'Weekly Progress Report'!O62 -> FIR Closed | BR3: ="FIR "&'Weekly Progress Report'!P62 -> FIR Pending | BS3: ="FIR "&'Weekly Progress Report'!Q62 -> FIR Avg. Closing (Days) | BT3: ='Weekly Progress Report'!L70 -> 1 Quality Plan Approval | BU3: ='Weekly Progress Report'!L71 -> 2 Quality Plan Last Up | BV3: ='Weekly Progress Report'!L72 -> 3 Safety Plan Approval | BW3: ='Weekly Progress Report'!L73 -> 4 Safety Plan Last Up | BX3: ='Weekly Progress Report'!L74 -> 5 Construction Plan Approval | BY3: ='Weekly Progress Report'!Q70 -> 6 Baseline Approval | BZ3: ='Weekly Progress Report'!Q71 -> 7 No of Approved Version of Schedule | CA3: ='Weekly Progress Report'!Q72 -> 8 Last Approved Schedule | CB3: ='Weekly Progress Report'!Q73 -> 9 BOQ Approval Date | CC3: ='Weekly Progress Report'!Q74 -> 10 No of Approved Version of BOQ | CD3: ='Weekly Progress Report'!L76 -> Total Submitted Invoices | CE3: ='Weekly Progress Report'!L77 -> PM Approved Invoices | CF3: ='Weekly Progress Report'!L78 -> No of Paid Invoices | CG3: ='Weekly Progress Report'!L79 -> No of Pending Invoices | CH3: ='Weekly Progress Report'!L80 -> Advance Payment % | CI3: ='Weekly Progress Report'!L81 -> Retention % | CJ3: ='Weekly Progress Report'!L82 -> Deduction / Penalties % | CK3: ='Weekly Progress Report'!O76 -> Submitted Invoices (SAR) | CL3: ='Weekly Progress Report'!O77 -> PM Approved Invoices (SAR) | CM3: ='Weekly Progress Report'!O78 -> Paid Invoices (SAR) | CN3: ='Weekly Progress Report'!O79 -> Last Submitted Period | CO3: ='Weekly Progress Report'!O80 -> Advance Payment (SAR) | CP3: ='Weekly Progress Report'!O81 -> Retention (SAR) | CQ3: ='Weekly Progress Report'!O82 -> Deduction / Penalties (SAR) | CR3: Planned Head Count | CS3: Actual Head Count | CT3: Saudi Staff | CU3: Labor Planned | CV3: Labor Actual | CW3: Equipment Planned | CX3: Equipment Actual | CY3: ="This Week "&'Weekly Progress Report'!X64 -> This Week Total Hours Worked | CZ3: ="This Week "&'Weekly Progress Report'!X65 -> This Week Safe Hours Worked | DA3: ="This Week "&'Weekly Progress Report'!X66 -> This Week LTI | DB3: ="This Week "&'Weekly Progress Report'!X67 -> This Week MTC (Healed w/o Disability) | DC3: ="This Week "&'Weekly Progress Report'!X68 -> This Week MTC (Healed w/ Disability) | DD3: ="This Week "&'Weekly Progress Report'!X69 -> This Week Near Miss | DE3: ="This Week "&'Weekly Progress Report'!X70 -> This Week First Aid Cases | DF3: ="This Week "&'Weekly Progress Report'!X71 -> This Week Fatality | DG3: ="This Week "&'Weekly Progress Report'!X72 -> This Week Fire Incident Cases | DH3: ="This Week "&'Weekly Progress Report'!X73 -> This Week Vehicle Incident | DI3: ="This Week "&'Weekly Progress Report'!X74 -> This Week Property Damages | DJ3: ="This Week "&'Weekly Progress Report'!X75 -> This Week Induction Training | DK3: ="This Week "&'Weekly Progress Report'!X76 -> This Week No.of Internal Training | DL3: ="This Week "&'Weekly Progress Report'!X77 -> This Week No.of Internal Audit | DM3: ="This Week "&'Weekly Progress Report'!X78 -> This Week No. of Toolbox Talks | DN3: ="This Week "&'Weekly Progress Report'!X79 -> This Week Safety Awards/Incentives | DO3: ="This Month "&'Weekly Progress Report'!X64 -> This Month Total Hours Worked | DP3: ="This Month "&'Weekly Progress Report'!X65 -> This Month Safe Hours Worked | DQ3: ="This Month "&'Weekly Progress Report'!X66 -> This Month LTI | DR3: ="This Month "&'Weekly Progress Report'!X67 -> This Month MTC (Healed w/o Disability) | DS3: ="This Month "&'Weekly Progress Report'!X68 -> This Month MTC (Healed w/ Disability) | DT3: ="This Month "&'Weekly Progress Report'!X69 -> This Month Near Miss | DU3: ="This Month "&'Weekly Progress Report'!X70 -> This Month First Aid Cases | DV3: ="This Month "&'Weekly Progress Report'!X71 -> This Month Fatality | DW3: ="This Month "&'Weekly Progress Report'!X72 -> This Month Fire Incident Cases | DX3: ="This Month "&'Weekly Progress Report'!X73 -> This Month Vehicle Incident | DY3: ="This Month "&'Weekly Progress Report'!X74 -> This Month Property Damages | DZ3: ="This Month "&'Weekly Progress Report'!X75 -> This Month Induction Training | EA3: ="This Month "&'Weekly Progress Report'!X76 -> This Month No.of Internal Training | EB3: ="This Month "&'Weekly Progress Report'!X77 -> This Month No.of Internal Audit | EC3: ="This Month "&'Weekly Progress Report'!X78 -> This Month No. of Toolbox Talks | ED3: ="This Month "&'Weekly Progress Report'!X79 -> This Month Safety Awards/Incentives | EE3: ="YTD "&'Weekly Progress Report'!X64 -> YTD Total Hours Worked | EF3: ="YTD "&'Weekly Progress Report'!X65 -> YTD Safe Hours Worked | EG3: ="YTD "&'Weekly Progress Report'!X66 -> YTD LTI | EH3: ="YTD "&'Weekly Progress Report'!X67 -> YTD MTC (Healed w/o Disability) | EI3: ="YTD "&'Weekly Progress Report'!X68 -> YTD MTC (Healed w/ Disability) | EJ3: ="YTD "&'Weekly Progress Report'!X69 -> YTD Near Miss | EK3: ="YTD "&'Weekly Progress Report'!X70 -> YTD First Aid Cases | EL3: ="YTD "&'Weekly Progress Report'!X71 -> YTD Fatality | EM3: ="YTD "&'Weekly Progress Report'!X72 -> YTD Fire Incident Cases | EN3: ="YTD "&'Weekly Progress Report'!X73 -> YTD Vehicle Incident | EO3: ="YTD "&'Weekly Progress Report'!X74 -> YTD Property Damages | EP3: ="YTD "&'Weekly Progress Report'!X75 -> YTD Induction Training | EQ3: ="YTD "&'Weekly Progress Report'!X76 -> YTD No.of Internal Training | ER3: ="YTD "&'Weekly Progress Report'!X77 -> YTD No.of Internal Audit | ES3: ="YTD "&'Weekly Progress Report'!X78 -> YTD No. of Toolbox Talks | ET3: ="YTD "&'Weekly Progress Report'!X79 -> YTD Safety Awards/Incentives | EU3: ="Cum "&'Weekly Progress Report'!X64 -> Cum Total Hours Worked | EV3: ="Cum "&'Weekly Progress Report'!X65 -> Cum Safe Hours Worked | EW3: ="Cum "&'Weekly Progress Report'!X66 -> Cum LTI | EX3: ="Cum "&'Weekly Progress Report'!X67 -> Cum MTC (Healed w/o Disability) | EY3: ="Cum "&'Weekly Progress Report'!X68 -> Cum MTC (Healed w/ Disability) | EZ3: ="Cum "&'Weekly Progress Report'!X69 -> Cum Near Miss | FA3: ="Cum "&'Weekly Progress Report'!X70 -> Cum First Aid Cases | FB3: ="Cum "&'Weekly Progress Report'!X71 -> Cum Fatality | FC3: ="Cum "&'Weekly Progress Report'!X72 -> Cum Fire Incident Cases | FD3: ="Cum "&'Weekly Progress Report'!X73 -> Cum Vehicle Incident | FE3: ="Cum "&'Weekly Progress Report'!X74 -> Cum Property Damages | FF3: ="Cum "&'Weekly Progress Report'!X75 -> Cum Induction Training | FG3: ="Cum "&'Weekly Progress Report'!X76 -> Cum No.of Internal Training | FH3: ="Cum "&'Weekly Progress Report'!X77 -> Cum No.of Internal Audit | FI3: ="Cum "&'Weekly Progress Report'!X78 -> Cum No. of Toolbox Talks | FJ3: ="Cum "&'Weekly Progress Report'!X79 -> Cum Safety Awards/Incentives | FK3: ='Weekly Progress Report'!A91 -> Total Act. | FL3: ='Weekly Progress Report'!B91 -> Not Started | FM3: ='Weekly Progress Report'!C91 -> In Progress | FN3: ='Weekly Progress Report'!D91 -> Completed | FO3: Critical Path Act.Last Week | FP3: Critical Path Act.This Week | FQ3: Failed start Last Week | FR3: Failed start This Week | FS3: ='Weekly Progress Report'!B99 -> 0 | FT3: ='Weekly Progress Report'!D99 -> 0 | FU3: ='Weekly Progress Report'!F99 -> 0 | FV3: ='Weekly Progress Report'!H99 -> 0 | FW3: ='Weekly Progress Report'!J99 -> 0 | FX3: ='Weekly Progress Report'!L99 -> 0 | FY3: ='Weekly Progress Report'!N99 -> 0 | FZ3: ='Weekly Progress Report'!O99 -> 0 | GA3: ='Weekly Progress Report'!P99 -> 0
A4: ='Weekly Progress Report'!AG1 -> 46286 | B4: ='Weekly Progress Report'!B3 -> Factories Low-process Unit (HAFR Al Batin) | C4: ='Weekly Progress Report'!B4 -> HFR1-05-03 | D4: ='Weekly Progress Report'!B5 -> SOROH AL KHAIR CONTRACTING CO. | E4: ='Weekly Progress Report'!B6 -> EGIS | F4: ='Weekly Progress Report'!E4 -> Construction | G4: ='Weekly Progress Report'!E5 -> Active | H4: ='Weekly Progress Report'!E6 -> Eng. Mohammed Al Essa | I4: ='Weekly Progress Report'!AA3 -> The Project scope of work to construct a Factories of low process unit (Hafr Al Batin) industrial city that refer to specific tasks and activities involved in a project. This typically includes activities such as site preparation, Excavation, Foundation work, Structural construction work, Installation of utilities, Finishing works, Electrical Work, Mechanical Works and Landscaping. The scope outlines what will be done and by whom and within the planned timeframe. | J4: ='Weekly Progress Report'!H3 -> 45945 | K4: ='Weekly Progress Report'!H4 -> 45977 | L4: ='Weekly Progress Report'!H5 -> 45988 | M4: ='Weekly Progress Report'!H6 -> 46291 | N4: ='Weekly Progress Report'!$J$3 -> 45945 | O4: ='Weekly Progress Report'!$J$4 -> 45977 | P4: ='Weekly Progress Report'!$J$5 -> 45988 | Q4: ='Weekly Progress Report'!$J$6 -> 46291 | R4: ='Weekly Progress Report'!$L$3 -> 46291 | S4: ='Weekly Progress Report'!$L$4 -> 46324 | T4: ='Weekly Progress Report'!$L$5 -> 46333 | U4: ='Weekly Progress Report'!$O$3 -> 16496856 | V4: ='Weekly Progress Report'!$O$4 -> 16496856 | W4: ='Weekly Progress Report'!$O$5 -> 16496856 | X4: ='Weekly Progress Report'!$O$6 -> 0 | Y4: ='Weekly Progress Report'!$S$3 -> 0 | Z4: ='Weekly Progress Report'!$S$4 -> 10687825 | AA4: ='Weekly Progress Report'!$S$5 -> -141000 | AB4: ='Weekly Progress Report'!$S$6 -> 11743680 | AC4: ='Weekly Progress Report'!$J$31 -> 0.99545455 | AD4: ='Weekly Progress Report'!$V$3 -> 0.99545455 | AE4: ='Weekly Progress Report'!$V$4 -> 0.98173011 | AF4: ='Weekly Progress Report'!$X$3 -> 0.9971756 | AG4: ='Weekly Progress Report'!$X$4 -> 0.98016783 | AH4: ='Weekly Progress Report'!$Z$3 -> 0.79137931 | AI4: ='Weekly Progress Report'!$Z$5 -> 0.78846154 | AJ4: ='Weekly Progress Report'!$E$31 -> 311438.92 | AK4: ='Weekly Progress Report'!$F$31 -> 195657.68 | AL4: =AJ4/V4 -> 0.018878683 | AM4: =AK4/V4 -> 0.011860301 | AN4: ='Weekly Progress Report'!S31 -> 0.0095101651 | AO4: ='Weekly Progress Report'!T31 -> 0.019422841 | AP4: ='Weekly Progress Report'!C69 -> 266 | AQ4: ='Weekly Progress Report'!I69 -> 0 | AR4: ='Weekly Progress Report'!J69 -> 0 | AS4: ='Weekly Progress Report'!K69 -> 266 | AT4: ='Weekly Progress Report'!C78 -> 86 | AU4: ='Weekly Progress Report'!J78 -> 2 | AV4: ='Weekly Progress Report'!K78 -> 86 | AW4: ='Weekly Progress Report'!C87 -> 93 | AX4: ='Weekly Progress Report'!D87 -> 93 | AY4: ='Weekly Progress Report'!E87 -> 93 | AZ4: ='Weekly Progress Report'!F87 -> 0 | BA4: ='Weekly Progress Report'!G87 -> 93 | BB4: ='Weekly Progress Report'!H87 -> 0 | BC4: ='Weekly Progress Report'!I87 -> 46284 | BD4: ='Weekly Progress Report'!N65 -> 7 | BE4: ='Weekly Progress Report'!O65 -> 7 | BF4: ='Weekly Progress Report'!P65 -> 0 | BG4: ='Weekly Progress Report'!Q65 -> 0 | BH4: ='Weekly Progress Report'!N66 -> 15 | BI4: ='Weekly Progress Report'!O66 -> 15 | BJ4: ='Weekly Progress Report'!P66 -> 0 | BK4: ='Weekly Progress Report'!Q66 -> 0 | BL4: ='Weekly Progress Report'!N67 -> 81 | BM4: ='Weekly Progress Report'!O67 -> 65 | BN4: ='Weekly Progress Report'!P67 -> 16 | BO4: ='Weekly Progress Report'!Q67 -> 0 | BP4: ='Weekly Progress Report'!N68 -> 727 | BQ4: ='Weekly Progress Report'!O68 -> 716 | BR4: ='Weekly Progress Report'!P68 -> 11 | BS4: ='Weekly Progress Report'!Q68 -> 0 | BT4: ='Weekly Progress Report'!O70 -> 46106 | BU4: ='Weekly Progress Report'!O71 -> 46106 | BV4: ='Weekly Progress Report'!O72 -> 46287 | BW4: ='Weekly Progress Report'!O73 -> 0 | BX4: ='Weekly Progress Report'!O74 -> 0 | BY4: ='Weekly Progress Report'!U70 -> 46088 | BZ4: ='Weekly Progress Report'!U71 -> 2 | CA4: ='Weekly Progress Report'!U72 -> 46088 | CB4: ='Weekly Progress Report'!U73 -> 46158 | CC4: ='Weekly Progress Report'!U74 -> 0 | CD4: ='Weekly Progress Report'!N76 -> 5 | CE4: ='Weekly Progress Report'!N77 -> 0 | CF4: ='Weekly Progress Report'!N78 -> 0 | CG4: ='Weekly Progress Report'!N79 -> 0 | CH4: ='Weekly Progress Report'!N80 -> 0.1 | CI4: ='Weekly Progress Report'!N81 -> 0 | CJ4: ='Weekly Progress Report'!N82 -> 0.0085470832 | CK4: ='Weekly Progress Report'!R76 -> 10687825 | CL4: ='Weekly Progress Report'!R77 -> 0 | CM4: ='Weekly Progress Report'!R78 -> 281548.46 | CN4: ='Weekly Progress Report'!R79 -> 46254 | CO4: ='Weekly Progress Report'!R80 -> 1649685.6 | CP4: ='Weekly Progress Report'!R81 -> 0 | CQ4: ='Weekly Progress Report'!R82 -> -141000 | CR4: ='Weekly Progress Report'!L86 -> 12 | CS4: ='Weekly Progress Report'!M86 -> 10 | CT4: ='Weekly Progress Report'!O86 -> 0 | CU4: ='Weekly Progress Report'!P86 -> 34 | CV4: ='Weekly Progress Report'!Q86 -> 58 | CW4: ='Weekly Progress Report'!T96 -> 0 | CX4: ='Weekly Progress Report'!U96 -> 13 | CY4: ='Weekly Progress Report'!Z64 -> 3480 | CZ4: ='Weekly Progress Report'!Z65 -> 3480 | DA4: ='Weekly Progress Report'!Z66 -> 0 | DB4: ='Weekly Progress Report'!Z67 -> 0 | DC4: ='Weekly Progress Report'!Z68 -> 0 | DD4: ='Weekly Progress Report'!Z69 -> 0 | DE4: ='Weekly Progress Report'!Z70 -> 0 | DF4: ='Weekly Progress Report'!Z71 -> 0 | DG4: ='Weekly Progress Report'!Z72 -> 0 | DH4: ='Weekly Progress Report'!Z73 -> 0 | DI4: ='Weekly Progress Report'!Z74 -> 0 | DJ4: ='Weekly Progress Report'!Z75 -> 0 | DK4: ='Weekly Progress Report'!Z76 -> 0 | DL4: ='Weekly Progress Report'!Z77 -> 0 | DM4: ='Weekly Progress Report'!Z78 -> 0 | DN4: ='Weekly Progress Report'!Z79 -> 0 | DO4: ='Weekly Progress Report'!AB64 -> 11400 | DP4: ='Weekly Progress Report'!AB65 -> 11400 | DQ4: ='Weekly Progress Report'!AB66 -> 0 | DR4: ='Weekly Progress Report'!AB67 -> 0 | DS4: ='Weekly Progress Report'!AB68 -> 0 | DT4: ='Weekly Progress Report'!AB69 -> 0 | DU4: ='Weekly Progress Report'!AB70 -> 0 | DV4: ='Weekly Progress Report'!AB71 -> 0 | DW4: ='Weekly Progress Report'!AB72 -> 0 | DX4: ='Weekly Progress Report'!AB73 -> 0 | DY4: ='Weekly Progress Report'!AB74 -> 0 | DZ4: ='Weekly Progress Report'!AB75 -> 7 | EA4: ='Weekly Progress Report'!AB76 -> 4 | EB4: ='Weekly Progress Report'!AB77 -> 1 | EC4: ='Weekly Progress Report'!AB78 -> 18 | ED4: ='Weekly Progress Report'!AB79 -> 0 | EE4: ='Weekly Progress Report'!AC64 -> 143630 | EF4: ='Weekly Progress Report'!AC65 -> 143630 | EG4: ='Weekly Progress Report'!AC66 -> 0 | EH4: ='Weekly Progress Report'!AC67 -> 0 | EI4: ='Weekly Progress Report'!AC68 -> 0 | EJ4: ='Weekly Progress Report'!AC69 -> 0 | EK4: ='Weekly Progress Report'!AC70 -> 0 | EL4: ='Weekly Progress Report'!AC71 -> 0 | EM4: ='Weekly Progress Report'!AC72 -> 0 | EN4: ='Weekly Progress Report'!AC73 -> 0 | EO4: ='Weekly Progress Report'!AC74 -> 0 | EP4: ='Weekly Progress Report'!AC75 -> 11 | EQ4: ='Weekly Progress Report'!AC76 -> 5 | ER4: ='Weekly Progress Report'!AC77 -> 5 | ES4: ='Weekly Progress Report'!AC78 -> 23 | ET4: ='Weekly Progress Report'!AC79 -> 0 | EU4: ='Weekly Progress Report'!AD64 -> 143630 | EV4: ='Weekly Progress Report'!AD65 -> 143630 | EW4: ='Weekly Progress Report'!AD66 -> 0 | EX4: ='Weekly Progress Report'!AD67 -> 0 | EY4: ='Weekly Progress Report'!AD68 -> 0 | EZ4: ='Weekly Progress Report'!AD69 -> 0 | FA4: ='Weekly Progress Report'!AD70 -> 0 | FB4: ='Weekly Progress Report'!AD71 -> 0 | FC4: ='Weekly Progress Report'!AD72 -> 0 | FD4: ='Weekly Progress Report'!AD73 -> 0 | FE4: ='Weekly Progress Report'!AD74 -> 0 | FF4: ='Weekly Progress Report'!AD75 -> 11 | FG4: ='Weekly Progress Report'!AD76 -> 5 | FH4: ='Weekly Progress Report'!AD77 -> 5 | FI4: ='Weekly Progress Report'!AD78 -> 23 | FJ4: ='Weekly Progress Report'!AD79 -> 0 | FK4: ='Weekly Progress Report'!A92 -> 902 | FL4: ='Weekly Progress Report'!B92 -> 9 | FM4: ='Weekly Progress Report'!C92 -> 40 | FN4: ='Weekly Progress Report'!D92 -> 854 | FO4: ='Weekly Progress Report'!A96 -> 12 | FP4: ='Weekly Progress Report'!B96 -> 2 | FQ4: ='Weekly Progress Report'!H96 -> 11 | FR4: ='Weekly Progress Report'!I96 -> 10 | FS4: ='Weekly Progress Report'!B104 -> 0 | FT4: ='Weekly Progress Report'!D104 -> 0 | FU4: ='Weekly Progress Report'!F104 -> 0 | FV4: ='Weekly Progress Report'!H104 -> 0 | FW4: ='Weekly Progress Report'!J104 -> 0 | FX4: ='Weekly Progress Report'!L104 -> 0 | FY4: ='Weekly Progress Report'!N104 -> 0 | FZ4: ='Weekly Progress Report'!O104 -> 0 | GA4: ='Weekly Progress Report'!P104 -> 0

Sheet Weekly Progress Report
A1: MODON - Weekly Progress Report - Construction Projects | AF1: Data Date | AG1: ='General Information'!L1 -> 46286
A2: Contract General Information | G2: Key Dates | M2: Cost Summary (SR) | U2: Performance Summary | AA2: Project Scope
A3: Project Name | B3: ='General Information'!C3 -> Factories Low-process Unit (HAFR Al Batin) | G3: Contract Award | H3: ='General Information'!C12 -> 45945 | I3: Contract Award (Hijri) | J3: ='General Information'!C16 -> 45945 | K3: Revised Completion | L3: ='General Information'!C15 -> 46291 | M3: Original Contract Value | O3: ='Invoice Log'!E3 -> 16496856 | Q3: O&M Value (if any) | S3: ='Invoice Log'!I3 -> 0 | T3: EAC | U3: Plan Value | V3: =K31 -> 0.99545455 | W3: Phys. Plan Value | X3: =W31 -> 0.9971756 | Y3: Quality Score | Z3: =Quality!AC10 -> 0.79137931 | AA3: =+Progress!B1 -> The Project scope of work to construct a Factories of low process unit (Hafr Al Batin) industrial city that refer to specific tasks and activities involved in a project. This typically includes activities such as site preparation, Excavation, Foundation work, Structural construction work, Installation of utilities, Finishing works, Electrical Work, Mechanical Works and Landscaping. The scope outlines what will be done and by whom and within the planned timeframe.
A4: Project ID | B4: ='General Information'!C4 -> HFR1-05-03 | D4: Stage | E4: ='General Information'!C7 -> Construction | G4: Contract Sign | H4: ='General Information'!C13 -> 45977 | I4: Contract Sign (Hijri) | J4: ='General Information'!C17 -> 45977 | K4: Committed Completion | L4: ='General Information'!C21 -> 46324 | M4: Revised Contract Value | O4: ='Invoice Log'!E4 -> 16496856 | P4: EAC | Q4: Submitted Invoices (Gross Value) | S4: ='Invoice Log'!I5 -> 10687825 | U4: Earn Value | V4: =L31 -> 0.98173011 | W4: Phys. Earn Value | X4: =X31 -> 0.98016783 | Z4: =REPT("¢",IF(INT(+Z3*10)>5,5,INT(+Z3*10)))&REPT("£",IF(INT(+Z3*10)>5,0,5-INT(+Z3*10)))&CHAR(10)&REPT("¢",+IF(INT(+Z3*10)>5,-5+INT(+Z3*10),0))&REPT("£",IF(INT(+Z3*10)>5,10-INT(+Z3*10),5)) -> ¢¢¢¢¢ ¢¢£££
A5: Contractor | B5: ='General Information'!C5 -> SOROH AL KHAIR CONTRACTING CO. | D5: Status | E5: ='General Information'!C8 -> Active | G5: Site Handover | H5: ='General Information'!C14 -> 45988 | I5: Site Handover (Hijri) | J5: ='General Information'!C18 -> 45988 | K5: Forecast Completion | L5: ='General Information'!C22 -> 46333 | M5: Estimate At Completion Value | O5: ='Invoice Log'!E5 -> 16496856 | P5: =+#REF!+#REF!+O5 -> #REF! | Q5: Penalities | S5: ='Invoice Log'!I59 -> -141000 | U5: Variance | V5: =V4-V3 -> -0.013724444 | W5: Variance | X5: =Y31 -> -0.017007777 | Y5: Safety Score | Z5: ='HSE-Stat'!J23 -> 0.78846154
A6: Consultant | B6: ='General Information'!C6 -> EGIS | D6: Modon PM | E6: ='General Information'!C9 -> Eng. Mohammed Al Essa | G6: Original Completion | H6: ='General Information'!C15 -> 46291 | I6: Original Completion (Hijri) | J6: ='General Information'!C19 -> 46291 | K6: Variance | L6: ='General Information'!C23 -> -42 | M6: Potential Changes | O6: =O4-O5 -> 0 | Q6: FIR Value (Todate) | S6: ='FIR from Begining up to date '!K328 -> 11743680 | U6: FIR % | V6: =S6/O4 -> 0.71187384 | W6: Invoiced % | X6: =S4/O4 -> 0.64787044 | Z6: =REPT("¢",IF(INT(+Z5*10)>5,5,INT(+Z5*10)))&REPT("£",IF(INT(+Z5*10)>5,0,5-INT(+Z5*10)))&CHAR(10)&REPT("¢",+IF(INT(+Z5*10)>5,-5+INT(+Z5*10),0))&REPT("£",IF(INT(+Z5*10)>5,10-INT(+Z5*10),5)) -> ¢¢¢¢¢ ¢¢£££
A8: Progress Overview
A9: Earned Value Progress (SAR) | O9: Physical Progress (Effort) | AA9: Earned Value Progress (%)
A10: WBS | C10: BOQ Value (SAR) | D10: % Wt. | E10: Weekly (SAR) | G10: To Date (SAR) | O10: Budgeted | P10: % Wt. | Q10: Weekly Physical Progress | U10: To Date Physical Progress
E11: Planned | F11: Earned | G11: Original Plan | H11: Revised Planned | I11: Earned | J11: Original Plan % | K11: Revised Planned % | L11: Earned % | M11: Variance | N11: SPI | O11: (Manhours) | Q11: Planned | R11: Earned | S11: Plan % | T11: Earned % | U11: Planned | V11: Earned | W11: Plan % | X11: Earned % | Y11: Variance | Z11: SPI
A12: =Progress!A8 -> Mobilization | C12: =Progress!C8 -> 0 | D12: =IF(ISBLANK(C12),"",C12/$C$31) -> 0 | E12: =Progress!E8 -> 0 | F12: =Progress!F8 -> 0 | G12: =Progress!G8 -> 0 | H12: =Progress!H8 -> 0 | I12: =Progress!I8 -> 0 | J12: =IFERROR(IF(ISBLANK(G12),"",G12/C12),0) -> 0 | K12: =IFERROR(IF(ISBLANK(H12),"",H12/C12),0) -> 0 | L12: =IFERROR(IF(ISBLANK(I12),"",I12/C12),0) -> 0 | M12: =IFERROR(L12-K12,"") -> 0 | N12: =IFERROR(L12/K12,"") | O12: =Progress!K8 -> 4400 | P12: =IF(ISBLANK(O12),"",O12/$O$31) -> 0.030017738 | Q12: =Progress!M8 -> 0 | R12: =Progress!N8 -> 0 | S12: =IFERROR(IF(ISBLANK(Q12),"",Q12/O12),0) -> 0 | T12: =IFERROR(IF(ISBLANK(R12),"",R12/O12),0) -> 0 | U12: =Progress!O8 -> 4400 | V12: =Progress!P8 -> 4400 | W12: =IFERROR(IF(ISBLANK(U12),"",U12/O12),0) -> 1 | X12: =IFERROR(IF(ISBLANK(V12),"",V12/O12),0) -> 1 | Y12: =IFERROR(X12-W12,"") -> 0 | Z12: =IFERROR(X12/W12,"") -> 1
A13: =Progress!A9 -> Engineering Phase | C13: =Progress!C9 -> 494865 | D13: =IF(ISBLANK(C13),"",C13/$C$31) -> 0.029997534 | E13: =Progress!E9 -> 0 | F13: =Progress!F9 -> 0 | G13: =Progress!G9 -> 494865 | H13: =Progress!H9 -> 494865 | I13: =Progress!I9 -> 494865 | J13: =IFERROR(IF(ISBLANK(G13),"",G13/C13),0) -> 1 | K13: =IFERROR(IF(ISBLANK(H13),"",H13/C13),0) -> 1 | L13: =IFERROR(IF(ISBLANK(I13),"",I13/C13),0) -> 1 | M13: =IFERROR(L13-K13,"") -> 0 | N13: =IFERROR(L13/K13,"") -> 1 | O13: =Progress!K9 -> 7321 | P13: =IF(ISBLANK(O13),"",O13/$O$31) -> 0.049945422 | Q13: =Progress!M9 -> 0 | R13: =Progress!N9 -> 0 | S13: =IFERROR(IF(ISBLANK(Q13),"",Q13/O13),0) -> 0 | T13: =IFERROR(IF(ISBLANK(R13),"",R13/O13),0) -> 0 | U13: =Progress!O9 -> 7321 | V13: =Progress!P9 -> 7321 | W13: =IFERROR(IF(ISBLANK(U13),"",U13/O13),0) -> 1 | X13: =IFERROR(IF(ISBLANK(V13),"",V13/O13),0) -> 1 | Y13: =IFERROR(X13-W13,"") -> 0 | Z13: =IFERROR(X13/W13,"") -> 1
A14: =Progress!A10 -> Procurment | C14: =Progress!C10 -> 3299371 | D14: =IF(ISBLANK(C14),"",C14/$C$31) -> 0.19999999 | E14: =Progress!E10 -> 0 | F14: =Progress!F10 -> 10324.7 | G14: =Progress!G10 -> 3299371 | H14: =Progress!H10 -> 3299371 | I14: =Progress!I10 -> 3299371 | J14: =IFERROR(IF(ISBLANK(G14),"",G14/C14),0) -> 1 | K14: =IFERROR(IF(ISBLANK(H14),"",H14/C14),0) -> 1 | L14: =IFERROR(IF(ISBLANK(I14),"",I14/C14),0) -> 1 | M14: =IFERROR(L14-K14,"") -> 0 | N14: =IFERROR(L14/K14,"") -> 1 | O14: =Progress!K10 -> 17626 | P14: =IF(ISBLANK(O14),"",O14/$O$31) -> 0.12024833 | Q14: =Progress!M10 -> 0 | R14: =Progress!N10 -> 74 | S14: =IFERROR(IF(ISBLANK(Q14),"",Q14/O14),0) -> 0 | T14: =IFERROR(IF(ISBLANK(R14),"",R14/O14),0) -> 0.0041983434 | U14: =Progress!O10 -> 17626 | V14: =Progress!P10 -> 17626 | W14: =IFERROR(IF(ISBLANK(U14),"",U14/O14),0) -> 1 | X14: =IFERROR(IF(ISBLANK(V14),"",V14/O14),0) -> 1 | Y14: =IFERROR(X14-W14,"") -> 0 | Z14: =IFERROR(X14/W14,"") -> 1
A15: =Progress!A11 -> Construction phase | C15: =Progress!C11 -> 11052936 | D15: =IF(ISBLANK(C15),"",C15/$C$31) -> 0.67000257 | E15: =Progress!E11 -> 52113.6 | F15: =Progress!F11 -> 144090.88 | G15: =Progress!G11 -> 11052936 | H15: =Progress!H11 -> 11052936 | I15: =Progress!I11 -> 10978372 | J15: =IFERROR(IF(ISBLANK(G15),"",G15/C15),0) -> 1 | K15: =IFERROR(IF(ISBLANK(H15),"",H15/C15),0) -> 1 | L15: =IFERROR(IF(ISBLANK(I15),"",I15/C15),0) -> 0.9932539 | M15: =IFERROR(L15-K15,"") -> -0.0067461045 | N15: =IFERROR(L15/K15,"") -> 0.9932539 | O15: =Progress!K11 -> 109913 | P15: =IF(ISBLANK(O15),"",O15/$O$31) -> 0.74984991 | Q15: =Progress!M11 -> 244 | R15: =Progress!N11 -> 2590 | S15: =IFERROR(IF(ISBLANK(Q15),"",Q15/O15),0) -> 0.0022199376 | T15: =IFERROR(IF(ISBLANK(R15),"",R15/O15),0) -> 0.023564092 | U15: =Progress!O11 -> 109832 | V15: =Progress!P11 -> 108012 | W15: =IFERROR(IF(ISBLANK(U15),"",U15/O15),0) -> 0.99926305 | X15: =IFERROR(IF(ISBLANK(V15),"",V15/O15),0) -> 0.9827045 | Y15: =IFERROR(X15-W15,"") -> -0.016558551 | Z15: =IFERROR(X15/W15,"") -> 0.98342924
A16: =Progress!A12 -> site general works | C16: =Progress!C12 -> 1298122 | D16: =Progress!D12 -> 0.078689057 | E16: =Progress!E12 -> 0 | F16: =Progress!F12 -> 0 | G16: =Progress!H12 -> 1298122 | H16: =Progress!H12 -> 1298122 | I16: =Progress!I12 -> 1298122 | J16: =IFERROR(IF(ISBLANK(G16),"",G16/C16),0) -> 1 | K16: =IFERROR(IF(ISBLANK(H16),"",H16/C16),0) -> 1 | L16: =IFERROR(IF(ISBLANK(I16),"",I16/C16),0) -> 1 | M16: =IFERROR(L16-K16,"") -> 0 | N16: =IFERROR(L16/K16,"") -> 1 | O16: =Progress!K12 -> 5423 | P16: =Progress!L12 -> 0.036996862 | Q16: =Progress!M12 -> 0 | R16: =Progress!N12 -> 0 | S16: =IFERROR(IF(ISBLANK(Q16),"",Q16/O16),0) -> 0 | T16: =IFERROR(IF(ISBLANK(R16),"",R16/O16),0) -> 0 | U16: =Progress!O12 -> 5423 | V16: =Progress!P12 -> 5423 | W16: =IFERROR(IF(ISBLANK(U16),"",U16/O16),0) -> 1 | X16: =IFERROR(IF(ISBLANK(V16),"",V16/O16),0) -> 1 | Y16: =IFERROR(X16-W16,"") -> 0 | Z16: =IFERROR(X16/W16,"") -> 1
A17: =Progress!A13 -> Hunger -1 | C17: =Progress!C13 -> 3846587.2 | D17: =Progress!D13 -> 0.23317093 | E17: =Progress!E13 -> 52113.6 | F17: =Progress!F13 -> 33514.57 | G17: =Progress!H13 -> 3846587.2 | H17: =Progress!H13 -> 3846587.2 | I17: =Progress!I13 -> 3832084.2 | J17: =IFERROR(IF(ISBLANK(G17),"",G17/C17),0) -> 1 | K17: =IFERROR(IF(ISBLANK(H17),"",H17/C17),0) -> 1 | L17: =IFERROR(IF(ISBLANK(I17),"",I17/C17),0) -> 0.99622966 | M17: =IFERROR(L17-K17,"") -> -0.0037703396 | N17: =IFERROR(L17/K17,"") -> 0.99622966 | O17: =Progress!K13 -> 23347 | P17: =Progress!L13 -> 0.15927821 | Q17: =Progress!M13 -> 157 | R17: =Progress!N13 -> 320 | S17: =IFERROR(IF(ISBLANK(Q17),"",Q17/O17),0) -> 0.0067246327 | T17: =IFERROR(IF(ISBLANK(R17),"",R17/O17),0) -> 0.013706258 | U17: =Progress!O13 -> 23295 | V17: =Progress!P13 -> 23137 | W17: =IFERROR(IF(ISBLANK(U17),"",U17/O17),0) -> 0.99777273 | X17: =IFERROR(IF(ISBLANK(V17),"",V17/O17),0) -> 0.99100527 | Y17: =IFERROR(X17-W17,"") -> -0.0067674648 | Z17: =IFERROR(X17/W17,"") -> 0.99321743
A18: =Progress!A14 -> Hunger-2 | C18: =Progress!C14 -> 3851109 | D18: =Progress!D14 -> 0.23344503 | E18: =Progress!E14 -> 0 | F18: =Progress!F14 -> 33277.93 | G18: =Progress!H14 -> 3851109 | H18: =Progress!H14 -> 3851109 | I18: =Progress!I14 -> 3836609.7 | J18: =IFERROR(IF(ISBLANK(G18),"",G18/C18),0) -> 1 | K18: =IFERROR(IF(ISBLANK(H18),"",H18/C18),0) -> 1 | L18: =IFERROR(IF(ISBLANK(I18),"",I18/C18),0) -> 0.99623502 | M18: =IFERROR(L18-K18,"") -> -0.0037649778 | N18: =IFERROR(L18/K18,"") -> 0.99623502 | O18: =Progress!K14 -> 24765 | P18: =Progress!L14 -> 0.16895211 | Q18: =Progress!M14 -> 88 | R18: =Progress!N14 -> 350 | S18: =IFERROR(IF(ISBLANK(Q18),"",Q18/O18),0) -> 0.003553402 | T18: =IFERROR(IF(ISBLANK(R18),"",R18/O18),0) -> 0.014132849 | U18: =Progress!O14 -> 24736 | V18: =Progress!P14 -> 24529 | W18: =IFERROR(IF(ISBLANK(U18),"",U18/O18),0) -> 0.99882899 | X18: =IFERROR(IF(ISBLANK(V18),"",V18/O18),0) -> 0.99047042 | Y18: =IFERROR(X18-W18,"") -> -0.0083585706 | Z18: =IFERROR(X18/W18,"") -> 0.99163163
A19: =Progress!A15 -> Sephtic Tank | C19: =Progress!C15 -> 149552.06 | D19: =Progress!D15 -> 0.0090654887 | E19: =Progress!E15 -> 0 | F19: =Progress!F15 -> 0 | G19: =Progress!H15 -> 149552.06 | H19: =Progress!H15 -> 149552.06 | I19: =Progress!I15 -> 149552.06 | J19: =IFERROR(IF(ISBLANK(G19),"",G19/C19),0) -> 1 | K19: =IFERROR(IF(ISBLANK(H19),"",H19/C19),0) -> 1 | L19: =IFERROR(IF(ISBLANK(I19),"",I19/C19),0) -> 1 | M19: =IFERROR(L19-K19,"") -> 0 | N19: =IFERROR(L19/K19,"") -> 1 | O19: =Progress!K15 -> 7817 | P19: =Progress!L15 -> 0.05332924 | Q19: =Progress!M15 -> 0 | R19: =Progress!N15 -> 0 | S19: =IFERROR(IF(ISBLANK(Q19),"",Q19/O19),0) -> 0 | T19: =IFERROR(IF(ISBLANK(R19),"",R19/O19),0) -> 0 | U19: =Progress!O15 -> 7817 | V19: =Progress!P15 -> 7817 | W19: =IFERROR(IF(ISBLANK(U19),"",U19/O19),0) -> 1 | X19: =IFERROR(IF(ISBLANK(V19),"",V19/O19),0) -> 1 | Y19: =IFERROR(X19-W19,"") -> 0 | Z19: =IFERROR(X19/W19,"") -> 1
A20: =Progress!A16 -> Mosque -elec room-Toilets Works | C20: =Progress!C16 -> 396377.89 | D20: =Progress!D16 -> 0.024027481 | E20: =Progress!E16 -> 0 | F20: =Progress!F16 -> 20068.17 | G20: =Progress!H16 -> 396377.89 | H20: =Progress!H16 -> 396377.89 | I20: =Progress!I16 -> 386130.49 | J20: =IFERROR(IF(ISBLANK(G20),"",G20/C20),0) -> 1 | K20: =IFERROR(IF(ISBLANK(H20),"",H20/C20),0) -> 1 | L20: =IFERROR(IF(ISBLANK(I20),"",I20/C20),0) -> 0.9741474 | M20: =IFERROR(L20-K20,"") -> -0.025852602 | N20: =IFERROR(L20/K20,"") -> 0.9741474 | O20: =Progress!K16 -> 15308 | P20: =Progress!L16 -> 0.10443444 | Q20: =Progress!M16 -> 0 | R20: =Progress!N16 -> 671 | S20: =IFERROR(IF(ISBLANK(Q20),"",Q20/O20),0) -> 0 | T20: =IFERROR(IF(ISBLANK(R20),"",R20/O20),0) -> 0.04383329 | U20: =Progress!O16 -> 15308 | V20: =Progress!P16 -> 14842 | W20: =IFERROR(IF(ISBLANK(U20),"",U20/O20),0) -> 1 | X20: =IFERROR(IF(ISBLANK(V20),"",V20/O20),0) -> 0.9695584 | Y20: =IFERROR(X20-W20,"") -> -0.030441599 | Z20: =IFERROR(X20/W20,"") -> 0.9695584
A21: =Progress!A17 -> GRB Tank | C21: =Progress!C17 -> 163749.6 | D21: =Progress!D17 -> 0.0099261096 | E21: =Progress!E17 -> 0 | F21: =Progress!F17 -> 0 | G21: =Progress!H17 -> 163749.6 | H21: =Progress!H17 -> 163749.6 | I21: =Progress!I17 -> 163749.6 | J21: =IFERROR(IF(ISBLANK(G21),"",G21/C21),0) -> 1 | K21: =IFERROR(IF(ISBLANK(H21),"",H21/C21),0) -> 1 | L21: =IFERROR(IF(ISBLANK(I21),"",I21/C21),0) -> 1 | M21: =IFERROR(L21-K21,"") -> 0 | N21: =IFERROR(L21/K21,"") -> 1 | O21: =Progress!K17 -> 9922 | P21: =Progress!L17 -> 0.067689999 | Q21: =Progress!M17 -> 0 | R21: =Progress!N17 -> 0 | S21: =IFERROR(IF(ISBLANK(Q21),"",Q21/O21),0) -> 0 | T21: =IFERROR(IF(ISBLANK(R21),"",R21/O21),0) -> 0 | U21: =Progress!O17 -> 9922 | V21: =Progress!P17 -> 9922 | W21: =IFERROR(IF(ISBLANK(U21),"",U21/O21),0) -> 1 | X21: =IFERROR(IF(ISBLANK(V21),"",V21/O21),0) -> 1 | Y21: =IFERROR(X21-W21,"") -> 0 | Z21: =IFERROR(X21/W21,"") -> 1
A22: =Progress!A18 -> Pump room | C22: =Progress!C18 -> 389712.84 | D22: =Progress!D18 -> 0.023623462 | E22: =Progress!E18 -> 0 | F22: =Progress!F18 -> 2664.93 | G22: =Progress!H18 -> 389712.84 | H22: =Progress!H18 -> 389712.84 | I22: =Progress!I18 -> 387774.89 | J22: =IFERROR(IF(ISBLANK(G22),"",G22/C22),0) -> 1 | K22: =IFERROR(IF(ISBLANK(H22),"",H22/C22),0) -> 1 | L22: =IFERROR(IF(ISBLANK(I22),"",I22/C22),0) -> 0.99502724 | M22: =IFERROR(L22-K22,"") -> -0.004972764 | N22: =IFERROR(L22/K22,"") -> 0.99502724 | O22: =Progress!K18 -> 7698 | P22: =Progress!L18 -> 0.052517397 | Q22: =Progress!M18 -> 0 | R22: =Progress!N18 -> 192 | S22: =IFERROR(IF(ISBLANK(Q22),"",Q22/O22),0) -> 0 | T22: =IFERROR(IF(ISBLANK(R22),"",R22/O22),0) -> 0.024941543 | U22: =Progress!O18 -> 7698 | V22: =Progress!P18 -> 7313 | W22: =IFERROR(IF(ISBLANK(U22),"",U22/O22),0) -> 1 | X22: =IFERROR(IF(ISBLANK(V22),"",V22/O22),0) -> 0.94998701 | Y22: =IFERROR(X22-W22,"") -> -0.05001299 | Z22: =IFERROR(X22/W22,"") -> 0.94998701
A23: =Progress!A19 -> External WORKS-MEP | C23: =Progress!C19 -> 581705.66 | D23: =Progress!D19 -> 0.035261608 | E23: =Progress!E19 -> 0 | F23: =Progress!F19 -> 3195.27 | G23: =Progress!H19 -> 581705.66 | H23: =Progress!H19 -> 581705.66 | I23: =Progress!I19 -> 570319.85 | J23: =IFERROR(IF(ISBLANK(G23),"",G23/C23),0) -> 1 | K23: =IFERROR(IF(ISBLANK(H23),"",H23/C23),0) -> 1 | L23: =IFERROR(IF(ISBLANK(I23),"",I23/C23),0) -> 0.98042685 | M23: =IFERROR(L23-K23,"") -> -0.019573146 | N23: =IFERROR(L23/K23,"") -> 0.98042685 | O23: =Progress!K19 -> 6008 | P23: =Progress!L19 -> 0.040987856 | Q23: =Progress!M19 -> 0 | R23: =Progress!N19 -> 7 | S23: =IFERROR(IF(ISBLANK(Q23),"",Q23/O23),0) -> 0 | T23: =IFERROR(IF(ISBLANK(R23),"",R23/O23),0) -> 0.0011651132 | U23: =Progress!O19 -> 6008 | V23: =Progress!P19 -> 5985 | W23: =IFERROR(IF(ISBLANK(U23),"",U23/O23),0) -> 1 | X23: =IFERROR(IF(ISBLANK(V23),"",V23/O23),0) -> 0.99617177 | Y23: =IFERROR(X23-W23,"") -> -0.003828229 | Z23: =IFERROR(X23/W23,"") -> 0.99617177
A24: =Progress!A20 -> External Works landscape | C24: =Progress!C20 -> 376019.58 | D24: =Progress!D20 -> 0.022793409 | E24: =Progress!E20 -> 0 | F24: =Progress!F20 -> 51370.56 | G24: =Progress!H20 -> 376019.58 | H24: =Progress!H20 -> 376019.58 | I24: =Progress!I20 -> 354028.77 | J24: =IFERROR(IF(ISBLANK(G24),"",G24/C24),0) -> 1 | K24: =IFERROR(IF(ISBLANK(H24),"",H24/C24),0) -> 1 | L24: =IFERROR(IF(ISBLANK(I24),"",I24/C24),0) -> 0.94151685 | M24: =IFERROR(L24-K24,"") -> -0.058483151 | N24: =IFERROR(L24/K24,"") -> 0.94151685 | O24: =Progress!K20 -> 9626 | P24: =Progress!L20 -> 0.065670624 | Q24: =Progress!M20 -> 0 | R24: =Progress!N20 -> 1050 | S24: =IFERROR(IF(ISBLANK(Q24),"",Q24/O24),0) -> 0 | T24: =IFERROR(IF(ISBLANK(R24),"",R24/O24),0) -> 0.10907958 | U24: =Progress!O20 -> 9626 | V24: =Progress!P20 -> 9045 | W24: =IFERROR(IF(ISBLANK(U24),"",U24/O24),0) -> 1 | X24: =IFERROR(IF(ISBLANK(V24),"",V24/O24),0) -> 0.93964263 | Y24: =IFERROR(X24-W24,"") -> -0.060357365 | Z24: =IFERROR(X24/W24,"") -> 0.93964263
A25: =Progress!A21 -> Testing and comissiong | C25: =Progress!C21 -> 1649684 | D25: =IF(ISBLANK(C25),"",C25/$C$31) -> 0.099999904 | E25: =Progress!E21 -> 259325.32 | F25: =Progress!F21 -> 41242.1 | G25: =Progress!G21 -> 1574698.4 | H25: =Progress!H21 -> 1574698.4 | I25: =Progress!I21 -> 1422852.4 | J25: =IFERROR(IF(ISBLANK(G25),"",G25/C25),0) -> 0.95454545 | K25: =IFERROR(IF(ISBLANK(H25),"",H25/C25),0) -> 0.95454545 | L25: =IFERROR(IF(ISBLANK(I25),"",I25/C25),0) -> 0.8625 | M25: =IFERROR(L25-K25,"") -> -0.092045452 | N25: =IFERROR(L25/K25,"") -> 0.90357143 | O25: =Progress!K21 -> 7320 | P25: =IF(ISBLANK(O25),"",O25/$O$31) -> 0.0499386 | Q25: =Progress!M21 -> 1150 | R25: =Progress!N21 -> 183 | S25: =IFERROR(IF(ISBLANK(Q25),"",Q25/O25),0) -> 0.15710383 | T25: =IFERROR(IF(ISBLANK(R25),"",R25/O25),0) -> 0.025 | U25: =Progress!O21 -> 6987 | V25: =Progress!P21 -> 6314 | W25: =IFERROR(IF(ISBLANK(U25),"",U25/O25),0) -> 0.9545082 | X25: =IFERROR(IF(ISBLANK(V25),"",V25/O25),0) -> 0.86256831 | Y25: =IFERROR(X25-W25,"") -> -0.091939891 | Z25: =IFERROR(X25/W25,"") -> 0.90367826
A26: =Progress!A22 -> Close Out | C26: =Progress!C22 -> 0 | D26: =IF(ISBLANK(C26),"",C26/$C$31) -> 0 | E26: =Progress!E22 -> 0 | F26: =Progress!F22 -> 0 | G26: =Progress!G22 -> 0 | H26: =Progress!H22 -> 0 | I26: =Progress!I22 -> 0 | J26: =IFERROR(IF(ISBLANK(G26),"",G26/C26),0) -> 0 | K26: =IFERROR(IF(ISBLANK(H26),"",H26/C26),0) -> 0 | L26: =IFERROR(IF(ISBLANK(I26),"",I26/C26),0) -> 0 | M26: =IFERROR(L26-K26,"") -> 0 | N26: =IFERROR(L26/K26,"") | O26: =Progress!K22 -> 0 | P26: =IF(ISBLANK(O26),"",O26/$O$31) -> 0 | Q26: =Progress!M22 -> 0 | R26: =Progress!N22 -> 0 | S26: =IFERROR(IF(ISBLANK(Q26),"",Q26/O26),0) -> 0 | T26: =IFERROR(IF(ISBLANK(R26),"",R26/O26),0) -> 0 | U26: =Progress!O22 -> 0 | V26: =Progress!P22 -> 0 | W26: =IFERROR(IF(ISBLANK(U26),"",U26/O26),0) -> 0 | X26: =IFERROR(IF(ISBLANK(V26),"",V26/O26),0) -> 0 | Y26: =IFERROR(X26-W26,"") -> 0 | Z26: =IFERROR(X26/W26,"")
D27: =IF(ISBLANK(C27),"",C27/$C$31) | J27: =IFERROR(IF(ISBLANK(G27),"",G27/C27),0) | K27: =IFERROR(IF(ISBLANK(H27),"",H27/C27),0) | L27: =IFERROR(IF(ISBLANK(I27),"",I27/C27),0) | M27: =IFERROR(L27-K27,"") | N27: =IFERROR(L27/K27,"") | S27: =IFERROR(IF(ISBLANK(Q27),"",Q27/O27),0) | T27: =IFERROR(IF(ISBLANK(R27),"",R27/O27),0) | W27: =IFERROR(IF(ISBLANK(U27),"",U27/O27),0) | X27: =IFERROR(IF(ISBLANK(V27),"",V27/O27),0) | Y27: =IFERROR(X27-W27,"") | Z27: =IFERROR(X27/W27,"")
D28: =IF(ISBLANK(C28),"",C28/$C$31) | J28: =IFERROR(IF(ISBLANK(G28),"",G28/C28),0) | K28: =IFERROR(IF(ISBLANK(H28),"",H28/C28),0) | L28: =IFERROR(IF(ISBLANK(I28),"",I28/C28),0) | M28: =IFERROR(L28-K28,"") | N28: =IFERROR(L28/K28,"") | S28: =IFERROR(IF(ISBLANK(Q28),"",Q28/O28),0) | T28: =IFERROR(IF(ISBLANK(R28),"",R28/O28),0) | W28: =IFERROR(IF(ISBLANK(U28),"",U28/O28),0) | X28: =IFERROR(IF(ISBLANK(V28),"",V28/O28),0) | Y28: =IFERROR(X28-W28,"") | Z28: =IFERROR(X28/W28,"")
D29: =IF(ISBLANK(C29),"",C29/$C$31) | J29: =IFERROR(IF(ISBLANK(G29),"",G29/C29),0) | K29: =IFERROR(IF(ISBLANK(H29),"",H29/C29),0) | L29: =IFERROR(IF(ISBLANK(I29),"",I29/C29),0) | M29: =IFERROR(L29-K29,"") | N29: =IFERROR(L29/K29,"") | S29: =IFERROR(IF(ISBLANK(Q29),"",Q29/O29),0) | T29: =IFERROR(IF(ISBLANK(R29),"",R29/O29),0) | W29: =IFERROR(IF(ISBLANK(U29),"",U29/O29),0) | X29: =IFERROR(IF(ISBLANK(V29),"",V29/O29),0) | Y29: =IFERROR(X29-W29,"") | Z29: =IFERROR(X29/W29,"")
D30: =IF(ISBLANK(C30),"",C30/$C$31) | J30: =IFERROR(IF(ISBLANK(G30),"",G30/C30),0) | K30: =IFERROR(IF(ISBLANK(H30),"",H30/C30),0) | L30: =IFERROR(IF(ISBLANK(I30),"",I30/C30),0) | M30: =IFERROR(L30-K30,"") | N30: =IFERROR(L30/K30,"") | S30: =IFERROR(IF(ISBLANK(Q30),"",Q30/O30),0) | T30: =IFERROR(IF(ISBLANK(R30),"",R30/O30),0) | W30: =IFERROR(IF(ISBLANK(U30),"",U30/O30),0) | X30: =IFERROR(IF(ISBLANK(V30),"",V30/O30),0) | Y30: =IFERROR(X30-W30,"") | Z30: =IFERROR(X30/W30,"")
B31: Total | C31: =SUM(C13:C15,C25) -> 16496856 | D31: =SUM(D13:D15,D25) -> 1 | E31: =SUM(E13:E15,E25) -> 311438.92 | F31: =SUM(F13:F15,F25) -> 195657.68 | G31: =SUM(G13:G15,G25) -> 16421870 | H31: =SUM(H13:H15,H25) -> 16421870 | I31: =SUM(I13:I15,I25) -> 16195460 | J31: =IFERROR(IF(ISBLANK(G31),"",G31/C31),0) -> 0.99545455 | K31: =IFERROR(IF(ISBLANK(H31),"",H31/C31),0) -> 0.99545455 | L31: =IFERROR(IF(ISBLANK(I31),"",I31/C31),0) -> 0.98173011 | M31: =+L31-K31 -> -0.013724444 | N31: =L31/K31 -> 0.98621289 | O31: =SUM(O12:O15,O25) -> 146580 | P31: =SUM(P12:P15,P25) -> 1 | Q31: =SUM(Q13:Q15,Q25) -> 1394 | R31: =SUM(R13:R15,R25) -> 2847 | S31: =IFERROR(IF(ISBLANK(Q31),"",Q31/O31),0) -> 0.0095101651 | T31: =IFERROR(IF(ISBLANK(R31),"",R31/O31),0) -> 0.019422841 | U31: =SUM(U12:U15,U25) -> 146166 | V31: =SUM(V12:V15,V25) -> 143673 | W31: =IFERROR(IF(ISBLANK(U31),"",U31/O31),0) -> 0.9971756 | X31: =IFERROR(IF(ISBLANK(V31),"",V31/O31),0) -> 0.98016783 | Y31: =+X31-W31 -> -0.017007777 | Z31: =X31/W31 -> 0.98294405
AA32: Construction Milestones
AA33: Item No. | AB33: Milestones | AD33: Original (Baseline) | AE33: Latest Plan | AF33: Forecast | AG33: Status | AH33: Days Change
AA34: =+Milestones!A4 -> 1 | AB34: =+Milestones!B4 -> Award Date | AD34: =+Milestones!C4 -> 45945 | AE34: =+Milestones!D4 -> 45945 | AF34: =+Milestones!E4 -> 45945 | AG34: =+Milestones!F4 -> A | AH34: =+Milestones!G4 -> 0
AA35: =+Milestones!A5 -> 2 | AB35: =+Milestones!B5 -> Contract Sign Date | AD35: =+Milestones!C5 -> 45977 | AE35: =+Milestones!D5 -> 45977 | AF35: =+Milestones!E5 -> 45977 | AG35: =+Milestones!F5 -> A | AH35: =+Milestones!G5 -> 0
AA36: =+Milestones!A6 -> 3 | AB36: =+Milestones!B6 -> Site Handover Date | AD36: =+Milestones!C6 -> 45988 | AE36: =+Milestones!D6 -> 45988 | AF36: =+Milestones!E6 -> 45988 | AG36: =+Milestones!F6 -> A | AH36: =+Milestones!G6 -> 0
AA37: =+Milestones!A7 -> 4 | AB37: =+Milestones!B7 -> Complete Mobilization | AD37: =+Milestones!C7 -> 46019 | AE37: =+Milestones!D7 -> 46019 | AF37: =+Milestones!E7 -> 46019 | AG37: =+Milestones!F7 -> A | AH37: =+Milestones!G7 -> 0
AA38: =+Milestones!A10 -> 7 | AB38: =+Milestones!B10 -> Complete Earthworks | AD38: =+Milestones!C10 -> 46103 | AE38: =+Milestones!D10 -> 46116 | AF38: =+Milestones!E10 -> 46116 | AG38: =+Milestones!F10 -> F | AH38: =+Milestones!G10 -> 0
AA39: =+Milestones!A11 -> 8 | AB39: =+Milestones!B11 -> Complete Civil & Arch Works | AD39: =+Milestones!C11 -> 45854 | AE39: =+Milestones!D11 -> 46340 | AF39: =+Milestones!E11 -> 46306 | AG39: =+Milestones!F11 -> F | AH39: =+Milestones!G11 -> 34
AA40: =+Milestones!A12 -> 9 | AB40: =+Milestones!B12 -> Complete Electrical Works | AD40: =+Milestones!C12 -> 45902 | AE40: =+Milestones!D12 -> 46333 | AF40: =+Milestones!E12 -> 46312 | AG40: =+Milestones!F12 -> F | AH40: =+Milestones!G12 -> 21
AA41: =+Milestones!A13 -> 10 | AB41: =+Milestones!B13 -> Complete Mechanical Works | AD41: =+Milestones!C13 -> 45926 | AE41: =+Milestones!D13 -> 46358 | AF41: =+Milestones!E13 -> 46324 | AG41: =+Milestones!F13 -> F | AH41: =+Milestones!G13 -> 34
AA42: =+Milestones!A14 -> 11 | AB42: =+Milestones!B14 -> Complete Finishing Works | AD42: =+Milestones!C14 -> 46291 | AE42: =+Milestones!D14 -> 46355 | AF42: =+Milestones!E14 -> 46324 | AG42: =+Milestones!F14 -> F | AH42: =+Milestones!G14 -> 31
AA43: =+Milestones!A15 -> 12 | AB43: =+Milestones!B15 -> Project Handover | AD43: =+Milestones!C15 -> 46291 | AE43: =+Milestones!D15 -> 46384 | AF43: =+Milestones!E15 -> 46333 | AG43: =+Milestones!F15 -> F | AH43: =+Milestones!G15 -> 51
A59: Performance overview
A60: Submittals Status | L60: Quality | W60: Safety
A61: Shop Drawings | L61: Quality Reports | W61: Safety Statistics | AE61: Proactive Vs Reactive Actions Taken
A62: Item Per WBS | C62: Total | D62: Total Submitted Drawings | I62: Remaining | J62: Pending | K62: Total Submittals | L62: Quality Reports | N62: Issued | O62: Closed | P62: Pending | Q62: Avg. Closing (Days) | R62: Pending | W62: Category | X62: Item | Z62: This Week | AB62: This Month | AC62: Year to Date | AD62: Cumulative
D63: A | E63: B | F63: C | G63: D | H63: Processed | R63: 0-10 Days | S63: 11-20 Days | T63: 21-30 Days | U63: 31-60 Days | V63: > 60 Days
A64: ='Quality-Stat'!$A$13 -> Civil /Roads | C64: =IF('Quality-Stat'!D13="","",'Quality-Stat'!D13) -> 19 | D64: =IF('Quality-Stat'!E13="","",'Quality-Stat'!E13) -> 2 | E64: =IF('Quality-Stat'!F13="","",'Quality-Stat'!F13) -> 17 | F64: =IF('Quality-Stat'!G13="","",'Quality-Stat'!G13) | G64: =IF('Quality-Stat'!H13="","",'Quality-Stat'!H13) | H64: =IF('Quality-Stat'!I13="","",'Quality-Stat'!I13) -> 19 | I64: =IF('Quality-Stat'!J13="","",'Quality-Stat'!J13) -> 0 | J64: =IF('Quality-Stat'!K13="","",'Quality-Stat'!K13) | K64: =IF('Quality-Stat'!L13="","",'Quality-Stat'!L13) -> 19 | W64: General | X64: ='HSE-Stat'!B4 -> Total Hours Worked | Z64: ='HSE-Stat'!D4 -> 3480 | AB64: ='HSE-Stat'!E4 -> 11400 | AC64: ='HSE-Stat'!F4 -> 143630 | AD64: ='HSE-Stat'!G4 -> 143630 | AG64: Proactive | AH64: =+SUM(AD75:AD79) -> 44
A65: ='Quality-Stat'!$A$14 -> Structural | C65: =IF('Quality-Stat'!D14="","",'Quality-Stat'!D14) -> 129 | D65: =IF('Quality-Stat'!E14="","",'Quality-Stat'!E14) -> 8 | E65: =IF('Quality-Stat'!F14="","",'Quality-Stat'!F14) -> 121 | F65: =IF('Quality-Stat'!G14="","",'Quality-Stat'!G14) | G65: =IF('Quality-Stat'!H14="","",'Quality-Stat'!H14) | H65: =IF('Quality-Stat'!I14="","",'Quality-Stat'!I14) -> 129 | I65: =IF('Quality-Stat'!J14="","",'Quality-Stat'!J14) | J65: =IF('Quality-Stat'!K14="","",'Quality-Stat'!K14) | K65: =IF('Quality-Stat'!L14="","",'Quality-Stat'!L14) -> 129 | L65: Non Conformance (NCR) | N65: ='Quality-Stat'!C5 -> 7 | O65: ='Quality-Stat'!D5 -> 7 | P65: ='Quality-Stat'!E5 -> 0 | Q65: ='Quality-Stat'!F5 -> 0 | R65: ='Quality-Stat'!G5 -> 0 | S65: ='Quality-Stat'!H5 -> 0 | T65: ='Quality-Stat'!I5 -> 0 | U65: ='Quality-Stat'!J5 -> 0 | V65: ='Quality-Stat'!K5 -> 0 | X65: ='HSE-Stat'!B5 -> Safe Hours Worked | Z65: ='HSE-Stat'!D5 -> 3480 | AB65: ='HSE-Stat'!E5 -> 11400 | AC65: ='HSE-Stat'!F5 -> 143630 | AD65: ='HSE-Stat'!G5 -> 143630 | AG65: Reactive | AH65: =SUM(AD66:AD74) -> 0
A66: ='Quality-Stat'!$A$15 -> Architectural | C66: =IF('Quality-Stat'!D15="","",'Quality-Stat'!D15) -> 37 | D66: =IF('Quality-Stat'!E15="","",'Quality-Stat'!E15) -> 3 | E66: =IF('Quality-Stat'!F15="","",'Quality-Stat'!F15) -> 34 | F66: =IF('Quality-Stat'!G15="","",'Quality-Stat'!G15) | G66: =IF('Quality-Stat'!H15="","",'Quality-Stat'!H15) | H66: =IF('Quality-Stat'!I15="","",'Quality-Stat'!I15) -> 37 | I66: =IF('Quality-Stat'!J15="","",'Quality-Stat'!J15) -> 0 | J66: =IF('Quality-Stat'!K15="","",'Quality-Stat'!K15) -> 0 | K66: =IF('Quality-Stat'!L15="","",'Quality-Stat'!L15) -> 37 | L66: Site Instruction (SIR) | N66: ='Quality-Stat'!C6 -> 15 | O66: ='Quality-Stat'!D6 -> 15 | P66: ='Quality-Stat'!E6 -> 0 | Q66: ='Quality-Stat'!F6 -> 0 | R66: ='Quality-Stat'!G6 -> 0 | S66: ='Quality-Stat'!H6 -> 0 | T66: ='Quality-Stat'!I6 -> 0 | U66: ='Quality-Stat'!J6 -> 0 | V66: ='Quality-Stat'!K6 -> 0 | W66: Reactive | X66: ='HSE-Stat'!B6 -> LTI | Z66: ='HSE-Stat'!D6 -> 0 | AB66: ='HSE-Stat'!E6 -> 0 | AC66: ='HSE-Stat'!F6 -> 0 | AD66: ='HSE-Stat'!G6 -> 0
A67: ='Quality-Stat'!$A$16 -> Mechanical | C67: =IF('Quality-Stat'!D16="","",'Quality-Stat'!D16) -> 41 | D67: =IF('Quality-Stat'!E16="","",'Quality-Stat'!E16) | E67: =IF('Quality-Stat'!F16="","",'Quality-Stat'!F16) -> 41 | F67: =IF('Quality-Stat'!G16="","",'Quality-Stat'!G16) | G67: =IF('Quality-Stat'!H16="","",'Quality-Stat'!H16) | H67: =IF('Quality-Stat'!I16="","",'Quality-Stat'!I16) -> 41 | I67: =IF('Quality-Stat'!J16="","",'Quality-Stat'!J16) -> 0 | J67: =IF('Quality-Stat'!K16="","",'Quality-Stat'!K16) -> 0 | K67: =IF('Quality-Stat'!L16="","",'Quality-Stat'!L16) -> 41 | L67: Material Inspection (MIR) | N67: ='Quality-Stat'!C7 -> 81 | O67: ='Quality-Stat'!D7 -> 65 | P67: ='Quality-Stat'!E7 -> 16 | Q67: ='Quality-Stat'!F7 -> 0 | R67: ='Quality-Stat'!G7 -> 0 | S67: ='Quality-Stat'!H7 -> 0 | T67: ='Quality-Stat'!I7 -> 0 | U67: ='Quality-Stat'!J7 -> 0 | V67: ='Quality-Stat'!K7 -> 0 | X67: ='HSE-Stat'!B7 -> MTC (Healed w/o Disability) | Z67: ='HSE-Stat'!D7 -> 0 | AB67: ='HSE-Stat'!E7 -> 0 | AC67: ='HSE-Stat'!F7 -> 0 | AD67: ='HSE-Stat'!G7 -> 0
A68: ='Quality-Stat'!$A$17 -> Electrical | C68: =IF('Quality-Stat'!D17="","",'Quality-Stat'!D17) -> 40 | D68: =IF('Quality-Stat'!E17="","",'Quality-Stat'!E17) -> 0 | E68: =IF('Quality-Stat'!F17="","",'Quality-Stat'!F17) -> 40 | F68: =IF('Quality-Stat'!G17="","",'Quality-Stat'!G17) | G68: =IF('Quality-Stat'!H17="","",'Quality-Stat'!H17) -> 0 | H68: =IF('Quality-Stat'!I17="","",'Quality-Stat'!I17) -> 40 | I68: =IF('Quality-Stat'!J17="","",'Quality-Stat'!J17) -> 0 | J68: =IF('Quality-Stat'!K17="","",'Quality-Stat'!K17) -> 0 | K68: =IF('Quality-Stat'!L17="","",'Quality-Stat'!L17) -> 40 | L68: Field Inspection (FIR) | N68: ='Quality-Stat'!C8 -> 727 | O68: ='Quality-Stat'!D8 -> 716 | P68: ='Quality-Stat'!E8 -> 11 | Q68: ='Quality-Stat'!F8 -> 0 | R68: ='Quality-Stat'!G8 -> 0 | S68: ='Quality-Stat'!H8 -> 0 | T68: ='Quality-Stat'!I8 -> 0 | U68: ='Quality-Stat'!J8 -> 0 | V68: ='Quality-Stat'!K8 -> 0 | X68: ='HSE-Stat'!B8 -> MTC (Healed w/ Disability) | Z68: ='HSE-Stat'!D8 -> 0 | AB68: ='HSE-Stat'!E8 -> 0 | AC68: ='HSE-Stat'!F8 -> 0 | AD68: ='HSE-Stat'!G8 -> 0
A69: TOTAL | C69: =SUM(C64:C68) -> 266 | D69: =SUM(D64:D68) -> 13 | E69: =SUM(E64:E68) -> 253 | F69: =SUM(F64:F68) -> 0 | G69: =SUM(G64:G68) -> 0 | H69: =SUM(H64:H68) -> 266 | I69: =SUM(I64:I68) -> 0 | J69: =SUM(J64:J68) -> 0 | K69: =SUM(K64:K68) -> 266 | L69: Key Submittals Approval Status | X69: ='HSE-Stat'!B9 -> Near Miss | Z69: ='HSE-Stat'!D9 -> 0 | AB69: ='HSE-Stat'!E9 -> 0 | AC69: ='HSE-Stat'!F9 -> 0 | AD69: ='HSE-Stat'!G9 -> 0
A70: Material Approval | L70: 1 Quality Plan Approval | O70: ='General Information'!C27 -> 46106 | Q70: 6 Baseline Approval | U70: ='General Information'!C39 -> 46088 | X70: ='HSE-Stat'!B10 -> First Aid Cases | Z70: ='HSE-Stat'!D10 -> 0 | AB70: ='HSE-Stat'!E10 -> 0 | AC70: ='HSE-Stat'!F10 -> 0 | AD70: ='HSE-Stat'!G10 -> 0 | AE70: Total Hours Worked Vs Safe Hours Worked
A71: Item Per WBS | C71: Total | D71: Total Submitted Material | I71: Remaining to approve | J71: Pending | K71: Total Submittals | L71: 2 Quality Plan Last Up | O71: ='General Information'!C28 -> 46106 | Q71: 7 No of Approved Version of Schedule | U71: ='General Information'!C40 -> 2 | X71: ='HSE-Stat'!B11 -> Fatality | Z71: ='HSE-Stat'!D11 -> 0 | AB71: ='HSE-Stat'!E11 -> 0 | AC71: ='HSE-Stat'!F11 -> 0 | AD71: ='HSE-Stat'!G11 -> 0
D72: A | E72: B | F72: C | G72: D | H72: Processed | I72: with Designer | L72: 3 Safety Plan Approval | O72: ='General Information'!C31 -> 46287 | Q72: 8 Last Approved Schedule | U72: ='General Information'!C41 -> 46088 | X72: ='HSE-Stat'!B12 -> Fire Incident Cases | Z72: ='HSE-Stat'!D12 -> 0 | AB72: ='HSE-Stat'!E12 -> 0 | AC72: ='HSE-Stat'!F12 -> 0 | AD72: ='HSE-Stat'!G12 -> 0
A73: ='Quality-Stat'!$A$24 -> Civil / Roads | C73: =IF('Quality-Stat'!D24="","",'Quality-Stat'!D24) -> 9 | D73: =IF('Quality-Stat'!E24="","",'Quality-Stat'!E24) | E73: =IF('Quality-Stat'!F24="","",'Quality-Stat'!F24) -> 9 | F73: =IF('Quality-Stat'!G24="","",'Quality-Stat'!G24) | G73: =IF('Quality-Stat'!H24="","",'Quality-Stat'!H24) -> 0 | H73: =IF('Quality-Stat'!I24="","",'Quality-Stat'!I24) -> 9 | I73: =IF('Quality-Stat'!J24="","",'Quality-Stat'!J24) | J73: =IF('Quality-Stat'!K24="","",'Quality-Stat'!K24) -> 0 | K73: =IF('Quality-Stat'!L24="","",'Quality-Stat'!L24) -> 9 | L73: 4 Safety Plan Last Up | O73: ='General Information'!C32 -> 0 | Q73: 9 BOQ Approval Date | U73: ='General Information'!C44 -> 46158 | X73: ='HSE-Stat'!B13 -> Vehicle Incident | Z73: ='HSE-Stat'!D13 -> 0 | AB73: ='HSE-Stat'!E13 -> 0 | AC73: ='HSE-Stat'!F13 -> 0 | AD73: ='HSE-Stat'!G13 -> 0
A74: ='Quality-Stat'!$A$25 -> Structural | C74: =IF('Quality-Stat'!D25="","",'Quality-Stat'!D25) -> 9 | D74: =IF('Quality-Stat'!E25="","",'Quality-Stat'!E25) -> 0 | E74: =IF('Quality-Stat'!F25="","",'Quality-Stat'!F25) -> 9 | F74: =IF('Quality-Stat'!G25="","",'Quality-Stat'!G25) -> 0 | G74: =IF('Quality-Stat'!H25="","",'Quality-Stat'!H25) -> 0 | H74: =IF('Quality-Stat'!I25="","",'Quality-Stat'!I25) -> 9 | I74: =IF('Quality-Stat'!J25="","",'Quality-Stat'!J25) | J74: =IF('Quality-Stat'!K25="","",'Quality-Stat'!K25) | K74: =IF('Quality-Stat'!L25="","",'Quality-Stat'!L25) -> 9 | L74: 5 Construction Plan Approval | O74: ='General Information'!C48 -> 0 | Q74: 10 No of Approved Version of BOQ | U74: ='General Information'!C45 -> 0 | X74: ='HSE-Stat'!B14 -> Property Damages | Z74: ='HSE-Stat'!D14 -> 0 | AB74: ='HSE-Stat'!E14 -> 0 | AC74: ='HSE-Stat'!F14 -> 0 | AD74: ='HSE-Stat'!G14 -> 0
A75: ='Quality-Stat'!$A$26 -> Architectural | C75: =IF('Quality-Stat'!D26="","",'Quality-Stat'!D26) -> 30 | D75: =IF('Quality-Stat'!E26="","",'Quality-Stat'!E26) -> 1 | E75: =IF('Quality-Stat'!F26="","",'Quality-Stat'!F26) -> 26 | F75: =IF('Quality-Stat'!G26="","",'Quality-Stat'!G26) -> 0 | G75: =IF('Quality-Stat'!H26="","",'Quality-Stat'!H26) -> 1 | H75: =IF('Quality-Stat'!I26="","",'Quality-Stat'!I26) -> 26 | I75: =IF('Quality-Stat'!J26="","",'Quality-Stat'!J26) -> 0 | J75: =IF('Quality-Stat'!K26="","",'Quality-Stat'!K26) -> 2 | K75: =IF('Quality-Stat'!L26="","",'Quality-Stat'!L26) -> 30 | L75: Invoices Summary | W75: Proactive | X75: ='HSE-Stat'!B15 -> Induction Training | Z75: ='HSE-Stat'!D15 -> 0 | AB75: ='HSE-Stat'!E15 -> 7 | AC75: ='HSE-Stat'!F15 -> 11 | AD75: ='HSE-Stat'!G15 -> 11
A76: ='Quality-Stat'!$A$27 -> Mechanical | C76: =IF('Quality-Stat'!D27="","",'Quality-Stat'!D27) -> 20 | D76: =IF('Quality-Stat'!E27="","",'Quality-Stat'!E27) -> 0 | E76: =IF('Quality-Stat'!F27="","",'Quality-Stat'!F27) -> 20 | F76: =IF('Quality-Stat'!G27="","",'Quality-Stat'!G27) | G76: =IF('Quality-Stat'!H27="","",'Quality-Stat'!H27) -> 0 | H76: =IF('Quality-Stat'!I27="","",'Quality-Stat'!I27) -> 20 | I76: =IF('Quality-Stat'!J27="","",'Quality-Stat'!J27) -> 0 | J76: =IF('Quality-Stat'!K27="","",'Quality-Stat'!K27) | K76: =IF('Quality-Stat'!L27="","",'Quality-Stat'!L27) -> 20 | L76: Total Submitted Invoices | N76: ='Invoice Log'!U3 -> 5 | O76: Submitted Invoices (SAR) | R76: ='Invoice Log'!Y3 -> 10687825 | T76: Contract Value (SR) | U76: =O4 -> 16496856 | X76: ='HSE-Stat'!B16 -> No.of Internal Training | Z76: ='HSE-Stat'!D16 -> 0 | AB76: ='HSE-Stat'!E16 -> 4 | AC76: ='HSE-Stat'!F16 -> 5 | AD76: ='HSE-Stat'!G16 -> 5
A77: ='Quality-Stat'!$A$28 -> Electrical | C77: =IF('Quality-Stat'!D28="","",'Quality-Stat'!D28) -> 18 | D77: =IF('Quality-Stat'!E28="","",'Quality-Stat'!E28) -> 0 | E77: =IF('Quality-Stat'!F28="","",'Quality-Stat'!F28) -> 18 | F77: =IF('Quality-Stat'!G28="","",'Quality-Stat'!G28) -> 0 | G77: =IF('Quality-Stat'!H28="","",'Quality-Stat'!H28) -> 0 | H77: =IF('Quality-Stat'!I28="","",'Quality-Stat'!I28) -> 18 | I77: =IF('Quality-Stat'!J28="","",'Quality-Stat'!J28) | J77: =IF('Quality-Stat'!K28="","",'Quality-Stat'!K28) | K77: =IF('Quality-Stat'!L28="","",'Quality-Stat'!L28) -> 18 | L77: PM Approved Invoices | N77: ='Invoice Log'!U5 -> 0 | O77: PM Approved Invoices (SAR) | R77: ='Invoice Log'!Y5 -> 0 | T77: Planned Value (SR) | U77: =H31 -> 16421870 | X77: ='HSE-Stat'!B17 -> No.of Internal Audit | Z77: ='HSE-Stat'!D17 -> 0 | AB77: ='HSE-Stat'!E17 -> 1 | AC77: ='HSE-Stat'!F17 -> 5 | AD77: ='HSE-Stat'!G17 -> 5
A78: TOTAL | C78: =SUM(C73:C77) -> 86 | D78: =SUM(D73:D77) -> 1 | E78: =SUM(E73:E77) -> 82 | F78: =SUM(F73:F77) -> 0 | G78: =SUM(G73:G77) -> 1 | H78: =SUM(H73:H77) -> 82 | I78: =SUM(I73:I77) -> 0 | J78: =SUM(J73:J77) -> 2 | K78: =SUM(K73:K77) -> 86 | L78: No of Paid Invoices | N78: ='Invoice Log'!U6 -> 0 | O78: Paid Invoices (SAR) | R78: ='Invoice Log'!Y6 -> 281548.46 | T78: Earned Value (SR) | U78: =I31 -> 16195460 | X78: ='HSE-Stat'!B18 -> No. of Toolbox Talks | Z78: ='HSE-Stat'!D18 -> 0 | AB78: ='HSE-Stat'!E18 -> 18 | AC78: ='HSE-Stat'!F18 -> 23 | AD78: ='HSE-Stat'!G18 -> 23
A79: Procurement Summary | L79: No of Pending Invoices | N79: =N77-N78 -> 0 | O79: Last Submitted Period | R79: ='Invoice Log'!AB3 -> 46254 | T79: Submitted (SAR) | U79: =R76 -> 10687825 | X79: ='HSE-Stat'!B19 -> Safety Awards/Incentives | Z79: ='HSE-Stat'!D19 -> 0 | AB79: ='HSE-Stat'!E19 -> 0 | AC79: ='HSE-Stat'!F19 -> 0 | AD79: ='HSE-Stat'!G19 -> 0
A80: Item Per WBS | C80: Total Materials | D80: Total Number of P.O. | E80: Actual P.O. To Date | F80: Remaining P.O | G80: Material on Site | H80: Remaining Materials | I80: Material Delivery Completion (Date) | L80: Advance Payment % | N80: ='Invoice Log'!M3 -> 0.1 | O80: Advance Payment (SAR) | R80: ='Invoice Log'!Q3 -> 1649685.6 | T80: PM Approved (SAR) | U80: =R77 -> 0 | W80: Latest Contract Change Order Log
D81: A | E81: B | F81: C | G81: D | H81: Processed | L81: Retention % | N81: ='Invoice Log'!M4 -> 0 | O81: Retention (SAR) | R81: ='Invoice Log'!Q4 -> 0 | T81: Total Paid (SAR) | U81: =R78 -> 281548.46
A82: ='Quality-Stat'!$A$34 -> Civil | C82: =IF('Quality-Stat'!D34="","",'Quality-Stat'!D34) -> 9 | D82: =IF('Quality-Stat'!E34="","",'Quality-Stat'!E34) -> 9 | E82: =IF('Quality-Stat'!F34="","",'Quality-Stat'!F34) -> 9 | F82: =IF('Quality-Stat'!G34="","",'Quality-Stat'!G34) | G82: =IF('Quality-Stat'!H34="","",'Quality-Stat'!H34) -> 9 | H82: =IF('Quality-Stat'!I34="","",'Quality-Stat'!I34) -> 0 | I82: ='Quality-Stat'!J34 -> 46284 | L82: Deduction / Penalties % | N82: ='Invoice Log'!M5 -> 0.0085470832 | O82: Deduction / Penalties (SAR) | R82: ='Invoice Log'!M6 -> -141000 | W82: CCO No. | X82: Date Added | Y82: Description of Change | AD82: Status | AE82: Cost | AF82: Sch Impact (Months) | AG82: Date Approved | AH82: Duration
A83: ='Quality-Stat'!$A$35 -> Structural | C83: =IF('Quality-Stat'!D35="","",'Quality-Stat'!D35) -> 9 | D83: =IF('Quality-Stat'!E35="","",'Quality-Stat'!E35) -> 9 | E83: =IF('Quality-Stat'!F35="","",'Quality-Stat'!F35) -> 9 | F83: =IF('Quality-Stat'!G35="","",'Quality-Stat'!G35) | G83: =IF('Quality-Stat'!H35="","",'Quality-Stat'!H35) -> 9 | H83: =IF('Quality-Stat'!I35="","",'Quality-Stat'!I35) -> 0 | I83: ='Quality-Stat'!J35 -> 46147 | L83: Resources at Site
A84: ='Quality-Stat'!$A$36 -> Architectural | C84: =IF('Quality-Stat'!D36="","",'Quality-Stat'!D36) -> 22 | D84: =IF('Quality-Stat'!E36="","",'Quality-Stat'!E36) -> 22 | E84: =IF('Quality-Stat'!F36="","",'Quality-Stat'!F36) -> 22 | F84: =IF('Quality-Stat'!G36="","",'Quality-Stat'!G36) | G84: =IF('Quality-Stat'!H36="","",'Quality-Stat'!H36) -> 22 | H84: =IF('Quality-Stat'!I36="","",'Quality-Stat'!I36) -> 0 | I84: ='Quality-Stat'!J36 -> 46284 | L84: Head Count - Non Manual | P84: Head Count - Manual | T84: Total Head Count | W84: =CCO!A3 -> 1
A85: ='Quality-Stat'!$A$37 -> Mechanical | C85: =IF('Quality-Stat'!D37="","",'Quality-Stat'!D37) -> 28 | D85: =IF('Quality-Stat'!E37="","",'Quality-Stat'!E37) -> 28 | E85: =IF('Quality-Stat'!F37="","",'Quality-Stat'!F37) -> 28 | F85: =IF('Quality-Stat'!G37="","",'Quality-Stat'!G37) -> 0 | G85: =IF('Quality-Stat'!H37="","",'Quality-Stat'!H37) -> 28 | H85: =IF('Quality-Stat'!I37="","",'Quality-Stat'!I37) -> 0 | I85: ='Quality-Stat'!J37 -> 46263 | L85: Planned | M85: Actual | N85: Next Month Forecast | O85: Saudi Staff | P85: Planned | Q85: Actual | R85: Next Month Forecast | S85: Saudi Staff | T85: Total Plan | U85: Total Actual | V85: Variance
A86: ='Quality-Stat'!$A$38 -> Electrical | C86: =IF('Quality-Stat'!D38="","",'Quality-Stat'!D38) -> 25 | D86: =IF('Quality-Stat'!E38="","",'Quality-Stat'!E38) -> 25 | E86: =IF('Quality-Stat'!F38="","",'Quality-Stat'!F38) -> 25 | F86: =IF('Quality-Stat'!G38="","",'Quality-Stat'!G38) | G86: =IF('Quality-Stat'!H38="","",'Quality-Stat'!H38) -> 25 | H86: =IF('Quality-Stat'!I38="","",'Quality-Stat'!I38) | I86: ='Quality-Stat'!J38 -> 46263 | L86: =Manpower!A20 -> 12 | M86: =Manpower!B20 -> 10 | N86: =Manpower!F20 -> #N/A | O86: =Manpower!H20 -> 0 | P86: =M96 -> 34 | Q86: =N96 -> 58 | R86: =Manpower!F24 -> #N/A | S86: =Manpower!H24 -> 0 | T86: =L86+P86 -> 46 | U86: =M86+Q86 -> 68 | V86: =+U86-T86 -> 22 | W86: =CCO!A4 | AF86: =CCO!F4 | AG86: =CCO!G4 | AH86: =CCO!H4
A87: TOTAL | C87: =IF('Quality-Stat'!D39="","",'Quality-Stat'!D39) -> 93 | D87: =IF('Quality-Stat'!E39="","",'Quality-Stat'!E39) -> 93 | E87: =IF('Quality-Stat'!F39="","",'Quality-Stat'!F39) -> 93 | F87: =IF('Quality-Stat'!G39="","",'Quality-Stat'!G39) -> 0 | G87: =IF('Quality-Stat'!H39="","",'Quality-Stat'!H39) -> 93 | H87: =IF('Quality-Stat'!I39="","",'Quality-Stat'!I39) -> 0 | I87: =MAX(I82:I86) -> 46284 | L87: Manpower Breakdown by Trade | S87: Major Equipment
A88: =Schedule!A1 -> Primavera P6 Schedule Status | L88: Key Trade | M88: Planned | N88: Actual | S88: Type | T88: Planned | U88: Actual | V88: Idle | W88: =CCO!A5 | X88: =CCO!B5 | Y88: =CCO!C5 | AD88: =IF(CCO!D5="","",CCO!D5) | AE88: =CCO!E5 | AF88: =CCO!F5 | AG88: =CCO!G5 | AH88: =CCO!H5
A89: =Schedule!A2 -> Project Activities Overview | L89: =+Manpower!N23 -> General Labor | M89: =Manpower!N24 -> 10 | N89: =Manpower!N25 -> 12 | S89: =+Manpower!$B$49 -> Excavator | T89: =+Manpower!B50 -> 0 | U89: =+Manpower!B51 -> 1 | V89: =+Manpower!B52 -> 0
A90: =Schedule!A3 -> Schedule Statistics | F90: =Schedule!F3 -> Active Schedule Activities | L90: =+Manpower!P23 -> Carpenter | M90: =Manpower!P24 -> 4 | N90: =Manpower!P25 -> 4 | S90: =+Manpower!$D$49 -> Loader | T90: =+Manpower!D50 -> 0 | U90: =+Manpower!D51 -> 2 | V90: =+Manpower!D52 -> 0 | W90: Major Quantity Trackers
A91: =Schedule!A4 -> Total Act. | B91: =Schedule!B4 -> Not Started | C91: =Schedule!C4 -> In Progress | D91: =Schedule!D4 -> Completed | E91: =Schedule!E4 -> % | F91: =Schedule!F4 -> Active | G91: =Schedule!G4 -> Ahead | H91: =Schedule!H4 -> On | ... K91: =Schedule!K4 -> 0 | L91: =+Manpower!R23 -> Plumber | M91: =+Manpower!R24 -> 3 | N91: =Manpower!R25 -> 4 | S91: =+Manpower!$F$49 -> Dozer | T91: =+Manpower!F50 -> 0 | U91: =+Manpower!F51 -> 0 | V91: =+Manpower!F52 -> 0 | W91: BOQ N0. | X91: Item Description | AC91: Total Qty | AD91: Measu Unit | AE91: Plan to Date | AF91: Act to Date | AG91: Remaining | AH91: Variance
A92: =Schedule!A5 -> 902 | B92: =Schedule!B5 -> 9 | C92: =Schedule!C5 -> 40 | D92: =Schedule!D5 -> 854 | E92: =Schedule!E5 -> 0.94678492 | F92: =Schedule!F5 -> 40 | G92: =Schedule!G5 -> 29 | H92: =Schedule!H5 -> 14 | ... J92: =Schedule!J5 -> 28 | L92: =+Manpower!T23 -> Operator | M92: =Manpower!T24 -> 0 | N92: =Manpower!T25 -> 13 | S92: =+Manpower!$H$49 -> Dumper | T92: =+Manpower!H50 -> 0 | U92: =+Manpower!H51 -> 2 | V92: =+Manpower!H52 -> 0 | W92: ='Major Quantities'!A2 -> 2.1.1 | X92: ='Major Quantities'!B2 -> Excavation | AC92: ='Major Quantities'!C2 -> 1503 | AD92: ='Major Quantities'!D2 -> M3 | AE92: ='Major Quantities'!E2 -> 1503 | AF92: ='Major Quantities'!F2 -> 629.42 | AG92: ='Major Quantities'!G2 -> 873.58 | AH92: ='Major Quantities'!H2 -> 873.58
A93: =Schedule!A6 -> Critical Path Activities | D93: =Schedule!D6 -> Free Float Management (Total) | H93: =Schedule!H6 -> Failed Start Activities | L93: =+Manpower!V23 -> Steel Fixer | M93: =+Manpower!V24 -> 4 | N93: =+Manpower!V25 -> 4 | S93: =+Manpower!$J$49 -> Crane | T93: =+Manpower!J50 -> 0 | U93: =+Manpower!J51 -> 1 | V93: =+Manpower!J52 -> 0 | W93: ='Major Quantities'!A3 -> 2.1.3 | X93: ='Major Quantities'!B3 -> Backfilling | AC93: ='Major Quantities'!C3 -> 20258.76 | AD93: ='Major Quantities'!D3 -> M3 | AE93: ='Major Quantities'!E3 -> 20258.76 | AF93: ='Major Quantities'!F3 -> 14724.77 | AG93: ='Major Quantities'!G3 -> 5533.99 | AH93: ='Major Quantities'!H3 -> 5533.99
D94: =Schedule!D7 -> Greater Than 14 Days | F94: =Schedule!F7 -> Less Than 14 Days | L94: =+Manpower!X23 -> Mason | M94: =+Manpower!X24 -> 2 | N94: =+Manpower!X25 -> 2 | S94: =+Manpower!$L$49 -> Grader | T94: =+Manpower!L50 -> 0 | U94: =+Manpower!L51 -> 1 | V94: =+Manpower!L52 -> 0 | W94: ='Major Quantities'!A4 -> 0 | X94: ='Major Quantities'!B4 -> 0 | AC94: ='Major Quantities'!C4 -> 0 | AD94: ='Major Quantities'!D4 -> 0 | AE94: ='Major Quantities'!E4 -> 0 | AF94: ='Major Quantities'!F4 -> 0 | AG94: ='Major Quantities'!G4 -> 0 | AH94: ='Major Quantities'!H4 -> 0
A95: =Schedule!A8 -> Last Week | B95: =Schedule!B8 -> This Week | C95: =Schedule!C8 -> Diff | D95: =Schedule!D8 -> Last Week | E95: =Schedule!E8 -> This Week | F95: =Schedule!F8 -> Last Week | G95: =Schedule!G8 -> This Week | H95: =Schedule!H8 -> Last Week | ... K95: =Schedule!K8 -> 0 | L95: =+Manpower!Z23 -> Others | M95: =+Manpower!Z24 -> 11 | N95: =+Manpower!Z25 -> 19 | S95: =+Manpower!$N$49 -> Other | T95: =+Manpower!N50 -> 0 | U95: =+Manpower!N51 -> 6 | V95: =+Manpower!N52 -> 0 | W95: ='Major Quantities'!A5 -> 0 | X95: ='Major Quantities'!B5 -> 0 | AC95: ='Major Quantities'!C5 -> 0 | AD95: ='Major Quantities'!D5 -> 0 | AE95: ='Major Quantities'!E5 -> 0 | AF95: ='Major Quantities'!F5 -> 0 | AG95: ='Major Quantities'!G5 -> 0 | AH95: ='Major Quantities'!H5 -> 0
A96: =Schedule!A9 -> 12 | B96: =Schedule!B9 -> 2 | C96: =Schedule!C9 -> 10 | D96: =Schedule!D9 -> 41 | E96: =Schedule!E9 -> 41 | F96: =Schedule!F9 -> -80 | G96: =Schedule!G9 -> -36 | H96: =Schedule!H9 -> 11 | ... J96: =Schedule!J9 -> 1 | L96: Total | M96: =SUM(M89:M95) -> 34 | N96: =SUM(N89:N95) -> 58 | S96: Total | T96: =SUM(T89:T95) -> 0 | U96: =SUM(U89:U95) -> 13 | V96: =SUM(V89:V95) -> 0 | W96: ='Major Quantities'!A6 -> 0 | X96: ='Major Quantities'!B6 -> 0 | AC96: ='Major Quantities'!C6 -> 0 | AD96: ='Major Quantities'!D6 -> 0 | AE96: ='Major Quantities'!E6 -> 0 | AF96: ='Major Quantities'!F6 -> 0 | AG96: ='Major Quantities'!G6 -> 0 | AH96: ='Major Quantities'!H6 -> 0
A97: Weekly Prgoress Photos | Q97: Top Issues and Risks
A98: ='Weekly Photos'!B23 -> Installation of Exaust Fan for Building 2 | F98: ='Weekly Photos'!L23 -> Installation of Epoxy Paint - Building 2 | L98: ='Weekly Photos'!B4 -> Commsission of Panel Board for Building 2 | Q98: Top 5 Issues
Q99: Issue No | R99: Date Identified | S99: Issue Description | W99: Responsible | X99: Action Taken | AA99: Mitigation | AF99: Current Status | AG99: Expected/Actual Closure | AH99: Duration Elapsed
Q100: =IF(+Issues!B11="","",+Issues!B11) -> 1 | R100: =IF(+Issues!C11="","",+Issues!C11) -> 14/06/2026 | S100: =IF(+Issues!D11="","",+Issues!D11) -> Workers at height during lifting operations without proper coordination. | W100: =IF(+Issues!E11="","",+Issues!E11) -> Contractor | X100: =IF(+Issues!F11="","",+Issues!F11) -> Work sequence revised, lifting and work-at-height activities separated, supervision increased. | AF100: =IF(+Issues!H11="","",+Issues!H11) -> Closed | AG100: =IF(+Issues!I11="","",+Issues!I11) -> 14/06/2026 | AH100: =IF(+Issues!J11="","",+Issues!J11) -> 0 days
Q101: =IF(+Issues!B12="","",+Issues!B12) -> 2 | R101: =IF(+Issues!C12="","",+Issues!C12) -> 14/06/2026 | S101: =IF(+Issues!D12="","",+Issues!D12) -> Workers were exposed to suspended load during lifting operations due to inadequate barricading and unsafe work positioning. | W101: =IF(+Issues!E12="","",+Issues!E12) -> Contractor | X101: =IF(+Issues!F12="","",+Issues!F12) -> Lifting activity stopped, exclusion zone established, barricades installed, workers relocated from the danger area, toolbox talk conducted, and tag lines provided. | AF101: =IF(+Issues!H12="","",+Issues!H12) -> Closed | AG101: =IF(+Issues!I12="","",+Issues!I12) -> 14/06/2026 | AH101: =IF(+Issues!J12="","",+Issues!J12) -> 0 days
Q102: =IF(+Issues!B13="","",+Issues!B13) -> 3 | R102: =IF(+Issues!C13="","",+Issues!C13) -> 14/06/2026 | S102: =IF(+Issues!D13="","",+Issues!D13) -> Lack of proper isolation of lifting area. | W102: =IF(+Issues!E13="","",+Issues!E13) -> Contractor | X102: =IF(+Issues!F13="","",+Issues!F13) -> Barricades and warning signs installed, access restricted to authorized personnel only. | AF102: =IF(+Issues!H13="","",+Issues!H13) -> Closed | AG102: =IF(+Issues!I13="","",+Issues!I13) -> 14/06/2026 | AH102: =IF(+Issues!J13="","",+Issues!J13) -> 0 days
Q103: =IF(+Issues!B14="","",+Issues!B14) -> 4 | R103: =IF(+Issues!C14="","",+Issues!C14) -> 29-06-2026 | S103: =IF(+Issues!D14="","",+Issues!D14) -> Poor House keeping obsered in work zone area | W103: =IF(+Issues!E14="","",+Issues!E14) -> Contractor | X103: =IF(+Issues!F14="","",+Issues!F14) -> Site house keeping team has been instruted to clean area immediately and maintain daily monitoring | AF103: =IF(+Issues!H14="","",+Issues!H14) -> Open | AG103: =IF(+Issues!I14="","",+Issues!I14) -> 46287 | AH103: =IF(+Issues!J14="","",+Issues!J14)
Q104: =IF(+Issues!B15="","",+Issues!B15) -> 5 | R104: =IF(+Issues!C15="","",+Issues!C15) | S104: =IF(+Issues!D15="","",+Issues!D15) | W104: =IF(+Issues!E15="","",+Issues!E15) | X104: =IF(+Issues!F15="","",+Issues!F15) | AF104: =IF(+Issues!H15="","",+Issues!H15) | AG104: =IF(+Issues!I15="","",+Issues!I15) | AH104: =IF(+Issues!J15="","",+Issues!J15)

Sheet General Information
A1: Weekly Progress Report - Construction Projects | K1: Data Date | L1: 46286
A2: Contract General Information
A3: Project Name | C3: Factories Low-process Unit (HAFR Al Batin)
A4: Project ID | C4: HFR1-05-03
A5: Contractor | C5: SOROH AL KHAIR CONTRACTING CO.
A6: Consultant | C6: EGIS
A7: Stage | C7: Construction
A8: Status | C8: Active
A9: Modon PM | C9: Eng. Mohammed Al Essa
A11: Key Dates
A12: Contract Award Date | C12: =Milestones!C4 -> 45945
A13: Contract Sign Date | C13: =Milestones!C5 -> 45977
A14: Site Handover Date | C14: =Milestones!C6 -> 45988
A15: Original Completion | C15: =Milestones!C15 -> 46291
A16: Contract Award Date (Hijri) | C16: =C12 -> 45945
A17: Contract Sign Date (Hijri) | C17: =C13 -> 45977
A18: Site Handover Date (Hijri) | C18: =C14 -> 45988
A19: Original Completion (Hijri) | C19: =C15 -> 46291
A20: Revised Completion Date | C20: =Milestones!C15 -> 46291
A21: Committed Completion Date | C21: =Milestones!E14 -> 46324
A22: Forecast Completion | C22: =Milestones!E15 -> 46333
A23: Variance | C23: =C20-C22 -> -42
A25: Key Project Submittals | C25: Submission Date | D25: Days taken to approve orginal plan from site handover date
A26: Quality Plan submission | C26: 46032 | D26: =C27-C14 -> 118
A27: Quality Plan approval | C27: 46106
A28: Quality Plan Last Update | C28: 46106
A30: Safety Plan submission | C30: 46021 | D30: =C31-C14 -> 299
A31: Safety Plan approval | C31: =TODAY() -> 46287
A32: Safety Plan Last Update
A34: Risk Management Plan submission | C34: 46021 | D34: =C35-C14 -> 299
A35: Risk Management Plan approval | C35: =TODAY() -> 46287
A36: Risk Management Plan Last Update
A38: Baseline Schedule submission | C38: 46020 | D38: =C38-C14 -> 32
A39: Baseline Schedule approval | C39: 46088
A40: No of Schedule Versions | C40: 2
A41: Last Recovery Schedule Approval Date | C41: 46088
A43: BOQ submission | C43: 46023 | D43: =C43-C14 -> 35
A44: BOQ approval | C44: 46158
A45: No of Approved Version of BOQ | C45: 0
A47: Construction Plan submission | C47: =TODAY() -> 46287 | D47: =C47-C14 -> 299
A48: Construction Plan Approval

Sheet Progress
A1: Project Scope Statement | B1: The Project scope of work to construct a Factories of low process unit (Hafr Al Batin) industrial city that refer to specific tasks and activities involved in a project. This typically includes activities such as site preparation, Excavation, Foundation work, Structural construction work, Installation of utilities, Finishing works, Electrical Work, Mechanical Works and Landscaping. The scope outlines what will be done and by whom and within the planned timeframe. | S1: ='General Information'!$K$1 -> Data Date | T1: ='General Information'!L1 -> 46286
A4: Earned Value Progress (SAR) | K4: Physical Progress (Effort)
A5: WBS | C5: BOQ Value (SAR) | D5: % Wt. | E5: Weekly (SAR) | H5: To Date (SAR) | K5: Budgeted | L5: % Wt. | M5: Weekly Physical Progress | O5: To Date Physical Progress
E6: Planned | F6: Earned | G6: Original Plan | H6: Planned | I6: Earned | K6: (Manhours) | M6: Planned | N6: Earned | O6: Planned | P6: Earned
A7: Project Milestones | C7: 0 | D7: =IF(ISBLANK(C7),"",C7/$C$23) -> 0 | E7: 0 | F7: 0 | G7: 0 | H7: 0 | I7: 0 | K7: 0 | L7: =IF(ISBLANK(K7),"",K7/$K$23) -> 0 | M7: 0 | N7: 0 | O7: 0 | P7: 0
A8: Mobilization | C8: 0 | D8: =IF(ISBLANK(C8),"",C8/$C$23) -> 0 | E8: 0 | F8: 0 | G8: 0 | H8: 0 | I8: 0 | K8: 4400 | L8: =IF(ISBLANK(K8),"",K8/$K$23) -> 0.030017738 | M8: 0 | O8: 4400 | P8: 4400
A9: Engineering Phase | B9: premilinary submittals | C9: 494865 | D9: =IF(ISBLANK(C9),"",C9/$C$23) -> 0.029997534 | G9: 494865 | H9: 494865 | I9: 494865 | K9: 7321 | L9: =IF(ISBLANK(K9),"",K9/$K$23) -> 0.049945422 | M9: 0 | O9: 7321 | P9: 7321
A10: Procurment | B10: premilinary Approve | C10: 3299371 | D10: =IF(ISBLANK(C10),"",C10/$C$23) -> 0.19999999 | F10: 10324.7 | G10: 3299371 | H10: 3299371 | I10: 3299371 | K10: 17626 | L10: =IF(ISBLANK(K10),"",K10/$K$23) -> 0.12024833 | N10: 74 | O10: 17626 | P10: 17626
A11: Construction phase | C11: 11052936 | D11: =IF(ISBLANK(C11),"",C11/$C$23) -> 0.67000257 | E11: 52113.6 | F11: 144090.88 | G11: 11052936 | H11: 11052936 | I11: 10978372 | K11: 109913 | L11: =IF(ISBLANK(K11),"",K11/$K$23) -> 0.74984991 | M11: 244 | N11: 2590 | O11: 109832 | P11: 108012
A12: site general works | C12: 1298122 | D12: =IF(ISBLANK(C12),"",C12/$C$23) -> 0.078689057 | H12: 1298122 | I12: 1298122 | K12: 5423 | L12: =IF(ISBLANK(K12),"",K12/$K$23) -> 0.036996862 | O12: 5423 | P12: 5423
A13: Hunger -1 | C13: 3846587.2 | D13: =IF(ISBLANK(C13),"",C13/$C$23) -> 0.23317093 | E13: 52113.6 | F13: 33514.57 | H13: 3846587.2 | I13: 3832084.2 | K13: 23347 | L13: =IF(ISBLANK(K13),"",K13/$K$23) -> 0.15927821 | M13: 157 | N13: 320 | O13: 23295 | P13: 23137
A14: Hunger-2 | C14: 3851109 | D14: =IF(ISBLANK(C14),"",C14/$C$23) -> 0.23344503 | F14: 33277.93 | H14: 3851109 | I14: 3836609.7 | K14: 24765 | L14: =IF(ISBLANK(K14),"",K14/$K$23) -> 0.16895211 | M14: 88 | N14: 350 | O14: 24736 | P14: 24529
A15: Sephtic Tank | C15: 149552.06 | D15: =IF(ISBLANK(C15),"",C15/$C$23) -> 0.0090654887 | H15: 149552.06 | I15: 149552.06 | K15: 7817 | L15: =IF(ISBLANK(K15),"",K15/$K$23) -> 0.05332924 | O15: 7817 | P15: 7817
A16: Mosque -elec room-Toilets Works | C16: 396377.89 | D16: =IF(ISBLANK(C16),"",C16/$C$23) -> 0.024027481 | F16: 20068.17 | H16: 396377.89 | I16: 386130.49 | K16: 15308 | L16: =IF(ISBLANK(K16),"",K16/$K$23) -> 0.10443444 | N16: 671 | O16: 15308 | P16: 14842
A17: GRB Tank | C17: 163749.6 | D17: =IF(ISBLANK(C17),"",C17/$C$23) -> 0.0099261096 | H17: 163749.6 | I17: 163749.6 | K17: 9922 | L17: =IF(ISBLANK(K17),"",K17/$K$23) -> 0.067689999 | O17: 9922 | P17: 9922
A18: Pump room | C18: 389712.84 | D18: =IF(ISBLANK(C18),"",C18/$C$23) -> 0.023623462 | F18: 2664.93 | H18: 389712.84 | I18: 387774.89 | K18: 7698 | L18: =IF(ISBLANK(K18),"",K18/$K$23) -> 0.052517397 | N18: 192 | O18: 7698 | P18: 7313
A19: External WORKS-MEP | C19: 581705.66 | D19: =IF(ISBLANK(C19),"",C19/$C$23) -> 0.035261608 | F19: 3195.27 | H19: 581705.66 | I19: 570319.85 | K19: 6008 | L19: =IF(ISBLANK(K19),"",K19/$K$23) -> 0.040987856 | N19: 7 | O19: 6008 | P19: 5985
A20: External Works landscape | C20: 376019.58 | D20: =IF(ISBLANK(C20),"",C20/$C$23) -> 0.022793409 | F20: 51370.56 | G20: 0 | H20: 376019.58 | I20: 354028.77 | K20: 9626 | L20: =IF(ISBLANK(K20),"",K20/$K$23) -> 0.065670624 | N20: 1050 | O20: 9626 | P20: 9045
A21: Testing and comissiong | C21: 1649684 | D21: =IF(ISBLANK(C21),"",C21/$C$23) -> 0.099999904 | E21: 259325.32 | F21: 41242.1 | G21: 1574698.4 | H21: 1574698.4 | I21: 1422852.4 | K21: 7320 | L21: =IF(ISBLANK(K21),"",K21/$K$23) -> 0.0499386 | M21: 1150 | N21: 183 | O21: 6987 | P21: 6314
A22: Close Out | C22: 0 | D22: =IF(ISBLANK(C22),"",C22/$C$23) -> 0 | E22: 0 | F22: 0 | G22: 0 | H22: 0 | I22: 0 | K22: 0 | L22: =IF(ISBLANK(K22),"",K22/$K$23) -> 0 | M22: 0 | N22: 0 | O22: 0 | P22: 0
B23: Total | C23: =SUM(C7:C11,C21,C22) -> 16496856 | D23: =SUM(D7:D11,D21,D22) -> 1 | E23: =SUM(E7:E11,E21,E22) -> 311438.92 | F23: =SUM(F7:F11,F21,F22) -> 195657.68 | G23: =SUM(G7:G11,G21,G22) -> 16421870 | H23: =SUM(H7:H11,H21,H22) -> 16421870 | I23: =SUM(I7:I11,I21,I22) -> 16195460 | K23: =SUM(K7:K11,K21,K22) -> 146580 | L23: =SUM(L7:L11,L21,L22) -> 1 | M23: =SUM(M7:M11,M21,M22) -> 1394 | N23: =SUM(N7:N11,N21,N22) -> 2847 | O23: =SUM(O7:O11,O21,O22) -> 146166 | P23: =SUM(P7:P11,P21,P22) -> 143673
E24: =E23/$C$23 -> 0.018878683 | F24: =F23/$C$23 -> 0.011860301 | G24: =G23/$C$23 -> 0.99545455 | H24: =H23/$C$23 -> 0.99545455 | I24: =I23/$C$23 -> 0.98173011 | M24: =M23/$K$23 -> 0.0095101651 | N24: =N23/$K$23 -> 0.019422841 | O24: =O23/$K$23 -> 0.9971756 | P24: =P23/$K$23 -> 0.98016783
M28: `

Sheet Weekly Photos
B1: Date | C1: ='Weekly Progress Report'!AG1 -> 46286
B4: Commsission of Panel Board for Building 2 | L4: Installation of Water draiange from roof top
B23: Installation of Exaust Fan for Building 2 | L23: Installation of Epoxy Paint - Building 2
B42: Installation of Traffic Signs | L42: Installation of Road Markings Work
B60: Installation of Cladding for Building 2 | L60: Asphlat work 2nd layer for Road Work

Sheet FIR Summary
A2: Project Name | D2: Factories Low-process Unit (HAFR Al Batin)
A3: Project ID | D3: HFR1-05-03 | E3: Project Budget | G3: 16496856
A4: Total FIR Approved Value (Cumulative) | D4: ='FIR from Begining up to date '!K328 -> 11743680 | E4: Remaining FIRs Value (Cumulative) | G4: =G3-D4 -> 4753175.8
A5: Date Period | D5: 46279 | E5: To | G5: =D5+7 -> 46286
A7: BOQ Item # | B7: BOQ Description | C7: FIR / DATE | D7: FIR # | E7: FIR Description | F7: Status | G7: Unit Rate | H7: Current Period Quantity | I7: Progress (%) | J7: Total (SAR) | K7: Remarks
A9: 2.2.4 | B9: Supply and execute subgrade material up to the full width of the road as per specifications and drawings | C9: 46253 | D9: HFR1-05-003-SAK-TS9-1FIR-SUV-0144-00 | E9: Supply and execute subgrade material Layer-2 (15cm Sub Base), as per highlighted drawing. | F9: Approved | G9: 66 | H9: 1047.6555 | I9: 1 | J9: 69145.263
A10: 5.1 | B10: Supply and install steel ladder with safety cage including all necessary fixings, fixtures, painting all as per drawings and specifications. (Height = 5.5m) | D10: HFR1-05-003-SAK-TS9-1-FIR- ARC-0074-00 | E10: Supply and install steel ladder with safety cage including all necessary fixings, fixtures. | F10: Approved | G10: 5940 | H10: 2 | I10: 1 | J10: 11880
A11: 8.1.1 | B11: Supply and install (D6) 3000*3500mm galvanized steel heavy duty industrial isolated type roll up shutter door finished with polyurethane coating, with automatic and manual control system, as per manufacturer specification and approved by the Client, complete with all accessories and fittings, and as per door schedule and specifications | D11: HFR1-05-003-SAK-TS9-1-FIR-ARC-0122-00 | F11: Approved | G11: 15510 | H11: 24 | I11: 0.35 | J11: 130284
A12: 8.1.2 | B12: Supply and install fire rated 45 min. (D5) 1000*2200mm single leaf steel door with door construction type C with hardware set type HW2 paint finish as per manufacturer detail and approved by the Client with complete accessories as per door schedule, drawings and specification | D12: HFR1-05-003-SAK-TS9-1-FIR-ARC-0123-00 | F12: Approved | G12: 2750 | H12: 24 | I12: 0.35 | J12: 23100
A13: 8.1.3 | B13: Supply and install (D2) 1000*2200 mm single leaf galvanized steel door with door construction type B with hardware set type HW1 paint finish as per manufacturer detail and approved by the Client with complete accessories as per door/window schedule and as per drawings and specification. | C13: 46254 | D13: HFR1-05-003-SAK-TS9-1-FIR- ARC-0120-00 | E13: Supply and install (D2) 1000*2200 mm single leaf galvanized steel door with door construction type B with hardware set type HW1 paint finish at Building-1 (axis A-N/1x3), as per highlighted drawing. | F13: Approved | G13: 3355 | H13: 2 | I13: 1 | J13: 6710
A14: 8.1.4 | B14: Supply and install (D3) 800*2200 mm single leaf semi solid wood door with door construction type B with hardware set type HW1 paint finish as per manufacturer detail and approved by the Client with complete accessories as per door/window schedule and as per drawings and specification. | C14: 46254 | D14: HFR1-05-003-SAK-TS9-1-FIR- ARC-0121-00 | E14: Supply and install (D3) 800*2200 mm single leaf semi solid wood door with door construction type B with hardware set type HW1 paint finish at Building-1 (axis A-N/1x3), as per highlighted drawing. | F14: Approved | G14: 2896 | H14: 2 | I14: 1 | J14: 5792
A15: 8.1.4 | B15: Supply and install (D3) 800*2200 mm single leaf semi solid wood door with door construction type B with hardware set type HW1 paint finish as per manufacturer detail and approved by the Client with complete accessories as per door/window schedule and as per drawings and specification. | C15: 46254 | D15: HFR1-05-003-SAK-TS9-1-FIR- ARC-0119-00 | E15: Supply and install (D3) 800*2200 mm single leaf semi solid wood door with door construction type B with hardware set type HW1 paint finish at Building-2 (axis A-N/1x3), as per highlighted drawing. | F15: Approved | G15: 2896 | H15: 2 | I15: 1 | J15: 5792
A16: 9.2.8 | B16: Supply and install phenolic partitions with doors for toilets including accessories, fixations, fittings, and all the required works as shown in the drawings and specification with approved quality by the Client | D16: HFR1-05-003-SAK-TS9-1-FIR- ARC-0116-00 | F16: Approved | G16: 660 | H16: 65 | I16: 1 | J16: 42900
J17: =IF(F17="Approved",G17*H17*I17,0) -> 0
J18: =IF(F18="Approved",G18*H18*I18,0) -> 0
J19: =IF(F19="Approved",G19*H19*I19,0) -> 0
J20: =IF(F20="Approved",G20*H20*I20,0) -> 0
J21: =IF(F21="Approved",G21*H21*I21,0) -> 0
J22: =IF(F22="Approved",G22*H22*I22,0) -> 0
J23: =IF(F23="Approved",G23*H23*I23,0) -> 0
J24: =IF(F24="Approved",G24*H24*I24,0) -> 0
J25: =IF(F25="Approved",G25*H25*I25,0) -> 0
J26: =IF(F26="Approved",G26*H26*I26,0) -> 0
J27: =IF(F27="Approved",G27*H27*I27,0) -> 0
J28: =IF(F28="Approved",G28*H28*I28,0) -> 0
... J34: =IF(F34="Approved",G34*H34*I34,0) -> 0
C43: Total Excuted Amount | J43: =SUM(J9:J42) -> 295603.26

Sheet Quality
B2: QC OBSERVATIONS CHECKLIST
BB4: 46069
B6: Project No. | E6: HFR1-05-03 | K6: OBS No. | O6: 14 | U6: Inspection Day: | X6: 46286
B8: Project | E8: Factories Low-process Unit (HAFR Al Batin) | O8: Contractor: Consultant: | U8: SOROH AL KHAIR CONTRACTING CO. EGIS
B10: 4 | D10: Excellent | G10: Quality Management System is being practiced and applies to MODON System | Z10: 90 - 100 | AB10: QC Overall Score | AC10: =Q49 -> 0.79137931 | AN10: =SUM(Z10:Z13) -> 0 | AO10: 100 | AP10: 0.22883295
B11: 3 | D11: Good | G11: Evidence of compliance with plans and procedures. | Z11: 80 - 89 | AN11: =SUM(Y10:Y14) -> 0 | AO11: 89 | AP11: 0.20366133
B12: 2 | D12: Average | G12: Indication level of compliance with standards but there is room for improvement | Z12: 70 - 79 | AO12: 79 | AP12: 0.18077803
B13: 1 | D13: Improve | G13: Quality and Control is NOT being managed effectively. Needs Improvement | Z13: ≤ 69 | AO13: 69 | AP13: 0.15789474
B14: 0 | D14: N/A | G14: Item was not applicable or this item was not reviewed during the inspection. | Z14: Zero | AO14: 100 | AP14: 0.22883295
B16: No. | C16: Topic | K16: E (4) | L16: G (3) | M16: A (2) | N16: I (1) | O16: N/A (0) | Q16: No. | R16: Topic | Z16: E (4) | AA16: G (3) | AB16: A (2) | AC16: I (1) | AD16: N/A (0) | AO16: =SUM(AO10:AO15) -> 437
K17: 1 | L17: 0.89 | M17: 0.79 | N17: 0.69 | O17: 1 | Z17: 1 | AA17: 0.89 | AB17: 0.79 | AC17: 0.69 | AD17: 1 | AF17: =SUM(AF18:AG46)/COUNT(AF18:AG46) -> 0.79137931
B18: 1 | C18: Control of Access to Site/Office | L18: 0 | M18: 1 | N18: 0 | Q18: 30 | R18: QC of Excavation | Z18: 0 | AA18: 0 | AB18: 0 | AC18: 1 | AD18: 0 | AF18: =SUMPRODUCT($K$17:$O$17,K18:O18) -> 0.79 | AG18: =SUMPRODUCT($Z$17:$AD$17,Z18:AD18) -> 0.69 | AV18: Item Count | AW18: Score | AX18: Distributtion
B19: 2 | C19: Document Control Administration | K19: 0 | L19: 0 | M19: 0 | N19: 1 | Q19: 31 | R19: QC of Roads/Round about | Z19: 0 | AA19: 0 | AC19: 1 | AD19: 0 | AF19: =SUMPRODUCT($K$17:$O$17,K19:O19) -> 0.69 | AG19: =SUMPRODUCT($Z$17:$AD$17,Z19:AD19) -> 0.69 | AX19: Overall | AY19: Relevant
B20: 3 | C20: Project Documents and Progress | K20: 0 | L20: 0 | M20: 0 | N20: 1 | Q20: 32 | R20: QC of Interlock & Curbstone | Z20: 0 | AC20: 1 | AD20: 0 | AF20: =SUMPRODUCT($K$17:$O$17,K20:O20) -> 0.69 | AG20: =SUMPRODUCT($Z$17:$AD$17,Z20:AD20) -> 0.69 | AM20: 4 | AN20: =58 -> 58 | AO20: counts | AQ20: 4 | AR20: Excellent | AV20: =SUM(Z18:Z46,K18:K46) -> 0 | AW20: =AQ20*AV20 -> 0 | AX20: =AV20/$AV$25 -> 0 | AY20: =AV20/SUM($AV$20:$AV$23) -> 0
B21: 4 | C21: Contractor's Quality Plan/CM (Updated and Reviewed) | K21: 0 | L21: 0 | M21: 1 | Q21: 33 | R21: Layers/Backfilling Sampling | Z21: 0 | AA21: 0 | AB21: 0 | AC21: 1 | AD21: 0 | AF21: =SUMPRODUCT($K$17:$O$17,K21:O21) -> 0.79 | AG21: =SUMPRODUCT($Z$17:$AD$17,Z21:AD21) -> 0.69 | AM21: 3 | AN21: =58 -> 58 | AO21: counts | AQ21: 3 | AR21: Good | AV21: =SUM(L18:L46,AA18:AA46) -> 0 | AW21: =AQ21*AV21 -> 0 | AX21: =AV21/$AV$25 -> 0 | AY21: =AV21/SUM($AV$20:$AV$23) -> 0
B22: 5 | C22: MS Log and Paperwork | K22: 0 | L22: 0 | M22: 0 | N22: 1 | Q22: 34 | R22: Pump Stations Units | Z22: 0 | AA22: 0 | AB22: 0 | AC22: 1 | AD22: 0 | AF22: =SUMPRODUCT($K$17:$O$17,K22:O22) -> 0.69 | AG22: =SUMPRODUCT($Z$17:$AD$17,Z22:AD22) -> 0.69 | AM22: 2 | AN22: =58 -> 58 | AO22: counts | AQ22: 2 | AR22: Average | AV22: =SUM(M18:M46,AB18:AB46) -> 3 | AW22: =AQ22*AV22 -> 6 | AX22: =AV22/$AV$25 -> 0.051724138 | AY22: =AV22/SUM($AV$20:$AV$23) -> 0.075 | BC22: NB: Insert 1, or 0 in the required cell only.
B23: 6 | C23: RFI, FIR, & MIR Procedure | K23: 0 | L23: 0 | M23: 0 | N23: 1 | Q23: 35 | R23: Quality of Form Work | Z23: 0 | AA23: 0 | AB23: 0 | AC23: 1 | AD23: 0 | AF23: =SUMPRODUCT($K$17:$O$17,K23:O23) -> 0.69 | AG23: =SUMPRODUCT($Z$17:$AD$17,Z23:AD23) -> 0.69 | AM23: 1 | AN23: =58 -> 58 | AO23: counts | AQ23: 1 | AR23: Improve | AV23: =SUM(N18:N46,AC18:AC46) -> 37 | AW23: =AQ23*AV23 -> 37 | AX23: =AV23/$AV$25 -> 0.63793103 | AY23: =AV23/SUM($AV$20:$AV$23) -> 0.925
B24: 7 | C24: RFI, FIR, & MIR Inventory system | K24: 0 | L24: 0 | M24: 0 | N24: 1 | Q24: 36 | R24: Design Change List | AC24: 0 | AD24: 1 | AF24: =SUMPRODUCT($K$17:$O$17,K24:O24) -> 0.69 | AG24: =SUMPRODUCT($Z$17:$AD$17,Z24:AD24) -> 1 | AM24: 0 | AN24: =58 -> 58 | AO24: counts | AQ24: 0 | AR24: N/A | AV24: =SUM(O18:O46,AD18:AD46) -> 18 | AW24: =AQ24*AV24 -> 0 | AX24: =AV24/$AV$25 -> 0.31034483 | AY24: -
B25: 8 | C25: NCRs Control & Procedure | K25: 0 | L25: 0 | M25: 0 | N25: 1 | Q25: 37 | R25: Quality of Concrete Placing | Z25: 0 | AB25: 0 | AC25: 1 | AD25: 0 | AF25: =SUMPRODUCT($K$17:$O$17,K25:O25) -> 0.69 | AG25: =SUMPRODUCT($Z$17:$AD$17,Z25:AD25) -> 0.69 | AR25: Total | AV25: =SUM(AV20:AV24) -> 58 | AW25: =SUM(AW20:AW24) -> 43 | AX25: =SUM(AX20:AX24) -> 1 | AY25: =SUM(AY20:AY24) -> 1
B26: 9 | C26: NCR Log | K26: 0 | M26: 0 | N26: 1 | Q26: 38 | R26: Concrete Surface Finishing | Z26: 0 | AA26: 0 | AB26: 0 | AC26: 1 | AD26: 0 | AF26: =SUMPRODUCT($K$17:$O$17,K26:O26) -> 0.69 | AG26: =SUMPRODUCT($Z$17:$AD$17,Z26:AD26) -> 0.69
B27: 10 | C27: MODON Standard* | K27: 0 | L27: 0 | N27: 1 | Q27: 39 | R27: Pedestals/Columns/Beams Alignment | Z27: 0 | AA27: 0 | AB27: 0 | AC27: 1 | AD27: 0 | AF27: =SUMPRODUCT($K$17:$O$17,K27:O27) -> 0.69 | AG27: =SUMPRODUCT($Z$17:$AD$17,Z27:AD27) -> 0.69 | AV27: Maz Score Available: | AW27: =SUM(AV20:AV23)*AQ20 -> 160 | AX27: <- Excludes N/A items
B28: 11 | C28: Project Risk Plan/Management* | K28: 0 | L28: 0 | N28: 1 | Q28: 40 | R28: Siporex Lifting & Unloading | AB28: 0 | AD28: 1 | AF28: =SUMPRODUCT($K$17:$O$17,K28:O28) -> 0.69 | AG28: =SUMPRODUCT($Z$17:$AD$17,Z28:AD28) -> 1
B29: 12 | C29: Monthly Quality Reports* | K29: 0 | L29: 0 | M29: 0 | N29: 1 | Q29: 41 | R29: Siporex Quality Pre-installation | AB29: 0 | AD29: 1 | AF29: =SUMPRODUCT($K$17:$O$17,K29:O29) -> 0.69 | AG29: =SUMPRODUCT($Z$17:$AD$17,Z29:AD29) -> 1
B30: 13 | C30: ITP | K30: 0 | L30: 0 | M30: 1 | Q30: 42 | R30: Siporex Finishing Quality | Z30: 0 | AD30: 1 | AF30: =SUMPRODUCT($K$17:$O$17,K30:O30) -> 0.79 | AG30: =SUMPRODUCT($Z$17:$AD$17,Z30:AD30) -> 1 | AR30: Total Score | AW30: Percentage (%)
B31: 14 | C31: MODON Weekly Report | K31: 0 | L31: 0 | M31: 0 | N31: 1 | Q31: 43 | R31: Roads / Parking Markings | Z31: 0 | AA31: 0 | AD31: 1 | AF31: =SUMPRODUCT($K$17:$O$17,K31:O31) -> 0.69 | AG31: =SUMPRODUCT($Z$17:$AD$17,Z31:AD31) -> 1 | AN31: =MAX(AN20:AN24) -> 58 | AR31: =AW25 -> 43 | AW31: =SUM(100/AR33*AR31) -> 26.875 | AY31: %
B32: 15 | C32: Design Change Official Paperwork* | K32: 0 | O32: 1 | Q32: 44 | R32: QC of Finishing Outdoors | Z32: 0 | AA32: 0 | AD32: 1 | AF32: =SUMPRODUCT($K$17:$O$17,K32:O32) -> 1 | AG32: =SUMPRODUCT($Z$17:$AD$17,Z32:AD32) -> 1 | AR32: Max Score Available | BP32: 31
B33: 16 | C33: Design Change was Applied* | K33: 0 | O33: 1 | Q33: 45 | R33: Quality of Finishing Indoors | Z33: 0 | AC33: 1 | AD33: 0 | AF33: =SUMPRODUCT($K$17:$O$17,K33:O33) -> 1 | AG33: =SUMPRODUCT($Z$17:$AD$17,Z33:AD33) -> 0.69 | AR33: =AW27 -> 160 | BP33: 32
B34: 17 | C34: Material List | K34: 0 | M34: 0 | N34: 1 | Q34: 46 | R34: Stairs Quality | Z34: 0 | AD34: 1 | AF34: =SUMPRODUCT($K$17:$O$17,K34:O34) -> 0.69 | AG34: =SUMPRODUCT($Z$17:$AD$17,Z34:AD34) -> 1 | BP34: 33
B35: 18 | C35: Pending Material Status | K35: 0 | M35: 0 | N35: 1 | O35: 0 | Q35: 47 | R35: Tanks Method Statement Work | Z35: 0 | AD35: 1 | AF35: =SUMPRODUCT($K$17:$O$17,K35:O35) -> 0.69 | AG35: =SUMPRODUCT($Z$17:$AD$17,Z35:AD35) -> 1 | BP35: 34
B36: 19 | C36: Lifting Plan* | O36: 1 | Q36: 48 | R36: Electric Rooms | Z36: 0 | AD36: 1 | AF36: =SUMPRODUCT($K$17:$O$17,K36:O36) -> 1 | AG36: =SUMPRODUCT($Z$17:$AD$17,Z36:AD36) -> 1 | BP36: 35
B37: 20 | C37: DWG Log | L37: 0 | M37: 0 | N37: 1 | O37: 0 | Q37: 49 | R37: QC of MCC/ATS Plant Units | Z37: 0 | AD37: 1 | AF37: =SUMPRODUCT($K$17:$O$17,K37:O37) -> 0.69 | AG37: =SUMPRODUCT($Z$17:$AD$17,Z37:AD37) -> 1 | BP37: 36
B38: 21 | C38: Invoice Status | K38: 0 | L38: 0 | M38: 0 | N38: 1 | O38: 0 | Q38: 50 | R38: Qualified Subcontractor | Z38: 0 | AA38: 0 | AD38: 1 | AF38: =SUMPRODUCT($K$17:$O$17,K38:O38) -> 0.69 | AG38: =SUMPRODUCT($Z$17:$AD$17,Z38:AD38) -> 1 | BP38: 37
B39: 22 | C39: Site Handover Letter | K39: 0 | L39: 0 | O39: 1 | Q39: 51 | R39: Scaffold/Ladders/Slope/Bridge Compliance | Z39: 0 | AC39: 1 | AD39: 0 | AF39: =SUMPRODUCT($K$17:$O$17,K39:O39) -> 1 | AG39: =SUMPRODUCT($Z$17:$AD$17,Z39:AD39) -> 0.69 | BP39: 38
B40: 23 | C40: Material Testing Results & Certification | K40: 0 | M40: 0 | N40: 1 | Q40: 52 | R40: Protection Applied to Completed Work | AC40: 0 | AD40: 1 | AF40: =SUMPRODUCT($K$17:$O$17,K40:O40) -> 0.69 | AG40: =SUMPRODUCT($Z$17:$AD$17,Z40:AD40) -> 1
B41: 24 | C41: As Build Drawings Status* | K41: 0 | L41: 0 | O41: 1 | Q41: 53 | R41: Storage Management in/out Control | AA41: 0 | AC41: 1 | AD41: 0 | AF41: =SUMPRODUCT($K$17:$O$17,K41:O41) -> 1 | AG41: =SUMPRODUCT($Z$17:$AD$17,Z41:AD41) -> 0.69
B42: 25 | C42: Calibrated Lab Tools & Equipment | K42: 0 | L42: 0 | N42: 0 | O42: 1 | Q42: 54 | R42: Material Control | AA42: 0 | AB42: 0 | AC42: 1 | AD42: 0 | AF42: =SUMPRODUCT($K$17:$O$17,K42:O42) -> 1 | AG42: =SUMPRODUCT($Z$17:$AD$17,Z42:AD42) -> 0.69
B43: 26 | C43: Storage Inventory System | L43: 0 | M43: 0 | N43: 1 | Q43: 55 | R43: Manholes Storing and Quality | AA43: 0 | AC43: 1 | AD43: 0 | AF43: =SUMPRODUCT($K$17:$O$17,K43:O43) -> 0.69 | AG43: =SUMPRODUCT($Z$17:$AD$17,Z43:AD43) -> 0.69
B44: 27 | C44: Logistics Plan | M44: 0 | N44: 1 | Q44: 56 | R44: Reinforced Steel Quality | AA44: 0 | AC44: 1 | AD44: 0 | AF44: =SUMPRODUCT($K$17:$O$17,K44:O44) -> 0.69 | AG44: =SUMPRODUCT($Z$17:$AD$17,Z44:AD44) -> 0.69
B45: 28 | C45: Project Progress Planview | K45: 0 | M45: 0 | N45: 1 | O45: 0 | Q45: 57 | R45: Safety Overview | Z45: 0 | AB45: 0 | AC45: 1 | AD45: 0 | AF45: =SUMPRODUCT($K$17:$O$17,K45:O45) -> 0.69 | AG45: =SUMPRODUCT($Z$17:$AD$17,Z45:AD45) -> 0.69
B46: 29 | C46: Sufficient Number of QC Inspectors | K46: 0 | M46: 0 | N46: 1 | O46: 0 | Q46: 58 | R46: Waste Management Control | Z46: 0 | AB46: 0 | AC46: 1 | AD46: 0 | AF46: =SUMPRODUCT($K$17:$O$17,K46:O46) -> 0.69 | AG46: =SUMPRODUCT($Z$17:$AD$17,Z46:AD46) -> 0.69
O47: 0
I48: Score
M49: *QC % | Q49: =AF17 -> 0.79137931
B51: Prepared by: | G51: Abdul Majeed | Q51: Issued to PM: | V51: Eng.Mohammed Al Essa
B53: *QC Observations refer only to the practices and documentation observed at time of inspection. The responsibility of the CM and Contractor is to ensure that aspects of Quality are suitably managed. *Scores are a reflection of the general site conditions based upon the findings at the time of the walk through *If Applicable

Sheet Quality-Stat
A1: Quality Reports
A2: Item | C2: Issued | D2: Closed | E2: Pending | F2: Avg. Closing (Days) | G2: Pending
G3: 0-10 Days | H3: 11-20 Days | I3: 21-30 Days | J3: 31-60 Days | K3: > 60 Days
A5: Non Conforomance Report (NCR) | C5: 7 | D5: 7 | E5: 0 | F5: 0 | G5: 0 | H5: 0 | I5: 0 | J5: 0 | K5: 0
A6: Site Instruction (SI) | C6: 15 | D6: 15 | F6: 0 | G6: 0 | H6: 0 | I6: 0 | J6: 0 | K6: 0
A7: Material Inspection Report (MIR) | C7: 81 | D7: 65 | E7: 16 | F7: 0 | G7: 0 | H7: 0 | I7: 0 | J7: 0 | K7: 0
A8: Field Inspection Report (FIR) | C8: 727 | D8: 716 | E8: 11 | F8: 0 | G8: 0 | H8: 0 | I8: 0 | J8: 0 | K8: 0
A10: Shop Drawings
A11: Item Per WBS | D11: Total Planned | E11: Total Drawings Submitted | J11: Remaining Drawings | K11: Pending | L11: Total Submittals
E12: A | F12: B | G12: C | H12: D | I12: Approved | J12: with Designer | K12: Submittals With Consultant
A13: Civil /Roads | D13: 19 | E13: 2 | F13: 17 | I13: 19 | J13: 0 | L13: =E13+F13+G13+H13+K13 -> 19
A14: Structural | C14: Structural | D14: 129 | E14: 8 | F14: 121 | I14: 129 | L14: =E14+F14+G14+H14+K14 -> 129
A15: Architectural | C15: Architectural | D15: 37 | E15: 3 | F15: 34 | I15: 37 | J15: =D15-E15-F15-G15-H15 -> 0 | K15: 0 | L15: =E15+F15+G15+H15+K15 -> 37
A16: Mechanical | C16: Mechanical | D16: 41 | F16: 41 | I16: 41 | J16: =D16-E16-F16-G16-H16 -> 0 | K16: 0 | L16: =E16+F16+G16+H16+K16 -> 41
A17: Electrical | C17: Electrical | D17: 40 | E17: 0 | F17: 40 | H17: 0 | I17: 40 | J17: =D17-E17-F17-G17-H17 -> 0 | K17: 0 | L17: =E17+F17+G17+H17+K17 -> 40
A18: TOTAL | D18: =SUM(D13:D17) -> 266 | E18: =SUM(E13:E17) -> 13 | F18: =SUM(F13:F17) -> 253 | G18: =SUM(G13:G17) -> 0 | H18: =SUM(H13:H17) -> 0 | I18: =SUM(I13:I17) -> 266 | J18: =SUM(J13:J17) -> 0 | K18: =SUM(K13:K17) -> 0 | L18: =SUM(L13:L17) -> 266
A21: Material Approval
A22: Item Per WBS | D22: Total Planned | E22: Total Materials Submitted | J22: Remaining to approve | K22: Pending | L22: Total Submittals
E23: A | F23: B | G23: C | H23: D | I23: Approved | J23: with Designer | K23: Submittals With Consultant
A24: Civil / Roads | D24: 9 | F24: 9 | H24: 0 | I24: 9 | K24: 0 | L24: =SUM(E24:H24)+K24 -> 9
A25: Structural | C25: Structural | D25: 9 | E25: 0 | F25: 9 | G25: 0 | H25: 0 | I25: =SUM(E25:F25) -> 9 | L25: =SUM(E25:H25)+K25 -> 9
A26: Architectural | C26: Architectural | D26: 30 | E26: 1 | F26: 26 | G26: 0 | H26: 1 | I26: 26 | J26: 0 | K26: 2 | L26: =SUM(E26:H26)+K26 -> 30
A27: Mechanical | C27: Mechanical | D27: 20 | E27: 0 | F27: 20 | H27: 0 | I27: 20 | J27: =D27-I27 -> 0 | L27: =SUM(E27:H27)+K27 -> 20
A28: Electrical | C28: Electrical | D28: 18 | E28: 0 | F28: 18 | G28: 0 | H28: 0 | I28: =SUM(E28:F28) -> 18 | L28: =SUM(E28:H28)+K28 -> 18
A29: TOTAL | D29: =SUM(D24:D28) -> 86 | E29: =SUM(E24:E28) -> 1 | F29: =SUM(F24:F28) -> 82 | G29: =SUM(G24:G28) -> 0 | H29: =SUM(H24:H28) -> 1 | I29: =SUM(I24:I28) -> 82 | J29: =SUM(J24:J28) -> 0 | K29: =SUM(K24:K28) -> 2 | L29: =SUM(L24:L28) -> 86
A31: Procurement Summary
A32: Item Per WBS | D32: Total Materials Planned | E32: Total Number of P.O. | F32: Actual P.O. To Date | G32: Remaining P.O | H32: Actual Material on Site | I32: Remaining Materials | J32: Material Delivery Completion (Date)
E33: A | F33: B | G33: C | H33: D | I33: Processed
A34: Civil | D34: 9 | E34: 9 | F34: 9 | H34: 9 | I34: 0 | J34: 46284
A35: Structural | C35: Structural | D35: 9 | E35: 9 | F35: 9 | H35: 9 | I35: 0 | J35: 46147
A36: Architectural | C36: Architectural | D36: 22 | E36: 22 | F36: 22 | H36: 22 | I36: 0 | J36: 46284
A37: Mechanical | C37: Mechanical | D37: 28 | E37: 28 | F37: 28 | G37: 0 | H37: 28 | I37: 0 | J37: 46263
A38: Electrical | C38: Electrical | D38: 25 | E38: 25 | F38: 25 | H38: 25 | J38: 46263
A39: TOTAL | D39: =SUM(D34:D38) -> 93 | E39: =SUM(E34:E38) -> 93 | F39: =SUM(F34:F38) -> 93 | G39: =SUM(G34:G38) -> 0 | H39: =SUM(H34:H38) -> 93 | I39: =SUM(I34:I38) -> 0 | J39: =MAX(J34:J38) -> 46284
A41: Consultant Quality Inspections / Observations (Weekly Basis) | I41: Overall Average | J41: =AVERAGE(E43:E117) -> 0.78876667 | L41: Average Closing | M41: =AVERAGE(G43:G117) -> 1.4
A42: Week Number | B42: Date of Audit | C42: Date Issued | D42: Numbers Of Comments | E42: Quality Score | F42: Date Closed | G42: Closure Duration | I42: This Week Score | J42: =Quality!AC10 -> 0.79137931 | L42: Average Number of Comments Per Audit | M42: =AVERAGE(D43:D117) -> 1.3
A43: Week-1 | B43: 46083 | C43: 46064 | D43: 2 | E43: 0.802 | F43: 46074 | G43: =F43-C43 -> 10
A44: Week-2 | B44: 46090 | C44: 46077 | D44: 1 | E44: 0.802 | F44: 46081 | G44: =F44-C44 -> 4
A45: Week-3 | B45: 46097 | C45: 46083 | D45: 2 | E45: 0.802 | F45: 46084 | G45: =F45-C45 -> 1
A46: Week-4 | B46: 46104 | C46: 46095 | D46: 2 | E46: 0.802 | F46: 46098 | G46: =F46-C46 -> 3
A47: Week-5 | B47: 46111 | C47: 46106 | D47: 1 | E47: 0.802 | F47: 46112 | G47: =F47-C47 -> 6
A48: Week-6 | B48: 46118 | C48: 46118 | D48: 2 | E48: 0.802 | F48: 46119 | G48: =F48-C48 -> 1
A49: Week-7 | B49: 46125 | C49: 46121 | D49: 3 | E49: 0.802 | F49: 46121 | G49: =F49-C49 -> 0
A50: Week-8 | B50: 46131 | C50: 46131 | D50: 2 | E50: 0.783 | F50: 46131 | G50: =F50-C50 -> 0
A51: Week-9 | B51: 46139 | C51: 46138 | D51: 3 | E51: 0.783 | F51: 46138 | G51: =F51-C51 -> 0
A52: Week-10 | B52: 46146 | C52: 46146 | D52: 1 | E52: 0.783 | F52: 46146 | G52: =F52-C52 -> 0
A53: Week-11 | B53: 46153 | C53: 46152 | D53: 1 | E53: 0.783 | F53: 46153 | G53: =F53-C53 -> 1
A54: Week-12 | B54: 46160 | C54: 46158 | D54: 1 | E54: 0.783 | F54: 46160 | G54: =F54-C54 -> 2
... A72: Week-30 | B72: 46286 | C72: 46285 | D72: 1 | E72: 0.791 | F72: 46286 | G72: =F72-C72 -> 1
A73: Week-31
A74: Week-32
A75: Week-33
A76: Week-34
A77: Week-35
A78: Week-36
A79: Week-37
A80: Week-38
A81: Week-39
A82: Week-40
A83: Week-41
A84: Week-42
... A117: Week-75

Sheet HSE
B1: MODON HSE Site Inspection Report
B2: Date | E2: ='General Information'!L1 -> 46286 | L2: Inspected By: | U2: Engr Abdul Salam
B4: Project ID. | E4: HFR1-05-03 | L4: Report No. | P4: 5 | W4: MODON PM Name | Y4: ='[36]General Information'!C9 -> Eng. Mohammed Al Essa
B6: Project Name: | E6: Factories Low-process Unit (HAFR Al Batin) | L6: Contractor: | R6: ='[36]General Information'!C5 -> SAK | X6: Safety Performance | AA6: =IF(W29>0,3,IF(L29>6,3,IF(D29>0,2,1)*1)*1) -> 3 | AE6: =(((COUNTIF(L13:Q25,"1")+COUNTIF(AC13:AH25,"1"))*AR13)+(COUNTIF(L13:Q25,"2")+COUNTIF(AC13:AH25,"2"))*AR14+(COUNTIF(L13:Q25,"3")+COUNTIF(AC13:AH25,"3"))*AR15)/((COUNT(L13:Q25)+COUNT(AC13:AH25))*100) -> 0.78846154
B8: Inspections are a snapshot in time and refer only to the practices and documentation observed at the time of the Inspection. It remains the responsibility of the Consultant and Contractor to ensure that all aspects of Health & Safety are suitably managed.
B9: 1 | D9: Good Practice | H9: 2 | I9: Need Improvement | T9: 3 | U9: Fail (Life Threatening Activity) / Comliance with Plan & Procedures | X9: N/A | Y9: Atcitty Not Applicable for this Site Inspection Report
B11: No. | C11: Topic | K11: Wt. | L11: HSE Compliance | S11: No. | T11: Topic | AB11: Wt. | AC11: HSE Compliance
B13: 1 | C13: Access and Egress - (General access to site, segregated from vehicles, / Overhead protection, while entering into the building /Adequate lighting provided when dark or overnight work) | K13: 0.05 | L13: 1 | S13: 14 | T13: Work at Height - (PPE/Fall Protection(Same level, above and blow) / Training / Fall restraint / competency /Safe access & egress to and from work at height / Ladders / Openings (floor/shafts/Provision of emergency rescue) | AB13: 0.05 | AC13: 2 | AP13: 1 | AR13: 100 | AU13: 1
B14: 2 | C14: Traffic Management - (Loading/unloading/sheeting/temp. routes/speed/parking/competence) | K14: 0.03 | L14: 2 | S14: 15 | T14: Scaffolding - (Temp. Scaffolding Work-platform (All types) - qualified scaffolder / Inspection / Tagged / Safe Access/egress / PTW/Falsework & Formwork) | AB14: 0.04 | AC14: 2 | AP14: 2 | AR14: 75 | AU14: 2
B15: 3 | C15: Site Signage - (Project Notice Board & General Signage) | K15: 0.02 | L15: 1 | S15: 16 | T15: Mobile Elevated Work platform (MEWP) - (PTW/competence requirements/conditions/inspections/tagged/training/Full-body harness) | AB15: 0.04 | AC15: 2 | AP15: 3 | AR15: 0 | AU15: 3
B16: 4 | C16: PPE Compliance - (Use, storage, stock, handling & checks - Head, Foot, Eye, Hearing) | K16: 0.05 | L16: 2 | S16: 17 | T16: Excavation & Trenches - (PTW/Edge protection/buffer zone/Slope/Benching/Shoring/Geo-tech report/Atmospheric hazards/Acess&egress/Emergency management / MS&RA/H.E) | AB16: 0.03 | AC16: 2 | AU16: N/A
B17: 5 | C17: Housekeeping - (Material correctly stored/Rubbish cleaned & removed daily/slips & trips hazards) | K17: 0.03 | L17: 1 | S17: 18 | T17: Confined Space - (PTW/Training/competence/Emergency Management/MS & RA/Safe access/egress) | AB17: 0.05 | AC17: 2
B18: 6 | C18: Storage of Materials - (Transporting, storage, training and use - Combustible / Flammable / Hazardous substances (COSHH) | L18: 2 | S18: 19 | T18: Fire Protection - (Flammable/Oxy. LPG /Combustible separated/FE's/Flashback arrestor/Sparks & slags/Smoking area/PTW/Generators/MS & RA/Emergency Management) | AC18: 2 | AL18: Red | AM18: Serious injury or death (immediately)
B19: 7 | C19: Site Waste Management - (Hazardous waste /Combustible waste / Human waste / Construction waste - asphalt, cable, timber, paving roof sheeting tiles, plastic & bricks) | L19: 2 | S19: 20 | T19: Health & Welfare - (Adequate drinking water/shaded - eating & rest area/washing & sanitary facilities/Certified FA/FA Box & Stock/adequate toilets/Ambulance) | AC19: 2 | AL19: Yellow | AM19: Minor or near miss (3 days to comply)
B20: 8 | C20: Health Surveillance - (Expose to excessive noise/vibration/dust/silica/CO/cement/radiation/extreme weather condition) | K20: 0.03 | L20: 2 | S20: 21 | T20: Environmental Incident Measures - (Spill/ Leakage / Concrete wash / vehicle & eqpts. wash / waste disposal/Sewers and drains/emissions/Emergency Management/Training/site run-off water) | AB20: 0.05 | AC20: 2 | AL20: Green | AM20: No issues
B21: 9 | C21: Electrical Safety - (Electrical qualified /RCD/GFCI/Industrial Cocket/LOTO/Cable-overhung or buried/Cords in good condition/current inspection tag) | K21: 0.05 | L21: 2 | S21: 22 | T21: HSE Communications & Meetings - (Schedule HSE Meetings/Safety Committee meetings/Alerts / Lesson learned/Safety Bulletin contains latest HSE KPI) | AB21: 0.05 | AC21: 2
B22: 10 | C22: Tools & Equipment - (Includes, powered, hydraulic & pneumatic/Guards in place/Properly stored/RCD Protection/Earthed/Good condition & tagged) | K22: 0.03 | L22: 2 | S22: 23 | T22: HSE Plan & Associated Procedures - (Approved updated HSE Plan/ CEMP/HAZComm/Procedures/Standards/Project Safety Risk Register) | AB22: 0.03 | AC22: 2 | AL22: 26 points > 4 minors then is it’s a serious issue
B23: 11 | C23: Manual Handling - (Lifting/loading/pulling/pushing/twisting/awkward posture/repetitive task/frequent and prolong physical effort/Reasonable practicable use of mechanical aid) | K23: 0.03 | L23: 2 | S23: 24 | T23: Health, Safety & Environment Incident reporting - (Review of HSE Statistics, Reporting of Unsafe Act & Conditions/ Reporting of Near Miss incident/Reporting of FA cases/Record MT cases) | AB23: 0.03 | AC23: 2
B24: 12 | C24: Vehicle and mobile equipment / Plant - (dumpers; excavators, cranes, piling rigs, grader, roller, loaders/condition/KSA License/certification) | K24: 0.05 | L24: 1 | S24: 25 | T24: HSE Awareness, Training & Competence - (Policy /Objective & targets/Information, training/Climatic condition awareness/Reponses in emergency situation/ Safety Behavior Observation) | AB24: 0.04 | AC24: 2
B25: 13 | C25: Lifting Operations & Rigging - (Lifting Plan/Lifting devices & gears/PTW/Condition/3rd party certification/bank-man/rigger/slingers/man-basket/inspection record/tagged) | L25: 2 | S25: 26 | T25: Project Leadership Site Tours - (Provide evidence of proactive safety performance/Deficient discovered discussed/Positive feedback/Workers resolving safety issues) | AC25: 2
B27: Prepared by: | G27: Taher Alabdullatif | S27: Sent to MODON PM: | X27: =Y4 -> Eng. Mohammed Al Essa
B28: Safety Results
B29: 1 | D29: =COUNTIF(L13:Q26,"1")+COUNTIF(AB13:AG26,"1") -> 4 | I29: 2 | L29: =COUNTIF(L13:Q26,"2")+COUNTIF(AB13:AG26,"2") -> 22 | U29: 3 | W29: =COUNTIF(L13:Q26,"3")+COUNTIF(AB13:AG26,"3") -> 0

Sheet HSE-Stat
A1: Safety Statistics
A3: Category | B3: Item | D3: This Week | E3: This Month | F3: Year to Date | G3: Cumulative
A4: Category | B4: Total Hours Worked | D4: 3480 | E4: 11400 | F4: =132230+E4 -> 143630 | G4: =F4 -> 143630 | K4: =16*4 -> 64 | L4: =COUNTA(D4:G19) -> 64
B5: Safe Hours Worked | D5: 3480 | E5: 11400 | F5: =132230+E5 -> 143630 | G5: =F5 -> 143630 | L5: =COUNTBLANK(D4:G19) -> 0
A6: Reactive | B6: LTI | D6: 0 | E6: 0 | F6: 0 | G6: 0
B7: MTC (Healed w/o Disability) | D7: 0 | E7: 0 | F7: 0 | G7: 0
B8: MTC (Healed w/ Disability) | D8: 0 | E8: 0 | F8: 0 | G8: 0
B9: Near Miss | D9: 0 | E9: 0 | F9: 0 | G9: 0
B10: First Aid Cases | D10: 0 | E10: 0 | F10: 0 | G10: 0
B11: Fatality | D11: 0 | E11: 0 | F11: 0 | G11: 0
B12: Fire Incident Cases | D12: 0 | E12: 0 | F12: 0 | G12: 0
B13: Vehicle Incident | D13: 0 | E13: 0 | F13: 0 | G13: 0
B14: Property Damages | D14: 0 | E14: 0 | F14: 0 | G14: 0
A15: Proactive | B15: Induction Training | D15: 0 | E15: 7 | F15: 11 | G15: 11
B16: No.of Internal Training | D16: 0 | E16: 4 | F16: 5 | G16: 5
B17: No.of Internal Audit | D17: 0 | E17: 1 | F17: 5 | G17: 5
B18: No. of Toolbox Talks | D18: 0 | E18: 18 | F18: 23 | G18: 23
B19: Safety Awards/Incentives | D19: 0 | E19: 0 | F19: 0 | G19: 0
I20: Category | J20: Item | L20: This Week | M20: This Month | N20: Year to Date | O20: Cumulative
A22: Consultant Safety Inspection (Weekly Basis) | I22: Overall Average | J22: =AVERAGE(E24:E98) -> 0.755
A23: Week Number | B23: Date of Audit | C23: Date Issued | D23: Numbers Of Comments | E23: Overall Score | F23: Date Closed | G23: Closure Duration | I23: This Week Score | J23: =HSE!AE6 -> 0.78846154
A24: Week-1 | B24: 46083 | C24: 46072 | D24: 7 | E24: 0.66 | F24: 46083
A25: Week-2 | B25: 46090 | C25: 46081 | D25: 5 | E25: 0.66 | F25: 46084
A26: Week-3 | B26: 46097 | C26: 46081 | D26: 5 | E26: 0.66 | F26: 46084
A27: Week-4 | B27: 46104 | C27: 46109 | D27: 6 | E27: 0.66 | F27: 46110
A28: Week-5 | B28: 46111 | C28: 46108 | D28: 6 | E28: 0.66 | F28: 46116
A29: Week-6 | B29: 46118 | C29: 46108 | D29: 5 | E29: 0.66 | F29: 46123
A30: Week-7 | B30: 46125 | C30: 46119 | D30: 6 | E30: 0.66 | F30: 46123
A31: Week-8 | B31: 46131 | C31: 46109 | D31: 7 | E31: 0.66 | F31: 46129
A32: Week-9 | B32: 46139 | C32: 46138 | D32: 4 | E32: 0.78 | F32: 46138
A33: Week-10 | B33: 46146 | C33: 46145 | D33: 1 | E33: 0.79 | F33: 46146
A34: Week-11 | B34: 46153 | C34: 46151 | D34: 2 | E34: 0.79 | F34: 46152
A35: Week-12 | B35: 46160 | C35: 46159 | D35: 2 | E35: 0.79 | F35: 46160
... A53: Week-30 | B53: 46286 | C53: 46285 | D53: 1 | E53: 0.79 | F53: 46286
A54: Week-31
A55: Week-32
A56: Week-33
A57: Week-34
A58: Week-35
A59: Week-36
A60: Week-37
A61: Week-38
A62: Week-39
A63: Week-40
A64: Week-41
A65: Week-42
... A98: Week-75

Sheet Major Quantities
A1: BOQ Number | B1: Description of Item | C1: Total Quantity | D1: Unit of Measurement | E1: Plan To Date | F1: Actual To Date | G1: Remaining Total | H1: Variance | I1: Variance % | J1: Notices
A2: 2.1.1 | B2: Excavation | C2: 1503 | D2: M3 | E2: 1503 | F2: 629.42 | G2: =E2-F2 -> 873.58 | H2: =E2-F2 -> 873.58 | I2: =F2/C2 -> 0.41877578 | L2: =F2/C2 -> 0.41877578
A3: 2.1.3 | B3: Backfilling | C3: 20258.76 | D3: M3 | E3: 20258.76 | F3: 14724.77 | G3: =E3-F3 -> 5533.99 | H3: =E3-F3 -> 5533.99 | I3: =F3/C3 -> 0.72683471 | L3: =F3/C3 -> 0.72683471
L4: =F4/C4 -> #DIV/0!
L5: =F5/C5 -> #DIV/0!
L6: =F6/C6 -> #DIV/0!
L7: =F7/C7 -> #DIV/0!
L8: =F8/C8 -> #DIV/0!
L9: =F9/C9 -> #DIV/0!
L10: =F10/C10 -> #DIV/0!
L11: =F11/C11 -> #DIV/0!
L12: =F12/C12 -> #DIV/0!
L13: =F13/C13 -> #DIV/0!
L14: =F14/C14 -> #DIV/0!
L15: =F15/C15 -> #DIV/0!
... L19: =F19/C19 -> #DIV/0!
A31: Activity ID | B31: Activity Name | C31: Resource Name | D31: Price / Unit | E31: Budgeted Units | F31: Actual Units | G31: Budgeted Cost | H31: Budgeted Cost | I31: Actual | J31: 45319 | K31: 45320 | L31: 45321 | M31: 45322 | N31: 45323 | O31: 45324 | P31: 45325 | Q31: 45326 | R31: 45327 | S31: 45328 | T31: 45329 | U31: 45330 | V31: 45331 | W31: 45332 | X31: 45333 | Y31: 45334 | Z31: 45335 | AA31: 45336 | AB31: 45337 | AC31: 45338 | AD31: 45339 | AE31: 45340 | AF31: 45341 | AG31: 45342 | AH31: 45343 | AI31: 45344 | AJ31: 45345 | AK31: 45346 | AL31: 45347 | AM31: 45348 | AN31: 45349 | AO31: 45350 | AP31: 45351 | AQ31: 45352 | AR31: 45353 | AS31: 45354 | AT31: 45355 | AU31: 45356 | AV31: 45357 | AW31: 45358 | AX31: 45359 | AY31: 45360 | AZ31: 45361 | BA31: 45362 | BB31: 45363 | BC31: 45364 | BD31: 45365 | BE31: 45366 | BF31: 45367 | BG31: 45368 | BH31: 45369 | BI31: 45370 | BJ31: 45371 | BK31: 45372 | BL31: 45373 | BM31: 45374 | BN31: 45375 | BO31: 45376 | BP31: 45377 | BQ31: 45378 | BR31: 45379 | BS31: 45380 | BT31: 45381 | BU31: 45382 | BV31: 45383 | BW31: 45384 | BX31: 45385 | BY31: 45386 | BZ31: 45387 | CA31: 45388 | CB31: 45389 | CC31: 45390 | CD31: 45391 | CE31: 45392 | CF31: 45393 | CG31: 45394 | CH31: 45395 | CI31: 45396 | CJ31: 45397 | CK31: 45398 | CL31: 45399 | CM31: 45400 | CN31: 45401 | CO31: 45402 | CP31: 45403 | CQ31: 45404 | CR31: 45405 | CS31: 45406 | CT31: 45407 | CU31: 45408 | CV31: 45409 | CW31: 45410 | CX31: 45411 | CY31: 45412 | CZ31: 45413 | DA31: 45414 | DB31: 45415 | DC31: 45416 | DD31: 45417 | DE31: 45418 | DF31: 45419 | DG31: 45420 | DH31: 45421 | DI31: 45422 | DJ31: 45423 | DK31: 45424 | DL31: 45425 | DM31: 45426 | DN31: 45427 | DO31: 45428 | DP31: 45429 | DQ31: 45430 | DR31: 45431 | DS31: 45432 | DT31: 45433 | DU31: 45434 | DV31: 45435 | DW31: 45436 | DX31: 45437 | DY31: 45438 | DZ31: 45439 | EA31: 45440 | EB31: 45441 | EC31: 45442 | ED31: 45443 | EE31: 45444 | EF31: 45445 | EG31: 45446 | EH31: 45447 | EI31: 45448 | EJ31: 45449 | EK31: 45450 | EL31: 45451 | EM31: 45452 | EN31: 45453 | EO31: 45454 | EP31: 45455 | EQ31: 45456 | ER31: 45457 | ES31: 45458 | ET31: 45459 | EU31: 45460 | EV31: 45461 | EW31: 45462 | EX31: 45463 | EY31: 45464 | EZ31: 45465 | FA31: 45466 | FB31: 45467 | FC31: 45468 | FD31: 45469 | FE31: 45470 | FF31: 45471 | FG31: 45472 | FH31: 45473 | FI31: 45474 | FJ31: 45475 | FK31: 45476 | FL31: 45477 | FM31: 45478 | FN31: 45479 | FO31: 45480 | FP31: 45481 | FQ31: 45482 | FR31: 45483 | FS31: 45484 | FT31: 45485 | FU31: 45486 | FV31: 45487 | FW31: 45488 | FX31: 45489 | FY31: 45490 | FZ31: 45491 | GA31: 45492 | GB31: 45493 | GC31: 45494 | GD31: 45495 | GE31: 45496 | GF31: 45497 | GG31: 45498 | GH31: 45499 | GI31: 45500 | GJ31: 45501 | GK31: 45502 | GL31: 45503 | GM31: 45504 | GN31: 45505 | GO31: 45506 | GP31: 45507 | GQ31: 45508 | GR31: 45509 | GS31: 45510 | GT31: 45511 | GU31: 45512 | GV31: 45513 | GW31: 45514 | GX31: 45515 | GY31: 45516 | GZ31: 45517 | HA31: 45518 | HB31: 45519 | HC31: 45520 | HD31: 45521 | HE31: 45522 | HF31: 45523 | HG31: 45524 | HH31: 45525 | HI31: 45526 | HJ31: 45527 | HK31: 45528 | HL31: 45529 | HM31: 45530 | HN31: 45531 | HO31: 45532 | HP31: 45533 | HQ31: 45534 | HR31: 45535 | HS31: 45536 | HT31: 45537 | HU31: 45538 | HV31: 45539 | HW31: 45540 | HX31: 45541 | HY31: 45542 | HZ31: 45543 | IA31: 45544 | IB31: 45545 | IC31: 45546 | ID31: 45547 | IE31: 45548 | IF31: 45549 | IG31: 45550 | IH31: 45551 | II31: 45552 | IJ31: 45553 | IK31: 45554 | IL31: 45555 | IM31: 45556 | IN31: 45557 | IO31: 45558 | IP31: 45559 | IQ31: 45560 | IR31: 45561 | IS31: 45562 | IT31: 45563 | IU31: 45564 | IV31: 45565 | IW31: 45566 | IX31: 45567 | IY31: 45568 | IZ31: 45569 | JA31: 45570 | JB31: 45571 | JC31: 45572 | JD31: 45573 | JE31: 45574 | JF31: 45575 | JG31: 45576 | JH31: 45577 | JI31: 45578 | JJ31: 45579 | JK31: 45580 | JL31: 45581 | JM31: 45582 | JN31: 45583 | JO31: 45584 | JP31: 45585 | JQ31: 45586 | JR31: 45587 | JS31: 45588 | JT31: 45589 | JU31: 45590 | JV31: 45591 | JW31: 45592 | JX31: 45593 | JY31: 45594 | JZ31: 45595 | KA31: 45596 | KB31: 45597 | KC31: 45598 | KD31: 45599 | KE31: 45600 | KF31: 45601 | KG31: 45602 | KH31: 45603 | KI31: 45604 | KJ31: 45605 | KK31: 45606 | KL31: 45607 | KM31: 45608 | KN31: 45609 | KO31: 45610 | KP31: 45611 | KQ31: 45612 | KR31: 45613 | KS31: 45614 | KT31: 45615 | KU31: 45616 | KV31: 45617 | KW31: 45618 | KX31: 45619 | KY31: 45620 | KZ31: 45621 | LA31: 45622 | LB31: 45623 | LC31: 45624 | LD31: 45625 | LE31: 45626 | LF31: 45627 | LG31: 45628 | LH31: 45629 | LI31: 45630 | LJ31: 45631 | LK31: 45632 | LL31: 45633 | LM31: 45634 | LN31: 45635 | LO31: 45636 | LP31: 45637 | LQ31: 45638 | LR31: 45639 | LS31: 45640 | LT31: 45641 | LU31: 45642 | LV31: 45643 | LW31: 45644 | LX31: 45645 | LY31: 45646 | LZ31: 45647 | MA31: 45648 | MB31: 45649 | MC31: 45650 | MD31: 45651 | ME31: 45652 | MF31: 45653 | MG31: 45654 | MH31: 45655 | MI31: 45656 | MJ31: 45657 | MK31: 45658 | ML31: 45659 | MM31: 45660 | MN31: 45661 | MO31: 45662 | MP31: 45663 | MQ31: 45664 | MR31: 45665 | MS31: 45666 | MT31: 45667 | MU31: 45668 | MV31: 45669 | MW31: 45670 | MX31: 45671 | MY31: 45672 | MZ31: 45673 | NA31: 45674 | NB31: 45675 | NC31: 45676 | ND31: 45677 | NE31: 45678 | NF31: 45679 | NG31: 45680 | NH31: 45681 | NI31: 45682 | NJ31: 45683 | NK31: 45684 | NL31: 45685 | NM31: 45686 | NN31: 45687 | NO31: 45688 | NP31: 45689 | NQ31: 45690 | NR31: 45691 | NS31: 45692 | NT31: 45693 | NU31: 45694 | NV31: 45695 | NW31: 45696 | NX31: 45697 | NY31: 45698 | NZ31: 45699 | OA31: 45700 | OB31: 45701 | OC31: 45702 | OD31: 45703 | OE31: 45704 | OF31: 45705 | OG31: 45706 | OH31: 45707 | OI31: 45708 | OJ31: 45709 | OK31: 45710 | OL31: 45711 | OM31: 45712 | ON31: 45713 | OO31: 45714 | OP31: 45715 | OQ31: 45716 | OR31: 45717 | OS31: 45718 | OT31: 45719 | OU31: 45720 | OV31: 45721 | OW31: 45722 | OX31: 45723 | OY31: 45724 | OZ31: 45725 | PA31: 45726 | PB31: 45727 | PC31: 45728 | PD31: 45729 | PE31: 45730 | PF31: 45731 | PG31: 45732 | PH31: 45733 | PI31: 45734 | PJ31: 45735 | PK31: 45736 | PL31: 45737 | PM31: 45738 | PN31: 45739 | PO31: 45740 | PP31: 45741 | PQ31: 45742 | PR31: 45743 | PS31: 45744 | PT31: 45745 | PU31: 45746 | PV31: 45747 | PW31: 45748 | PX31: 45749 | PY31: 45750 | PZ31: 45751 | QA31: 45752 | QB31: 45753 | QC31: 45754 | QD31: 45755 | QE31: 45756 | QF31: 45757 | QG31: 45758 | QH31: 45759 | QI31: 45760 | QJ31: 45761 | QK31: 45762 | QL31: 45763 | QM31: 45764 | QN31: 45765 | QO31: 45766 | QP31: 45767 | QQ31: 45768 | QR31: 45769 | QS31: 45770 | QT31: 45771 | QU31: 45772 | QV31: 45773 | QW31: 45774 | QX31: 45775 | QY31: 45776 | QZ31: 45777 | RA31: 45778 | RB31: 45779 | RC31: 45780 | RD31: 45781 | RE31: 45782 | RF31: 45783 | RG31: 45784 | RH31: 45785 | RI31: 45786 | RJ31: 45787 | RK31: 45788 | RL31: 45789 | RM31: 45790 | RN31: 45791 | RO31: 45792 | RP31: 45793 | RQ31: 45794 | RR31: 45795 | RS31: 45796 | RT31: 45797 | RU31: 45798 | RV31: 45799 | RW31: 45800 | RX31: 45801 | RY31: 45802 | RZ31: 45803 | SA31: 45804 | SB31: 45805 | SC31: 45806 | SD31: 45807 | SE31: 45808 | SF31: 45809 | SG31: 45810 | SH31: 45811 | SI31: 45812 | SJ31: 45813 | SK31: 45814 | SL31: 45815 | SM31: 45816 | SN31: 45817 | SO31: 45818 | SP31: 45819 | SQ31: 45820 | SR31: 45821 | SS31: 45822 | ST31: 45823 | SU31: 45824 | SV31: 45825 | SW31: 45826 | SX31: 45827 | SY31: 45828 | SZ31: 45829 | TA31: 45830 | TB31: 45831 | TC31: 45832 | TD31: 45833 | TE31: 45834 | TF31: 45835 | TG31: 45836 | TH31: 45837 | TI31: 45838 | TJ31: 45839 | TK31: 45840 | TL31: 45841 | TM31: 45842 | TN31: 45843 | TO31: 45844 | TP31: 45845 | TQ31: 45846 | TR31: 45847 | TS31: 45848 | TT31: 45849 | TU31: 45850 | TV31: 45851 | TW31: 45852 | TX31: 45853 | TY31: 45854 | TZ31: 45855 | UA31: 45856 | UB31: 45857 | UC31: 45858 | UD31: 45859 | UE31: 45860 | UF31: 45861 | UG31: 45862 | UH31: 45863 | UI31: 45864 | UJ31: 45865 | UK31: 45866 | UL31: 45867 | UM31: 45868 | UN31: 45869 | UO31: 45870 | UP31: 45871 | UQ31: 45872 | UR31: 45873 | US31: 45874 | UT31: 45875 | UU31: 45876 | UV31: 45877 | UW31: 45878 | UX31: 45879 | UY31: 45880 | UZ31: 45881 | VA31: 45882 | VB31: 45883 | VC31: 45884 | VD31: 45885 | VE31: 45886 | VF31: 45887 | VG31: 45888 | VH31: 45889 | VI31: 45890 | VJ31: 45891 | VK31: 45892 | VL31: 45893 | VM31: 45894 | VN31: 45895 | VO31: 45896 | VP31: 45897 | VQ31: 45898 | VR31: 45899 | VS31: 45900 | VT31: 45901 | VU31: 45902 | VV31: 45903 | VW31: 45904 | VX31: 45905 | VY31: 45906 | VZ31: 45907 | WA31: 45908 | WB31: 45909 | WC31: 45910 | WD31: 45911 | WE31: 45912 | WF31: 45913 | WG31: 45914 | WH31: 45915 | WI31: 45916 | WJ31: 45917 | WK31: 45918 | WL31: 45919 | WM31: 45920 | WN31: 45921 | WO31: 45922 | WP31: 45923 | WQ31: 45924 | WR31: 45925 | WS31: 45926 | WT31: 45927 | WU31: 45928 | WV31: 45929 | WW31: 45930 | WX31: 45931 | WY31: 45932 | WZ31: 45933 | XA31: 45934 | XB31: 45935 | XC31: 45936 | XD31: 45937 | XE31: 45938 | XF31: 45939 | XG31: 45940 | XH31: 45941 | XI31: 45942 | XJ31: 45943 | XK31: 45944 | XL31: 45945 | XM31: 45946 | XN31: 45947 | XO31: 45948 | XP31: 45949 | XQ31: 45950 | XR31: 45951 | XS31: 45952 | XT31: 45953 | XU31: 45954 | XV31: 45955 | XW31: 45956 | XX31: 45957 | XY31: 45958 | XZ31: 45959 | YA31: 45960 | YB31: 45961 | YC31: 45962 | YD31: 45963 | YE31: 45964 | YF31: 45965 | YG31: 45966 | YH31: 45967 | YI31: 45968 | YJ31: 45969 | YK31: 45970 | YL31: 45971 | YM31: 45972 | YN31: 45973 | YO31: 45974 | YP31: 45975 | YQ31: 45976 | YR31: 45977 | YS31: 45978 | YT31: 45979 | YU31: 45980 | YV31: 45981 | YW31: 45982 | YX31: 45983 | YY31: 45984 | YZ31: 45985 | ZA31: 45986 | ZB31: 45987 | ZC31: 45988 | ZD31: 45989 | ZE31: 45990 | ZF31: 45991 | ZG31: 45992 | ZH31: 45993 | ZI31: 45994 | ZJ31: 45995 | ZK31: 45996 | ZL31: 45997 | ZM31: 45998 | ZN31: 45999 | ZO31: 46000 | ZP31: 46001 | ZQ31: 46002 | ZR31: 46003 | ZS31: 46004 | ZT31: 46005 | ZU31: 46006 | ZV31: 46007 | ZW31: 46008 | ZX31: 46009
A32: Total | E32: 102031 | F32: 23531.31 | G32: 45093675 | H32: 45093675 | I32: =F32 -> 23531.31 | J32: 21.55 | K32: 21.55 | L32: 21.55 | M32: 21.55 | N32: 21.55 | P32: 21.83 | Q32: 21.83 | R32: 21.83 | S32: 0.27 | T32: 0.27 | U32: 1.46 | W32: 1.46 | X32: 1.46 | Y32: 70.33 | Z32: 70.33 | AA32: 70.33 | AB32: 112.19 | AD32: 112.19 | AE32: 112.19 | AF32: 59.21 | AG32: 59.21 | AH32: 59.21 | AK32: 35.32 | AL32: 35.32 | AM32: 16.44 | AN32: 16.85 | AO32: 16.85 | AP32: 0.87 | AR32: 0.27 | AS32: 0.27 | AT32: 0 | AU32: 0 | AV32: 0 | AW32: 189.2 | AY32: 189.2 | AZ32: 189.2 | BA32: 141.9 | BB32: 141.9 | BC32: 141.9 | BD32: 141.9 | BF32: 141.9 | BG32: 141.9 | BH32: 141.9 | BI32: 141.9 | BJ32: 141.9 | BK32: 141.9 | BM32: 141.9 | BN32: 141.9 | BO32: 141.9 | BP32: 141.9 | BQ32: 141.9 | BR32: 141.9 | BT32: 141.9 | BU32: 141.9 | BV32: 141.9 | BW32: 141.9 | BX32: 127.2 | BY32: 126.6 | CA32: 126.6 | CB32: 126.6 | CC32: 126.6 | CD32: 126.6 | CJ32: 168.8 | CK32: 168.8 | CL32: 168.8 | CM32: 168.8 | CO32: 168.8 | CP32: 168.8 | CQ32: 168.8 | CR32: 168.8 | CS32: 168.8 | CT32: 168.8 | CV32: 168.8 | CW32: 168.8 | CX32: 168.8 | CY32: 176.59 | CZ32: 184.37 | DA32: 184.37 | DC32: 184.37 | DD32: 184.37 | DE32: 184.37 | DF32: 184.37 | DG32: 184.48 | DH32: 184.59 | DJ32: 184.59 | DK32: 184.59 | DL32: 184.59 | DM32: 188.22 | DN32: 191.86 | DO32: 191.87 | DQ32: 192.51 | DR32: 193.15 | DS32: 189.52 | DT32: 173.9 | DU32: 161.91 | DV32: 162.5 | DX32: 164.88 | DY32: 167.11 | DZ32: 167.57 | EA32: 167.58 | EB32: 166.99 | EC32: 168.41 | EE32: 169.07 | EF32: 168.89 | EG32: 170.07 | EH32: 170.1 | EI32: 168.12 | EJ32: 166.1 | EL32: 173.18 | EM32: 181.19 | EN32: 182.12 | EO32: 182.19 | EP32: 182.26 | EQ32: 715.97 | ES32: 1253.81 | ET32: 1257.95 | EZ32: 1259.46 | FA32: 1260.97 | FB32: 1261.4 | FC32: 1257.71 | FD32: 1256.27 | FE32: 1258.96 | FG32: 1258.8 | FH32: 1259.08 | FI32: 1257.81 | FJ32: 1253.41 | FK32: 1250.72 | FL32: 1250.72 | FN32: 1256.66 | FO32: 1261.05 | FP32: 1261.24 | FQ32: 1262.99 | FR32: 1262.99 | FS32: 1396.73 | FU32: 1526.57 | FV32: 1521.77 | FW32: 1520.73 | FX32: 1520.58 | FY32: 1520.58 | FZ32: 1518.2 | GB32: 1516.6 | GC32: 1522.61 | GD32: 1531.64 | GE32: 1535.45 | GF32: 785.51 | GG32: 35.59 | GI32: 28.78 | GJ32: 21.94 | GK32: 21.94 | GL32: 23.84 | GM32: 25.12 | GN32: 24.42 | GP32: 24.2 | GQ32: 36.24 | GR32: 48.4 | GS32: 52.11 | GT32: 55.84 | GU32: 55.69 | GW32: 42.55 | GX32: 28.38 | GY32: 33.58 | GZ32: 40.48 | HA32: 41.01 | HB32: 41.81 | HD32: 72.51 | HE32: 274.38 | HF32: 459.01 | HG32: 471.56 | HH32: 471.46 | HI32: 467.45 | HK32: 464.26 | HL32: 452.44 | HM32: 444.04 | HN32: 448.3 | HO32: 448.19 | HP32: 445.73 | HR32: 444.97 | HS32: 442.3 | HT32: 438.04 | HU32: 260.54 | HV32: 83.03 | HW32: 78.29 | HY32: 43.88 | HZ32: 13.3 | IA32: 197.77 | IB32: 383.29 | IC32: 383.45 | ID32: 381.68 | IF32: 380 | IG32: 194.34 | IH32: 8.59 | II32: 8.59 | IJ32: 8.77 | IK32: 8.69 | IM32: 8.43 | IN32: 8.44 | IP32: 8.28 | IQ32: 8.96 | IR32: 9.8 | IT32: 9.74 | IU32: 11.69 | IV32: 13.68 | IW32: 14.81 | IX32: 15.72 | IY32: 15.51 | JA32: 14.14 | JB32: 15.53 | JC32: 19.42 | JD32: 22.57 | JE32: 24.53 | JF32: 27.69 | JH32: 35.94 | JI32: 41.52 | JJ32: 42.66 | JK32: 42.76 | JL32: 53.47 | JM32: 69.64 | JO32: 62.96 | JP32: 58.15 | JQ32: 72.8 | JR32: 112.27 | JS32: 142.58 | JT32: 129.26 | JV32: 127.31 | JW32: 144.73 | JX32: 105.34 | JY32: 57.11 | JZ32: 64.4 | KA32: 64.56 | KC32: 46.25 | KD32: 41.41 | KE32: 50.63 | KF32: 54.8 | KG32: 49.72 | KH32: 44.52 | KJ32: 47.52 | KK32: 50.57 | KL32: 39.97 | KM32: 29.71 | KN32: 37.26 | KO32: 44.53 | KQ32: 39.58 | KR32: 33.69 | KS32: 51.95 | KT32: 91.66 | KU32: 108.72 | KV32: 106.4 | KX32: 107.85 | KY32: 99.66 | KZ32: 92.65 | LA32: 83.03 | LB32: 72.46 | LC32: 60.56 | LE32: 48.38 | LF32: 45.24 | LG32: 44.94 | LH32: 57.38 | LI32: 66.43 | LJ32: 97.63 | LL32: 122.69 | LM32: 88.44 | LN32: 64.32 | LO32: 139.59 | LP32: 214.39 | LQ32: 219.2 | LS32: 217.1 | LT32: 215.73 | LU32: 224.41 | LV32: 153.08 | LW32: 75.72 | LX32: 77.28 | LZ32: 77.93 | MA32: 79.36 | MB32: 76.9 | MC32: 73.16 | MD32: 71.12 | ME32: 78.67 | MG32: 87.82 | MH32: 87.1 | MI32: 77.2 | MJ32: 62.8 | MK32: 63.13 | ML32: 66.81 | MN32: 64.95 | MO32: 63.67 | MP32: 51.03 | MQ32: 37.85 | MR32: 33.5 | MS32: 29.9 | MU32: 29.85 | MV32: 28.91 | MW32: 27.97 | MX32: 23.83 | MY32: 38.57 | MZ32: 58.66 | NB32: 38.82 | NC32: 17.75 | ND32: 17.73 | NE32: 16.56 | NF32: 15.49 | NG32: 15.6 | NI32: 15.6 | NJ32: 15.6 | NK32: 15.59 | NL32: 15.58 | NM32: 15.59 | NN32: 14.44 | NP32: 18.24 | NQ32: 23.21 | NR32: 23.26 | NS32: 23.31 | NT32: 23.31 | NU32: 23.31 | NW32: 32.13 | NX32: 40.95 | NY32: 40.95 | NZ32: 44.56 | OA32: 44.66 | OB32: 41.15 | OD32: 41.15 | OE32: 37.19 | OF32: 33.23 | OG32: 40.64 | OH32: 48.13 | OI32: 48.21 | OL32: 49.78 | OM32: 51.42 | ON32: 51.48 | OO32: 55.47 | OP32: 49.97 | OR32: 30.38 | OS32: 30.4 | OT32: 42.94 | OU32: 42.94 | OV32: 42.62 | OW32: 41.99 | OY32: 39.52 | OZ32: 39.62 | PA32: 38.85 | PB32: 37.2 | PC32: 41.88 | PD32: 39.29 | PF32: 38 | PG32: 38 | PH32: 36.57 | PI32: 34.12 | PJ32: 32.89 | PK32: 32.89 | PM32: 38.78 | PN32: 34.91 | PO32: 33.02 | PP32: 33.11 | PQ32: 33.11 | PR32: 33.11 | PT32: 33.11 | PY32: 44.87 | QA32: 41.58 | QB32: 25.17 | QC32: 25.17 | QD32: 24.87 | QE32: 23.97 | QF32: 21.96 | QH32: 26.95 | QI32: 59.98 | QJ32: 59.98 | QK32: 57.9 | QL32: 51.64 | QM32: 51.68 | QO32: 67.07 | QP32: 112.2 | QQ32: 110.21 | QR32: 105.83 | QS32: 105.85 | QT32: 93.69 | QV32: 57.03 | QW32: 57.06 | QX32: 60.03 | QY32: 73 | QZ32: 85.47 | RA32: 84.59 | RC32: 84.59 | RD32: 83.47 | RE32: 74.96 | RF32: 65.16 | RG32: 87.05 | RH32: 96.26 | RJ32: 81.82 | RK32: 88.54 | RL32: 92.61 | RM32: 92.47 | RN32: 92.47 | RO32: 88.12 | RQ32: 93.15 | RR32: 80.89 | RS32: 77.48 | RT32: 77.44 | RU32: 71.49 | RV32: 77.95 | RX32: 109.23 | RY32: 94.06 | RZ32: 48.46 | SA32: 57.19 | SB32: 82.65 | SC32: 70.88 | SE32: 33.17 | SF32: 23.85 | SG32: 26.07 | SH32: 23.38 | SI32: 15.24 | SJ32: 15.09 | SP32: 15.39 | SQ32: 15.14 | SS32: 14.41 | ST32: 15.11 | SU32: 18.47 | SV32: 23.22 | SW32: 23.21 | SX32: 23.18 | SZ32: 31.08 | TA32: 54.77 | TB32: 54.77 | TC32: 54.77 | TD32: 58.18 | TE32: 75.04 | TG32: 95.06 | TH32: 128.25 | TI32: 226.95 | TJ32: 228.05 | TK32: 188.29 | TL32: 69 | TN32: 67.01 | TO32: 57.64 | TP32: 47.52 | TQ32: 46.01 | TR32: 42.06 | TS32: 43.71 | TU32: 43.57 | TV32: 43.5 | TW32: 43.11 | TX32: 43.31 | TY32: 43.29 | TZ32: 41.84 | UB32: 32.36 | UC32: 16.67 | UD32: 15.57 | UE32: 18.25 | UF32: 27.31 | UG32: 29.33 | UI32: 29.03 | UJ32: 31.79 | UK32: 29.01 | UL32: 73.54 | UM32: 71.55 | UN32: 35.98 | UP32: 36.5 | UQ32: 38.47 | UR32: 41.74 | US32: 49.19 | UT32: 69.2 | UU32: 126.69 | UW32: 100.17 | UX32: 39.12 | UY32: 41.31 | UZ32: 52.36 | VA32: 55.87 | VB32: 32.83 | VD32: 32.65 | VE32: 32.1 | VF32: 32.1 | VG32: 33.15 | VH32: 36.26 | VI32: 36.38 | VK32: 36.5 | VL32: 33.19 | VM32: 23.46 | VN32: 24.23 | VO32: 23.62 | VP32: 20.59 | VR32: 20.57 | VS32: 31.85 | VT32: 67.01 | VU32: 82.05 | VV32: 118.49 | VW32: 121.05 | VY32: 117.22 | VZ32: 148.48 | WA32: 243.82 | WB32: 243.97 | WC32: 242.68 | WD32: 242.22 | WF32: 230.75 | WG32: 238.39 | WH32: 352.51 | WI32: 355.95 | WJ32: 362.35 | WK32: 359.99 | WM32: 359.75 | WN32: 365.12 | WO32: 378.86 | WQ32: 321.98 | WR32: 172.61 | WT32: 172.81 | WU32: 173.28 | WV32: 176.82 | WW32: 182.75 | WX32: 182.4 | WY32: 190.28 | XA32: 207.41 | XB32: 208.55 | XC32: 188.07 | XD32: 150.81 | XE32: 207.66 | XF32: 171.87 | XH32: 72.23 | XI32: 98.64 | XJ32: 176.75 | XK32: 173.92 | XL32: 164.68 | XM32: 135.94 | XO32: 135.06 | XP32: 135.74 | XQ32: 134.42 | XR32: 170 | XS32: 300.86 | XT32: 333.41 | XV32: 335.99 | XW32: 379.73 | XX32: 335.5 | XY32: 202 | XZ32: 200.23 | YA32: 241.61 | YC32: 366.26 | YD32: 364.93 | YE32: 373.75 | YF32: 440.86 | YG32: 526.67 | YH32: 526.62 | YJ32: 527.57 | YK32: 500.4 | YL32: 404.75 | YM32: 388.18 | YN32: 388.38 | YO32: 351.31 | YQ32: 231.37 | YR32: 217.45 | YS32: 244.64 | YT32: 247.28 | YU32: 254.64 | YV32: 235.11 | YX32: 181.35 | YY32: 181.02 | YZ32: 166.1 | ZA32: 123.29 | ZB32: 123.29 | ZC32: 121.71 | ZE32: 108.76 | ZF32: 84.11 | ZG32: 83.53 | ZH32: 82.26 | ZI32: 82.26 | ZJ32: 82.26 | ZL32: 82.26 | ZM32: 96.75 | ZN32: 140.23 | ZO32: 140.23 | ZP32: 140.23 | ZQ32: 140.23 | ZS32: 140.23 | ZT32: 140.23 | ZU32: 140.23 | ZV32: 140.23 | ZW32: 140.23 | ZX32: 105.17
A33: 2 Way PVC | E33: 90 | F33: 0 | G33: 42300 | H33: 42300 | I33: =F33 -> 0 | VV33: 1.23 | VW33: 3.68 | VZ33: 0.73 | WA33: 2.94 | WB33: 2.94 | WC33: 2.94 | WD33: 2.94 | WF33: 2.51 | WG33: 1.23 | WH33: 1.23 | WI33: 1.23 | WJ33: 0.92 | XF33: 0.21 | XH33: 0.85 | XI33: 0.85 | XJ33: 0.85 | XK33: 0.85 | XL33: 2.5 | XM33: 7.45 | XO33: 7.59 | XP33: 8.02 | XQ33: 6.87 | XR33: 3.41 | XS33: 4.07 | XT33: 5.34 | XV33: 3.21 | XW33: 3.21 | XX33: 3.21 | XY33: 2.64 | XZ33: 0.92 | YA33: 0.92 | YC33: 0.92 | YD33: 0.92 | YE33: 0.69
A34: 3-outlet Fire Hydrant (2 x 2.5 inch and 1 x 4 inch) | E34: 60 | F34: 1.8 | G34: 1043400 | H34: 1043400 | I34: =F34 -> 1.8 | AN34: 0.6 | AO34: 0.6 | AP34: 0.6 | OM34: 0.07 | ON34: 0.13 | OO34: 0.13 | OP34: 0.13 | OR34: 0.1 | OS34: 0.1 | OT34: 0.1 | OU34: 0.1 | OV34: 0.1 | OW34: 0.1 | OY34: 0.1 | OZ34: 0.1 | PA34: 0.1 | PB34: 0.1 | PC34: 0.1 | PD34: 0.1 | PF34: 0.1 | PG34: 0.1 | PH34: 0.1 | PI34: 0.1 | PJ34: 0.1 | PK34: 0.1 | PM34: 0.1 | PN34: 0.1 | PO34: 0.1 | PP34: 0.1 | PQ34: 0.1 | PR34: 0.1 | PT34: 0.1 | PY34: 0.13 | QA34: 0.13 | QB34: 0.13 | QC34: 0.13 | QD34: 0.13 | QE34: 0.13 | QF34: 0.13 | QH34: 0.13 | QI34: 0.13 | QJ34: 0.13 | QK34: 0.13 | QL34: 0.13 | QM34: 0.13 | QO34: 0.13 | QP34: 0.13 | QQ34: 0.13 | QR34: 0.13 | QS34: 0.13 | QT34: 0.13 | QV34: 0.13 | QW34: 0.13 | QX34: 0.13 | QY34: 0.13 | QZ34: 0.13 | RA34: 0.13 | RC34: 0.13 | RD34: 0.13 | RE34: 0.13 | RF34: 0.13 | RG34: 0.13 | RH34: 0.13 | RJ34: 0.13 | RK34: 0.13 | RL34: 0.13 | RM34: 0.13 | RN34: 0.13 | RO34: 0.13 | RQ34: 0.13 | RR34: 0.13 | RS34: 0.13 | RT34: 0.23 | RU34: 0.5 | RV34: 0.5 | RX34: 0.5 | RY34: 0.56 | RZ34: 0.75 | SA34: 1.09 | SB34: 2.1 | SC34: 2.19 | SE34: 2.44 | SF34: 2.44 | SG34: 2.44 | SH34: 2.1 | SI34: 1.09 | SJ34: 1.09 | SP34: 1.09 | SQ34: 1.03 | SS34: 0.84 | ST34: 0.74 | SU34: 0.38 | SV34: 0.13 | SW34: 0.2 | SX34: 0.39 | SZ34: 0.39 | TA34: 0.39 | TB34: 0.39 | TC34: 0.39 | TD34: 0.36 | TE34: 0.26 | TG34: 0.26 | TH34: 0.42 | TI34: 0.9 | TJ34: 0.9 | TK34: 0.9 | TL34: 0.9 | TN34: 0.9 | TO34: 0.9 | TP34: 0.9 | TQ34: 0.9 | TR34: 0.9 | TS34: 0.9 | TU34: 0.9 | TV34: 0.75 | TW34: 0.29 | TX34: 0.29 | TY34: 0.29 | TZ34: 0.29 | UB34: 0.29 | UC34: 0.29 | UD34: 0.29 | UE34: 0.22 | UT34: 0.05 | UU34: 0.2 | UW34: 0.25 | UX34: 0.4 | UY34: 0.43 | UZ34: 0.51 | VA34: 0.44 | VB34: 0.23 | VD34: 0.23 | VE34: 0.23 | VF34: 0.18 | VG34: 0.03 | VH34: 0.03 | VI34: 0.03 | VK34: 0.03 | VL34: 0.03 | VM34: 0.03 | VN34: 0.02 | YT34: 0.19 | YU34: 0.75 | YV34: 0.75 | YX34: 0.75 | YY34: 0.75 | YZ34: 0.75 | ZA34: 0.75 | ZB34: 0.75 | ZC34: 0.56
A35: 300 mm diameter pipe | E35: 925 | F35: 0 | G35: 342250 | H35: 342250 | I35: =F35 -> 0 | HD35: 12.68 | HE35: 25.37 | HF35: 25.37 | HG35: 25.37 | HH35: 25.37 | HI35: 25.37 | HK35: 25.37 | HL35: 25.37 | HM35: 25.37 | HN35: 25.37 | HO35: 25.37 | HP35: 25.37 | HR35: 25.37 | HS35: 25.37 | HT35: 25.37 | HU35: 25.37 | HV35: 25.37 | HW35: 25.37 | HY35: 12.68 | IU35: 0.57 | IV35: 1.14 | IW35: 1.14 | IX35: 1.14 | IY35: 1.14 | JA35: 0.57 | JR35: 9.58 | JS35: 19.16 | JT35: 19.16 | JV35: 19.16 | JW35: 20.97 | JX35: 13.21 | JY35: 3.63 | JZ35: 3.63 | KA35: 1.81 | KT35: 6.5 | KU35: 13 | KV35: 13 | KX35: 13 | KY35: 6.5 | LJ35: 7.54 | LL35: 15.09 | LM35: 7.54 | LO35: 18.02 | LP35: 36.04 | LQ35: 36.04 | LS35: 36.04 | LT35: 36.04 | LU35: 36.04 | LV35: 18.02 | MY35: 10.13 | MZ35: 20.25 | NB35: 10.13 | NW35: 1.69 | NX35: 3.38 | NY35: 3.38 | NZ35: 3.38 | OA35: 1.69
A36: 4 Way PVC | E36: 102 | F36: 0 | G36: 95880 | H36: 95880 | I36: =F36 -> 0 | XR36: 0.85 | XS36: 3.4 | XT36: 3.4 | XV36: 6.12 | XW36: 14.28 | XX36: 14.28 | XY36: 14.28 | XZ36: 14.28 | YA36: 12.41 | YC36: 6.8 | YD36: 6.8 | YE36: 5.1
A37: 400 mm diameter pipe | E37: 1231 | F37: 0 | G37: 689360 | H37: 689360 | I37: =F37 -> 0 | HD37: 14.86 | HE37: 29.73 | HF37: 29.73 | HG37: 29.73 | HH37: 29.73 | HI37: 29.73 | HK37: 29.73 | HL37: 29.73 | HM37: 29.73 | HN37: 29.73 | HO37: 29.73 | HP37: 29.73 | HR37: 29.73 | HS37: 29.73 | HT37: 29.73 | HU37: 29.73 | HV37: 29.73 | HW37: 29.73 | HY37: 14.86 | IU37: 0.67 | IV37: 1.34 | IW37: 1.34 | IX37: 1.34 | IY37: 1.34 | JA37: 0.67 | JR37: 12.29 | JS37: 24.58 | JT37: 24.58 | JV37: 24.58 | JW37: 26.9 | JX37: 16.94 | JY37: 4.65 | JZ37: 4.65 | KA37: 2.33 | KT37: 11.8 | KU37: 23.6 | KV37: 23.6 | KX37: 23.6 | KY37: 11.8 | LJ37: 12.63 | LL37: 25.26 | LM37: 12.63 | LO37: 30.17 | LP37: 60.33 | LQ37: 60.33 | LS37: 60.33 | LT37: 60.33 | LU37: 60.33 | LV37: 30.17 | MY37: 7.65 | MZ37: 15.3 | NB37: 7.65 | NW37: 1.27 | NX37: 2.55 | NY37: 2.55 | NZ37: 2.55 | OA37: 1.27
A38: 500 mm diameter pipe | E38: 625 | F38: 0 | G38: 468750 | H38: 468750 | I38: =F38 -> 0 | HD38: 2.98 | HE38: 5.96 | HF38: 5.96 | HG38: 5.96 | HH38: 5.96 | HI38: 5.96 | HK38: 5.96 | HL38: 5.96 | HM38: 5.96 | HN38: 5.96 | HO38: 5.96 | HP38: 5.96 | HR38: 5.96 | HS38: 5.96 | HT38: 5.96 | HU38: 5.96 | HV38: 5.96 | HW38: 5.96 | HY38: 2.98 | IU38: 0.13 | IV38: 0.27 | IW38: 0.27 | IX38: 0.27 | IY38: 0.27 | JA38: 0.13 | JR38: 15.53 | JS38: 31.05 | JT38: 31.05 | JV38: 31.05 | JW38: 34 | JX38: 21.41 | JY38: 5.88 | JZ38: 5.88 | KA38: 2.94 | KT38: 3.05 | KU38: 6.1 | KV38: 6.1 | KX38: 6.1 | KY38: 3.05 | LJ38: 9.04 | LL38: 18.09 | LM38: 9.04 | LO38: 21.6 | LP38: 43.2 | LQ38: 43.2 | LS38: 43.2 | LT38: 43.2 | LU38: 43.2 | LV38: 21.6 | MY38: 3.34 | MZ38: 6.68 | NB38: 3.34 | NW38: 0.56 | NX38: 1.11 | NY38: 1.11 | NZ38: 1.11 | OA38: 0.56
A39: Acess Entrace Ramp | E39: 2 | F39: 0 | G39: 70500 | H39: 70500 | I39: =F39 -> 0 | HU39: 0.2 | HV39: 0.4 | HW39: 0.4 | HY39: 0.4 | HZ39: 0.4 | IA39: 0.2
A40: Air V CH On pipes Dia. 160 mm | E40: 3 | F40: 0 | G40: 28680 | H40: 28680 | I40: =F40 -> 0 | QT40: 0.02 | QV40: 0.08 | QW40: 0.08 | QX40: 0.08 | QY40: 0.09 | QZ40: 0.15 | RA40: 0.15 | RC40: 0.15 | RD40: 0.15 | RE40: 0.15 | RF40: 0.15 | RG40: 0.15 | RH40: 0.14 | RJ40: 0.1 | RK40: 0.1 | RL40: 0.18 | RM40: 0.4 | RN40: 0.4 | RO40: 0.3
A41: Air V CH On pipes Dia. 250 mm | E41: 3 | F41: 0 | G41: 28680 | H41: 28680 | I41: =F41 -> 0 | RS41: 0.01 | RT41: 0.03 | RU41: 0.03 | RV41: 0.05 | RX41: 0.1 | RY41: 0.1 | RZ41: 0.1 | SA41: 0.09 | SB41: 0.05 | SC41: 0.1 | SE41: 0.25 | SF41: 0.23 | SG41: 0.15 | SH41: 0.16 | SI41: 0.2 | SJ41: 0.18 | SP41: 0.13 | SQ41: 0.12 | SS41: 0.11 | ST41: 0.23 | SU41: 0.23 | SV41: 0.2 | SW41: 0.15
A42: Air V CH On pipes Dia. 315 mm | E42: 1 | F42: 0 | G42: 9560 | H42: 9560 | I42: =F42 -> 0 | TZ42: 0.01 | UB42: 0.02 | UC42: 0.02 | UD42: 0.02 | UE42: 0.02 | UF42: 0.03 | UG42: 0.07 | UI42: 0.07 | UJ42: 0.07 | UK42: 0.07 | UL42: 0.07 | UM42: 0.06 | UN42: 0.03 | UP42: 0.03 | UQ42: 0.06 | UR42: 0.13 | US42: 0.13 | UT42: 0.1
A43: Air valve chamber; on 160 mm dia pipeline Depth 1.5- 3 m | E43: 7 | F43: 0 | G43: 66990 | H43: 66990 | I43: =F43 -> 0 | UC43: 0.03 | UD43: 0.1 | UE43: 0.1 | UF43: 0.11 | UG43: 0.15 | UI43: 0.15 | UJ43: 0.15 | UK43: 0.15 | UL43: 0.15 | UM43: 0.15 | UN43: 0.15 | UP43: 0.13 | UQ43: 0.08 | UR43: 0.08 | US43: 0.08 | UT43: 0.13 | UU43: 0.3 | UW43: 0.3 | UX43: 0.3 | UY43: 0.22 | VI43: 0.01 | VK43: 0.05 | VL43: 0.05 | VM43: 0.05 | VN43: 0.06 | VO43: 0.08 | VP43: 0.08 | VR43: 0.08 | VS43: 0.08 | VT43: 0.08 | VU43: 0.07 | VV43: 0.07 | VW43: 0.07 | VY43: 0.07 | VZ43: 0.07 | WA43: 0.07 | WB43: 0.07 | WC43: 0.07 | WD43: 0.07 | WF43: 0.07 | WG43: 0.09 | WH43: 0.16 | WI43: 0.16 | WJ43: 0.17 | WK43: 0.2 | WM43: 0.2 | WN43: 0.17 | WO43: 0.07 | WQ43: 0.07 | WR43: 0.07 | WT43: 0.07 | WU43: 0.07 | WV43: 0.07 | WW43: 0.07 | WX43: 0.07 | WY43: 0.06 | XA43: 0.02 | XB43: 0.02 | XC43: 0.02 | XD43: 0.02 | XE43: 0.02 | XF43: 0.02 | XH43: 0.02 | XI43: 0.02 | XJ43: 0.02 | XK43: 0.06 | XL43: 0.16 | XM43: 0.16 | XO43: 0.16 | XP43: 0.16 | XQ43: 0.12
A44: Chain link fence | E44: 650 | F44: 0 | G44: 113750 | H44: 113750 | I44: =F44 -> 0 | YD44: 4.88 | YE44: 19.5 | YF44: 19.5 | YG44: 19.5 | YH44: 19.5 | YJ44: 20.43 | YK44: 23.21 | YL44: 23.21 | YM44: 23.21 | YN44: 23.21 | YO44: 23.21 | YQ44: 23.21 | YR44: 31.34 | YS44: 55.71 | YT44: 55.71 | YU44: 55.71 | YV44: 55.71 | YX44: 55.71 | YY44: 55.71 | YZ44: 41.79
A45: Conc. lining, incl PC & Expansion Joints | E45: 3000 | F45: 0 | G45: 4935000 | H45: 4935000 | I45: =F45 -> 0 | XD45: 27.69 | XE45: 110.77 | XF45: 83.07 | XI45: 27.69 | XJ45: 110.77 | XK45: 110.77 | XL45: 99.69 | XM45: 66.46 | XO45: 66.46 | XP45: 66.46 | XQ45: 66.46 | XR45: 105.23 | XS45: 221.53 | XT45: 221.53 | XV45: 221.53 | XW45: 221.53 | XX45: 177.22 | XY45: 44.31 | XZ45: 44.31 | YA45: 68.83 | YC45: 142.39 | YD45: 131.32 | YE45: 98.09 | YF45: 98.09 | YG45: 98.09 | YH45: 98.09 | YJ45: 98.09 | YK45: 73.56
A46: Double Catch basin | E46: 20 | F46: 0 | G46: 483000 | H46: 483000 | I46: =F46 -> 0 | U46: 0.1 | W46: 0.1 | X46: 0.1 | Y46: 0.1 | Z46: 0.1 | AA46: 0.1 | BX46: 0.02 | BY46: 0.02 | CA46: 0.02 | CB46: 0.02 | CC46: 0.02 | CD46: 0.02 | CJ46: 0.02 | CK46: 0.02 | CL46: 0.02 | CM46: 0.02 | CO46: 0.02 | CP46: 0.02 | CQ46: 0.02 | CR46: 0.02 | CS46: 0.02 | CT46: 0.02 | CV46: 0.02 | CW46: 0.02 | CX46: 0.02 | CY46: 0.02 | CZ46: 0.02 | DA46: 0.02 | DC46: 0.02 | DD46: 0.02 | DE46: 0.02 | DF46: 0.02 | DG46: 0.02 | DH46: 0.02 | DJ46: 0.02 | DK46: 0.02 | DL46: 0.02 | DM46: 0.02 | DN46: 0.02 | DO46: 0.02 | DQ46: 0.02 | DR46: 0.02 | DS46: 0.02 | DT46: 0.02 | DU46: 0.02 | DV46: 0.02 | DX46: 0.02 | DY46: 0.02 | DZ46: 0.02 | EA46: 0.02 | EB46: 0.02 | EC46: 0.02 | EE46: 0.02 | EF46: 0.02 | EG46: 0.02 | EH46: 0.02 | EI46: 0.02 | EJ46: 0.02 | EL46: 0.02 | EM46: 0.02 | EN46: 0.02 | EO46: 0.02 | EP46: 0.02 | EQ46: 0.02 | ES46: 0.02 | ET46: 0.02 | EZ46: 0.02 | FA46: 0.02 | FB46: 0.02 | FC46: 0.02 | FD46: 0.02 | FE46: 0.02 | FG46: 0.02 | FH46: 0.02 | FI46: 0.02 | FJ46: 0.02 | FK46: 0.02 | FL46: 0.02 | FN46: 0.02 | FO46: 0.02 | FP46: 0.02 | FQ46: 0.02 | FR46: 0.02 | FS46: 0.02 | FU46: 0.02 | FV46: 0.02 | FW46: 0.02 | FX46: 0.02 | FY46: 0.02 | FZ46: 0.02 | GB46: 0.02 | GC46: 0.02 | GD46: 0.02 | GE46: 0.02 | GF46: 0.02 | GG46: 0.02 | GI46: 0.02 | GJ46: 0.02 | GK46: 0.02 | GL46: 0.02 | GM46: 0.02 | GN46: 0.02 | GP46: 0.02 | GQ46: 0.02 | GR46: 0.02 | GS46: 0.02 | GT46: 0.02 | GU46: 0.02 | GW46: 0.02 | GX46: 0.02 | GY46: 0.02 | GZ46: 0.02 | HA46: 0.02 | HB46: 0.02 | HD46: 0.02 | HE46: 0.02 | HF46: 0.02 | HG46: 0.02 | HH46: 0.02 | HI46: 0.02 | HK46: 0.02 | HL46: 0.02 | HM46: 0.02 | HN46: 0.02 | HO46: 0.02 | HP46: 0.02 | HR46: 0.02 | HS46: 0.02 | HT46: 0.02 | HU46: 0.02 | HV46: 0.02 | HW46: 0.02 | HY46: 0.02 | HZ46: 0.02 | IA46: 0.02 | IB46: 0.03 | IC46: 0.04 | ID46: 0.04 | IF46: 0.04 | IG46: 0.04 | IH46: 0.04 | II46: 0.04 | IJ46: 0.05 | IK46: 0.05 | IM46: 0.05 | IN46: 0.05 | IP46: 0.08 | IQ46: 0.1 | IR46: 0.1 | IT46: 0.1 | IU46: 0.06 | IV46: 0.02 | IW46: 0.02 | IX46: 0.02 | IY46: 0.02 | JA46: 0.03 | JB46: 0.03 | JC46: 0.03 | JD46: 0.03 | JE46: 0.03 | JF46: 0.08 | JH46: 0.13 | JI46: 0.13 | JJ46: 0.13 | JK46: 0.13 | JL46: 0.13 | JM46: 0.16 | JO46: 0.19 | JP46: 0.19 | JQ46: 0.19 | JR46: 0.31 | JS46: 0.44 | JT46: 0.44 | JV46: 0.44 | JW46: 0.23 | JX46: 0.02 | JY46: 0.02 | JZ46: 0.02 | KA46: 0.04 | KC46: 0.06 | KD46: 0.06 | KE46: 0.06 | KF46: 0.06 | KG46: 0.06 | KH46: 0.06 | KJ46: 0.06 | KK46: 0.06 | KL46: 0.04 | KM46: 0.02 | KN46: 0.02 | KO46: 0.02 | KQ46: 0.02 | KR46: 0.02 | KS46: 0.02 | KT46: 0.02 | KU46: 0.02 | KV46: 0.02 | KX46: 0.01 | LB46: 0.27 | LC46: 0.54 | LE46: 0.54 | LF46: 0.67 | LG46: 0.8 | LH46: 1.41 | LI46: 2.01 | LJ46: 1 | LM46: 0.1 | LN46: 0.2 | LO46: 0.2 | LP46: 0.2 | LQ46: 0.1 | NF46: 0.02 | NG46: 0.04 | NI46: 0.04 | NJ46: 0.04 | NK46: 0.04 | NL46: 0.04 | NM46: 0.06 | NN46: 0.07 | NP46: 0.07 | NQ46: 0.07 | NR46: 0.12 | NS46: 0.17 | NT46: 0.17 | NU46: 0.17 | NW46: 0.08 | OA46: 0.01 | OB46: 0.02 | OD46: 0.02 | OE46: 0.02 | OF46: 0.02 | OG46: 0.02 | OH46: 0.02 | OI46: 0.01 | YA46: 0.06 | YC46: 0.25 | YD46: 0.25 | YE46: 0.25 | YF46: 0.25 | YG46: 0.25 | YH46: 0.25 | YJ46: 0.25 | YK46: 0.19
A47: Double swing main entrance gate | E47: 2 | F47: 0 | G47: 117500 | H47: 117500 | I47: =F47 -> 0 | YZ47: 0.17 | ZA47: 0.67 | ZB47: 0.67 | ZC47: 0.5
A48: Drawpit incl. cover | E48: 23 | F48: 0 | G48: 135700 | H48: 135700 | I48: =F48 -> 0 | VS48: 0.05 | VT48: 0.2 | VU48: 0.2 | VV48: 0.24 | VW48: 0.38 | VY48: 0.38 | VZ48: 0.38 | WA48: 0.38 | WB48: 0.38 | WC48: 0.38 | WD48: 0.38 | WF48: 0.39 | WG48: 0.45 | WH48: 0.45 | WI48: 0.45 | WJ48: 0.42 | WK48: 0.27 | WM48: 0.12 | WN48: 0.2 | WO48: 0.45 | WQ48: 0.42 | WR48: 0.3 | WT48: 0.2 | WU48: 0.2 | WV48: 0.17 | WW48: 0.07 | WX48: 0.07 | WY48: 0.05 | XB48: 0.28 | XC48: 0.83 | XF48: 0.46 | XH48: 1.93 | XI48: 2.13 | XJ48: 1.65 | XK48: 1.1 | XL48: 1.1 | XM48: 0.92 | XO48: 0.45 | XP48: 0.7 | XQ48: 0.61 | XR48: 0.33 | XS48: 0.33 | XT48: 0.33 | XV48: 0.32 | XW48: 0.3 | XX48: 0.3 | XY48: 0.3 | XZ48: 0.25 | YA48: 0.08 | YC48: 0.08 | YD48: 0.08 | YE48: 0.08 | YF48: 0.06
A49: Earthing | E49: 13 | F49: 0 | G49: 152750 | H49: 152750 | I49: =F49 -> 0 | YN49: 0.33 | YO49: 0.98 | YR49: 0.76 | YS49: 3.03 | YT49: 3.03 | YU49: 2.49 | YV49: 0.87 | YX49: 0.87 | YY49: 0.65
A50: Excavation | E50: 37125 | F50: 22506.58 | G50: 2227500 | H50: 2227500 | I50: =F50 -> 22506.58 | AW50: 189.2 | AY50: 189.2 | AZ50: 189.2 | BA50: 141.9 | BB50: 141.9 | BC50: 141.9 | BD50: 141.9 | BF50: 141.9 | BG50: 141.9 | BH50: 141.9 | BI50: 141.9 | BJ50: 141.9 | BK50: 141.9 | BM50: 141.9 | BN50: 141.9 | BO50: 141.9 | BP50: 141.9 | BQ50: 141.9 | BR50: 141.9 | BT50: 141.9 | BU50: 141.9 | BV50: 141.9 | BW50: 141.9 | BX50: 120.97 | BY50: 120.97 | CA50: 120.97 | CB50: 120.97 | CC50: 120.97 | CD50: 120.97 | CJ50: 161.29 | CK50: 161.29 | CL50: 161.29 | CM50: 161.29 | CO50: 161.29 | CP50: 161.29 | CQ50: 161.29 | CR50: 161.29 | CS50: 161.29 | CT50: 161.29 | CV50: 161.29 | CW50: 161.29 | CX50: 161.29 | CY50: 168.11 | CZ50: 174.92 | DA50: 174.92 | DC50: 174.92 | DD50: 174.92 | DE50: 174.92 | DF50: 174.92 | DG50: 174.92 | DH50: 174.92 | DJ50: 174.92 | DK50: 174.92 | DL50: 174.92 | DM50: 174.92 | DN50: 174.92 | DO50: 174.92 | DQ50: 174.92 | DR50: 174.92 | DS50: 174.92 | DT50: 162.89 | DU50: 150.86 | DV50: 150.86 | DX50: 150.86 | DY50: 150.86 | DZ50: 150.86 | EA50: 150.86 | EB50: 150.86 | EC50: 150.86 | EE50: 150.86 | EF50: 150.86 | EG50: 150.86 | EH50: 150.86 | EI50: 150.86 | EJ50: 150.86 | EL50: 150.86 | EM50: 150.86 | EN50: 150.86 | EO50: 150.86 | EP50: 150.86 | EQ50: 691.69 | ES50: 1232.52 | ET50: 1232.52 | EZ50: 1232.52 | FA50: 1232.52 | FB50: 1232.52 | FC50: 1232.52 | FD50: 1232.52 | FE50: 1232.52 | FG50: 1232.52 | FH50: 1232.52 | FI50: 1232.52 | FJ50: 1232.52 | FK50: 1232.52 | FL50: 1232.52 | FN50: 1232.52 | FO50: 1232.52 | FP50: 1232.52 | FQ50: 1232.52 | FR50: 1232.52 | FS50: 616.26
A51: Filling | E51: 16500 | F51: 0 | G51: 825000 | H51: 825000 | I51: =F51 -> 0 | FS51: 750 | FU51: 1500 | FV51: 1500 | FW51: 1500 | FX51: 1500 | FY51: 1500 | FZ51: 1500 | GB51: 1500 | GC51: 1500 | GD51: 1500 | GE51: 1500 | GF51: 750
A52: Filling with imported Material | E52: 1856 | F52: 0 | G52: 129920 | H52: 129920 | I52: =F52 -> 0 | IA52: 185.6 | IB52: 371.2 | IC52: 371.2 | ID52: 371.2 | IF52: 371.2 | IG52: 185.6
A53: Flow meter chamber on 630 mm dia pipeline Depth 0- 1.5 m | E53: 1 | F53: 0 | G53: 9570 | H53: 9570 | I53: =F53 -> 0 | AK53: 0.01 | AL53: 0.01 | AM53: 0.01 | XB53: 0.01 | XC53: 0.02 | XD53: 0.02 | XE53: 0.02 | XF53: 0.02 | XH53: 0.02 | XI53: 0.02 | XJ53: 0.02 | XK53: 0.02 | XL53: 0.02 | XM53: 0.02 | XO53: 0.03 | XP53: 0.03 | XQ53: 0.03 | XR53: 0.03 | XS53: 0.02 | XT53: 0.02 | XV53: 0.02 | XW53: 0.04 | XX53: 0.12 | XY53: 0.12 | XZ53: 0.12 | YA53: 0.09 | ZC53: 0 | ZE53: 0.01 | ZF53: 0.01 | ZG53: 0.01 | ZH53: 0.01 | ZI53: 0.01 | ZJ53: 0.01 | ZL53: 0.01 | ZM53: 0.01
A54: LED Lumin 110 W | E54: 193 | F54: 0 | G54: 675500 | H54: 675500 | I54: =F54 -> 0 | AB54: 0.97 | AD54: 0.97 | AE54: 0.97 | AF54: 0.97 | AG54: 0.97 | AH54: 0.97 | TG54: 0.14 | TH54: 0.55 | TI54: 0.55 | TJ54: 0.55 | TK54: 0.55 | TL54: 0.55 | TN54: 0.55 | TO54: 0.55 | TP54: 0.55 | TQ54: 0.55 | TR54: 0.55 | TS54: 0.55 | TU54: 0.55 | TV54: 0.55 | TW54: 0.55 | TX54: 0.55 | TY54: 0.55 | TZ54: 0.55 | UB54: 0.55 | UC54: 0.55 | UD54: 0.55 | UE54: 0.55 | UF54: 0.55 | UG54: 0.55 | UI54: 0.55 | UJ54: 0.55 | UK54: 0.55 | UL54: 0.55 | UM54: 0.55 | UN54: 0.55 | UP54: 0.55 | UQ54: 0.55 | UR54: 0.55 | US54: 0.55 | UT54: 0.55 | UU54: 0.55 | UW54: 0.55 | UX54: 0.55 | UY54: 0.55 | UZ54: 0.55 | VA54: 0.55 | VB54: 0.55 | VD54: 0.55 | VE54: 0.55 | VF54: 0.55 | VG54: 0.55 | VH54: 0.55 | VI54: 0.55 | VK54: 0.55 | VL54: 0.55 | VM54: 0.55 | VN54: 0.55 | VO54: 0.55 | VP54: 0.55 | VR54: 0.55 | VS54: 0.55 | VT54: 0.55 | VU54: 0.55 | VV54: 0.55 | VW54: 0.55 | VY54: 0.55 | VZ54: 0.55 | WA54: 0.55 | WB54: 0.55 | WC54: 0.55 | WD54: 0.55 | WF54: 0.55 | WG54: 0.55 | WH54: 0.55 | WI54: 0.55 | WJ54: 0.41 | WX54: 1.27 | WY54: 5.06 | XA54: 6.07 | XB54: 9.08 | XC54: 9.08 | XD54: 9.08 | XE54: 8.08 | XF54: 5.9 | XH54: 8.41 | XI54: 7.15 | XJ54: 2.51 | YD54: 1.82 | YE54: 7.27 | YF54: 7.27 | YG54: 7.27 | YH54: 7.27 | YJ54: 7.27 | YK54: 7.27 | YL54: 5.45 | YV54: 0.56 | YX54: 2.23 | YY54: 2.23 | YZ54: 1.68 | ZM54: 0.48 | ZN54: 1.93 | ZO54: 1.93 | ZP54: 1.93 | ZQ54: 1.93 | ZS54: 1.93 | ZT54: 1.93 | ZU54: 1.93 | ZV54: 1.93 | ZW54: 1.93 | ZX54: 1.45
A55: Outfall 1000 | E55: 1 | F55: 0 | G55: 18800 | H55: 18800 | I55: =F55 -> 0 | GM55: 0.03 | GN55: 0.06 | GP55: 0.06 | GQ55: 0.06 | GR55: 0.06 | GS55: 0.18 | GT55: 0.3 | GU55: 0.16 | GW55: 0.02 | GX55: 0.02 | GY55: 0.02 | GZ55: 0.02 | HA55: 0.01
A56: Outfall 1400 | E56: 1 | F56: 0 | G56: 23500 | H56: 23500 | I56: =F56 -> 0 | GG56: 0.03 | GI56: 0.06 | GJ56: 0.06 | GK56: 0.06 | GL56: 0.06 | GM56: 0.18 | GN56: 0.3 | GP56: 0.16 | GQ56: 0.02 | GR56: 0.02 | GS56: 0.02 | GT56: 0.02 | GU56: 0.01
A57: Pipe encasement dia 200mm | E57: 215 | F57: 0 | G57: 202100 | H57: 202100 | I57: =F57 -> 0 | LN57: 1.89 | LO57: 3.77 | LP57: 3.77 | LQ57: 3.77 | LS57: 3.77 | LT57: 3.77 | LU57: 8.17 | LV57: 12.57 | LW57: 12.57 | LX57: 7.79 | LZ57: 3.02 | MA57: 3.02 | MB57: 3.02 | MC57: 3.02 | MD57: 5 | ME57: 6.98 | MG57: 6.98 | MH57: 6.98 | MI57: 6.98 | MJ57: 6.98 | MK57: 9.31 | ML57: 11.63 | MN57: 11.63 | MO57: 11.63 | MP57: 11.63 | MQ57: 11.63 | MR57: 8.14 | MS57: 4.65 | MU57: 4.65 | MV57: 4.65 | MW57: 4.65 | MX57: 4.65 | MY57: 2.33
A58: Pipe encasement dia 250mm | E58: 215 | F58: 0 | G58: 202100 | H58: 202100 | I58: =F58 -> 0 | KL58: 0.64 | KM58: 1.29 | KN58: 1.29 | KO58: 1.29 | KQ58: 1.29 | KR58: 1.29 | KS58: 1.29 | KT58: 1.29 | KU58: 1.29 | KV58: 2.02 | KX58: 2.76 | KY58: 2.76 | KZ58: 2.76 | LA58: 2.76 | LB58: 2.76 | LC58: 2.76 | LE58: 1.86 | LF58: 0.97 | LG58: 0.97 | LH58: 0.97 | LI58: 0.97 | LJ58: 0.97 | LL58: 0.97 | LM58: 0.97 | LN58: 0.48 | LU58: 3.61 | LV58: 7.21 | LW58: 7.21 | LX58: 7.21 | LZ58: 7.21 | MA58: 7.21 | MB58: 9.62 | MC58: 12.02 | MD58: 12.02 | ME58: 12.02 | MG58: 12.02 | MH58: 12.02 | MI58: 8.42 | MJ58: 4.81 | MK58: 4.81 | ML58: 4.81 | MN58: 4.81 | MO58: 4.81 | MP58: 2.4 | OP58: 0.97 | OR58: 1.45 | OS58: 1.45 | OT58: 1.45 | OU58: 1.45 | OV58: 1.45 | OW58: 1.45 | OY58: 6.03 | OZ58: 6.03 | PA58: 4.42 | PB58: 1.21 | PC58: 1.21 | PD58: 1.21 | PF58: 1.21 | PG58: 1.21
A59: Pipe encasement dia 315mm | E59: 215 | F59: 0 | G59: 202100 | H59: 202100 | I59: =F59 -> 0 | LV59: 1.08 | LW59: 2.17 | LX59: 2.17 | LZ59: 2.17 | MA59: 2.17 | MB59: 2.17 | MC59: 4.7 | MD59: 7.22 | ME59: 7.22 | MG59: 4.48 | MH59: 1.73 | MI59: 1.73 | MJ59: 1.73 | MK59: 1.73 | ML59: 0.87 | OE59: 3.22 | OF59: 6.44 | OG59: 6.44 | OH59: 6.44 | OI59: 6.44 | OL59: 6.44 | OM59: 6.44 | ON59: 6.44 | OO59: 10.37 | OP59: 14.31 | OR59: 10.73 | OS59: 10.73 | OT59: 10.73 | OU59: 10.73 | OV59: 10.73 | OW59: 10.73 | OY59: 3.68 | OZ59: 3.68 | PA59: 3.68 | PB59: 3.68 | PC59: 3.68 | PD59: 3.68 | PF59: 3.68 | PG59: 3.68 | PH59: 3.68 | PI59: 1.23
A60: Pot Air V on pipes with dia(160) mm. | E60: 4 | F60: 0.11 | G60: 11280 | H60: 11280 | I60: =F60 -> 0.11 | AF60: 0.02 | AG60: 0.02 | AH60: 0.02 | AK60: 0.02 | AL60: 0.02 | AM60: 0.02 | AN60: 0.02 | AO60: 0.02 | NN60: 0 | NP60: 0.01 | NQ60: 0.01 | NR60: 0.01 | NS60: 0.01 | NT60: 0.01 | NU60: 0.01 | NW60: 0.01 | NX60: 0.01 | NY60: 0.01 | NZ60: 0.01 | OA60: 0.01 | OB60: 0.01 | OD60: 0.01 | OE60: 0.01 | OF60: 0.01 | OG60: 0.01 | OH60: 0.01 | OI60: 0.01 | OL60: 0.01 | OM60: 0.01 | ON60: 0.01 | OO60: 0.01 | OP60: 0.01 | OR60: 0.01 | OS60: 0.01 | OT60: 0.01 | OU60: 0.01 | OV60: 0.01 | OW60: 0.01 | OY60: 0.01 | OZ60: 0.01 | PA60: 0.01 | PB60: 0.01 | PC60: 0.01 | PD60: 0.01 | PF60: 0.01 | PG60: 0.01 | PH60: 0.01 | PI60: 0.01 | PJ60: 0.01 | PK60: 0.01 | PM60: 0.01 | PN60: 0.01 | PO60: 0.01 | PP60: 0.01 | PQ60: 0.01 | PR60: 0.01 | PT60: 0.01 | PY60: 0.01 | QA60: 0.01 | QB60: 0.01 | QC60: 0.01 | QD60: 0.01 | QE60: 0.01 | QF60: 0.01 | QH60: 0.01 | QI60: 0.01 | QJ60: 0.01 | QK60: 0.01 | QL60: 0.01 | QM60: 0.01 | QO60: 0.01 | QP60: 0.01 | QQ60: 0.01 | QR60: 0.01 | QS60: 0.01 | QT60: 0.02 | QV60: 0.07 | QW60: 0.07 | QX60: 0.07 | QY60: 0.09 | QZ60: 0.14 | RA60: 0.14 | RC60: 0.14 | RD60: 0.14 | RE60: 0.14 | RF60: 0.14 | RG60: 0.14 | RH60: 0.13 | RJ60: 0.09 | RK60: 0.09 | RL60: 0.16 | RM60: 0.37 | RN60: 0.37 | RO60: 0.28 | RQ60: 0.01 | RR60: 0.01 | RS60: 0.01 | RT60: 0.01 | RU60: 0.01 | RV60: 0.01 | RX60: 0.01 | RY60: 0.01 | RZ60: 0.01 | SA60: 0.01 | SB60: 0.01 | SC60: 0.01 | SE60: 0.01 | SF60: 0.01 | SG60: 0.01 | SH60: 0.01 | SI60: 0.01 | SJ60: 0.01 | SP60: 0.01 | SQ60: 0.01 | SS60: 0.01 | YT60: 0.01 | YU60: 0.05 | YV60: 0.05 | YX60: 0.05 | YY60: 0.05 | YZ60: 0.05 | ZA60: 0.05 | ZB60: 0.05 | ZC60: 0.04
A61: Pot Air V on pipes with dia(250) mm. | E61: 2 | F61: 0.05 | G61: 5640 | H61: 5640 | I61: =F61 -> 0.05 | AF61: 0.01 | AG61: 0.01 | AH61: 0.01 | AK61: 0.01 | AL61: 0.01 | AM61: 0.01 | AN61: 0.01 | AO61: 0.01 | NN61: 0 | NP61: 0 | NQ61: 0 | NR61: 0 | NS61: 0 | NT61: 0 | NU61: 0 | NW61: 0 | NX61: 0 | NY61: 0 | NZ61: 0 | OA61: 0 | OB61: 0 | OD61: 0 | OE61: 0 | OF61: 0 | OG61: 0 | OH61: 0 | OI61: 0 | OL61: 0 | OM61: 0 | ON61: 0 | OO61: 0 | OP61: 0 | OR61: 0 | OS61: 0 | OT61: 0 | OU61: 0 | OV61: 0 | OW61: 0 | OY61: 0 | OZ61: 0 | PA61: 0 | PB61: 0 | PC61: 0 | PD61: 0 | PF61: 0 | PG61: 0 | PH61: 0 | PI61: 0 | PJ61: 0 | PK61: 0 | PM61: 0 | PN61: 0 | PO61: 0 | PP61: 0 | PQ61: 0 | PR61: 0 | PT61: 0 | PY61: 0 | QA61: 0 | QB61: 0 | QC61: 0 | QD61: 0 | QE61: 0 | QF61: 0 | QH61: 0 | QI61: 0 | QJ61: 0 | QK61: 0 | QL61: 0 | QM61: 0 | QO61: 0 | QP61: 0 | QQ61: 0 | QR61: 0 | QS61: 0 | QT61: 0 | QV61: 0 | QW61: 0 | QX61: 0 | QY61: 0 | QZ61: 0 | RA61: 0 | RC61: 0 | RD61: 0 | RE61: 0 | RF61: 0 | RG61: 0 | RH61: 0 | RJ61: 0 | RK61: 0 | RL61: 0 | RM61: 0 | RN61: 0 | RO61: 0 | RQ61: 0 | RR61: 0 | RS61: 0.01 | RT61: 0.02 | RU61: 0.02 | RV61: 0.03 | RX61: 0.05 | RY61: 0.05 | RZ61: 0.05 | SA61: 0.04 | SB61: 0.03 | SC61: 0.05 | SE61: 0.12 | SF61: 0.1 | SG61: 0.07 | SH61: 0.08 | SI61: 0.09 | SJ61: 0.09 | SP61: 0.06 | SQ61: 0.06 | SS61: 0.05 | ST61: 0.1 | SU61: 0.1 | SV61: 0.09 | SW61: 0.07 | YT61: 0.01 | YU61: 0.03 | YV61: 0.03 | YX61: 0.03 | YY61: 0.03 | YZ61: 0.03 | ZA61: 0.03 | ZB61: 0.03 | ZC61: 0.02
A62: Pot Air V on pipes with dia(315) mm. | E62: 1 | F62: 0.03 | G62: 2820 | H62: 2820 | I62: =F62 -> 0.03 | AF62: 0 | AG62: 0 | AH62: 0 | AK62: 0 | AL62: 0 | AM62: 0 | AN62: 0 | AO62: 0 | NN62: 0 | NP62: 0 | NQ62: 0 | NR62: 0 | NS62: 0 | NT62: 0 | NU62: 0 | NW62: 0 | NX62: 0 | NY62: 0 | NZ62: 0 | OA62: 0 | OB62: 0 | OD62: 0 | OE62: 0 | OF62: 0 | OG62: 0 | OH62: 0 | OI62: 0 | OL62: 0 | OM62: 0 | ON62: 0 | OO62: 0 | OP62: 0 | OR62: 0 | OS62: 0 | OT62: 0 | OU62: 0 | OV62: 0 | OW62: 0 | OY62: 0 | OZ62: 0 | PA62: 0 | PB62: 0 | PC62: 0 | PD62: 0 | PF62: 0 | PG62: 0 | PH62: 0 | PI62: 0 | PJ62: 0 | PK62: 0 | PM62: 0 | PN62: 0 | PO62: 0 | PP62: 0 | PQ62: 0 | PR62: 0 | PT62: 0 | PY62: 0 | QA62: 0 | QB62: 0 | QC62: 0 | QD62: 0 | QE62: 0 | QF62: 0 | QH62: 0 | QI62: 0 | QJ62: 0 | QK62: 0 | QL62: 0 | QM62: 0 | QO62: 0 | QP62: 0 | QQ62: 0 | QR62: 0 | QS62: 0 | QT62: 0 | QV62: 0 | QW62: 0 | QX62: 0 | QY62: 0 | QZ62: 0 | RA62: 0 | RC62: 0 | RD62: 0 | RE62: 0 | RF62: 0 | RG62: 0 | RH62: 0 | RJ62: 0 | RK62: 0 | RL62: 0 | RM62: 0 | RN62: 0 | RO62: 0 | RQ62: 0 | RR62: 0 | RS62: 0 | RT62: 0 | RU62: 0 | RV62: 0 | RX62: 0 | RY62: 0 | RZ62: 0 | SA62: 0 | SB62: 0 | SC62: 0 | SE62: 0 | SF62: 0 | SG62: 0 | SH62: 0 | SI62: 0 | SJ62: 0 | SP62: 0 | SQ62: 0 | SS62: 0 | TZ62: 0.01 | UB62: 0.03 | UC62: 0.03 | UD62: 0.03 | UE62: 0.03 | UF62: 0.03 | UG62: 0.02 | UI62: 0.02 | UJ62: 0.02 | UK62: 0.02 | UL62: 0.02 | UM62: 0.03 | UN62: 0.04 | UP62: 0.04 | UQ62: 0.06 | UR62: 0.09 | US62: 0.09 | UT62: 0.07 | YT62: 0 | YU62: 0.01 | YV62: 0.01 | YX62: 0.01 | YY62: 0.01 | YZ62: 0.01 | ZA62: 0.01 | ZB62: 0.01 | ZC62: 0.01
A63: Pot Butterfly Valves Dia. 315 mm | E63: 1 | F63: 0.03 | G63: 13630 | H63: 13630 | I63: =F63 -> 0.03 | AF63: 0 | AG63: 0 | AH63: 0 | AK63: 0 | AL63: 0 | AM63: 0 | AN63: 0 | AO63: 0 | NN63: 0 | NP63: 0 | NQ63: 0 | NR63: 0 | NS63: 0 | NT63: 0 | NU63: 0 | NW63: 0 | NX63: 0 | NY63: 0 | NZ63: 0 | OA63: 0 | OB63: 0 | OD63: 0 | OE63: 0 | OF63: 0 | OG63: 0 | OH63: 0 | OI63: 0 | OL63: 0 | OM63: 0 | ON63: 0 | OO63: 0 | OP63: 0 | OR63: 0 | OS63: 0 | OT63: 0 | OU63: 0 | OV63: 0 | OW63: 0 | OY63: 0 | OZ63: 0 | PA63: 0 | PB63: 0 | PC63: 0 | PD63: 0 | PF63: 0 | PG63: 0 | PH63: 0 | PI63: 0 | PJ63: 0 | PK63: 0 | PM63: 0 | PN63: 0 | PO63: 0 | PP63: 0 | PQ63: 0 | PR63: 0 | PT63: 0 | PY63: 0 | QA63: 0 | QB63: 0 | QC63: 0 | QD63: 0 | QE63: 0 | QF63: 0 | QH63: 0 | QI63: 0 | QJ63: 0 | QK63: 0.02 | QL63: 0.05 | QM63: 0.01 | QO63: 0.05 | QP63: 0.05 | QQ63: 0.05 | QR63: 0.05 | QS63: 0.05 | QT63: 0.04 | QV63: 0.04 | QW63: 0.06 | QX63: 0.14 | QY63: 0.1 | QZ63: 0 | RA63: 0 | RC63: 0 | RD63: 0 | RE63: 0 | RF63: 0 | RG63: 0 | RH63: 0 | RJ63: 0 | RK63: 0 | RL63: 0 | RM63: 0 | RN63: 0 | RO63: 0 | RQ63: 0 | RR63: 0 | RS63: 0 | RT63: 0 | RU63: 0 | RV63: 0 | RX63: 0 | RY63: 0 | RZ63: 0 | SA63: 0 | SB63: 0 | SC63: 0 | SE63: 0 | SF63: 0 | SG63: 0 | SH63: 0 | SI63: 0 | SJ63: 0 | SP63: 0 | SQ63: 0 | SS63: 0 | YT63: 0 | YU63: 0.01 | YV63: 0.01 | YX63: 0.01 | YY63: 0.01 | YZ63: 0.01 | ZA63: 0.01 | ZB63: 0.01 | ZC63: 0.01
A64: Pot Gate Valves Dia. 160 mm | E64: 12 | F64: 0.32 | G64: 36720 | H64: 36720 | I64: =F64 -> 0.32 | AF64: 0.05 | AG64: 0.05 | AH64: 0.05 | AK64: 0.05 | AL64: 0.05 | AM64: 0.05 | AN64: 0.05 | AO64: 0.05 | NN64: 0.01 | NP64: 0.02 | NQ64: 0.02 | NR64: 0.02 | NS64: 0.02 | NT64: 0.02 | NU64: 0.02 | NW64: 0.02 | NX64: 0.02 | NY64: 0.02 | NZ64: 0.02 | OA64: 0.02 | OB64: 0.02 | OD64: 0.02 | OE64: 0.02 | OF64: 0.02 | OG64: 0.02 | OH64: 0.02 | OI64: 0.02 | OL64: 0.02 | OM64: 0.02 | ON64: 0.02 | OO64: 0.02 | OP64: 0.02 | OR64: 0.02 | OS64: 0.02 | OT64: 0.02 | OU64: 0.02 | OV64: 0.02 | OW64: 0.02 | OY64: 0.02 | OZ64: 0.02 | PA64: 0.02 | PB64: 0.02 | PC64: 0.02 | PD64: 0.02 | PF64: 0.02 | PG64: 0.02 | PH64: 0.02 | PI64: 0.02 | PJ64: 0.02 | PK64: 0.02 | PM64: 0.02 | PN64: 0.02 | PO64: 0.02 | PP64: 0.02 | PQ64: 0.02 | PR64: 0.02 | PT64: 0.02 | PY64: 0.02 | QA64: 0.02 | QB64: 0.02 | QC64: 0.02 | QD64: 0.02 | QE64: 0.02 | QF64: 0.02 | QH64: 0.02 | QI64: 0.02 | QJ64: 0.02 | QK64: 0.26 | QL64: 0.96 | QM64: 0.96 | QO64: 0.96 | QP64: 0.79 | QQ64: 0.26 | QR64: 0.26 | QS64: 0.26 | QT64: 0.2 | QV64: 0.02 | QW64: 0.02 | QX64: 0.02 | QY64: 0.02 | QZ64: 0.02 | RA64: 0.02 | RC64: 0.02 | RD64: 0.02 | RE64: 0.02 | RF64: 0.02 | RG64: 0.02 | RH64: 0.16 | RJ64: 0.56 | RK64: 0.46 | RL64: 0.16 | RM64: 0.12 | RN64: 0.02 | RO64: 0.02 | RQ64: 0.06 | RR64: 0.16 | RS64: 0.16 | RT64: 0.16 | RU64: 0.13 | RV64: 0.06 | RX64: 0.06 | RY64: 0.06 | RZ64: 0.05 | SA64: 0.02 | SB64: 0.02 | SC64: 0.02 | SE64: 0.02 | SF64: 0.02 | SG64: 0.02 | SH64: 0.02 | SI64: 0.02 | SJ64: 0.02 | SP64: 0.02 | SQ64: 0.02 | SS64: 0.02 | UM64: 0.09 | UN64: 0.36 | UP64: 0.36 | UQ64: 0.29 | UR64: 0.09 | US64: 0.09 | UT64: 0.07 | YT64: 0.04 | YU64: 0.15 | YV64: 0.15 | YX64: 0.15 | YY64: 0.15 | YZ64: 0.15 | ZA64: 0.15 | ZB64: 0.15 | ZC64: 0.11
A65: Pot Gate Valves Dia. 200 mm | E65: 2 | F65: 0.05 | G65: 8460 | H65: 8460 | I65: =F65 -> 0.05 | AF65: 0.01 | AG65: 0.01 | AH65: 0.01 | AK65: 0.01 | AL65: 0.01 | AM65: 0.01 | AN65: 0.01 | AO65: 0.01 | NN65: 0 | NP65: 0 | NQ65: 0 | NR65: 0 | NS65: 0 | NT65: 0 | NU65: 0 | NW65: 0 | NX65: 0 | NY65: 0 | NZ65: 0 | OA65: 0 | OB65: 0 | OD65: 0 | OE65: 0 | OF65: 0 | OG65: 0 | OH65: 0 | OI65: 0 | OL65: 0 | OM65: 0 | ON65: 0 | OO65: 0 | OP65: 0 | OR65: 0 | OS65: 0 | OT65: 0 | OU65: 0 | OV65: 0 | OW65: 0 | OY65: 0 | OZ65: 0 | PA65: 0 | PB65: 0 | PC65: 0 | PD65: 0 | PF65: 0 | PG65: 0 | PH65: 0 | PI65: 0 | PJ65: 0 | PK65: 0 | PM65: 0 | PN65: 0 | PO65: 0 | PP65: 0 | PQ65: 0 | PR65: 0 | PT65: 0 | PY65: 0 | QA65: 0 | QB65: 0 | QC65: 0 | QD65: 0 | QE65: 0 | QF65: 0 | QH65: 0 | QI65: 0 | QJ65: 0 | QK65: 0 | QL65: 0 | QM65: 0 | QO65: 0 | QP65: 0 | QQ65: 0 | QR65: 0 | QS65: 0 | QT65: 0 | QV65: 0 | QW65: 0 | QX65: 0 | QY65: 0 | QZ65: 0 | RA65: 0 | RC65: 0 | RD65: 0 | RE65: 0 | RF65: 0 | RG65: 0 | RH65: 0 | RJ65: 0 | RK65: 0 | RL65: 0 | RM65: 0 | RN65: 0 | RO65: 0 | RQ65: 0 | RR65: 0 | RS65: 0 | RT65: 0 | RU65: 0.07 | RV65: 0.27 | RX65: 0.27 | RY65: 0.27 | RZ65: 0.22 | SA65: 0.07 | SB65: 0.07 | SC65: 0.07 | SE65: 0.05 | SF65: 0 | SG65: 0 | SH65: 0 | SI65: 0 | SJ65: 0 | SP65: 0 | SQ65: 0 | SS65: 0 | YT65: 0.01 | YU65: 0.03 | YV65: 0.03 | YX65: 0.03 | YY65: 0.03 | YZ65: 0.03 | ZA65: 0.03 | ZB65: 0.03 | ZC65: 0.02
A66: Pot Gate Valves Dia. 225 mm | E66: 3 | F66: 0.08 | G66: 18330 | H66: 18330 | I66: =F66 -> 0.08 | AF66: 0.01 | AG66: 0.01 | AH66: 0.01 | AK66: 0.01 | AL66: 0.01 | AM66: 0.01 | AN66: 0.01 | AO66: 0.01 | NN66: 0 | NP66: 0.01 | NQ66: 0.01 | NR66: 0.01 | NS66: 0.01 | NT66: 0.01 | NU66: 0.01 | NW66: 0.01 | NX66: 0.01 | NY66: 0.01 | NZ66: 0.01 | OA66: 0.01 | OB66: 0.01 | OD66: 0.01 | OE66: 0.01 | OF66: 0.01 | OG66: 0.01 | OH66: 0.01 | OI66: 0.01 | OL66: 0.01 | OM66: 0.01 | ON66: 0.01 | OO66: 0.01 | OP66: 0.01 | OR66: 0 | OS66: 0 | OT66: 0 | OU66: 0 | OV66: 0 | OW66: 0 | OY66: 0 | OZ66: 0 | PA66: 0 | PB66: 0 | PC66: 0 | PD66: 0 | PF66: 0 | PG66: 0 | PH66: 0 | PI66: 0 | PJ66: 0 | PK66: 0 | PM66: 0 | PN66: 0 | PO66: 0 | PP66: 0 | PQ66: 0 | PR66: 0 | PT66: 0 | PY66: 0.01 | QA66: 0.01 | QB66: 0.01 | QC66: 0.01 | QD66: 0.01 | QE66: 0.01 | QF66: 0.01 | QH66: 0.01 | QI66: 0.01 | QJ66: 0.01 | QK66: 0.01 | QL66: 0.01 | QM66: 0.01 | QO66: 0.01 | QP66: 0.01 | QQ66: 0.01 | QR66: 0.01 | QS66: 0.01 | QT66: 0.01 | QV66: 0.01 | QW66: 0.01 | QX66: 0.01 | QY66: 0.01 | QZ66: 0.01 | RA66: 0.01 | RC66: 0.01 | RD66: 0.01 | RE66: 0.01 | RF66: 0.01 | RG66: 0.01 | RH66: 0.01 | RJ66: 0.01 | RK66: 0.14 | RL66: 0.54 | RM66: 0.44 | RN66: 0.14 | RO66: 0.11 | RQ66: 0.01 | RR66: 0.01 | RS66: 0.01 | RT66: 0.01 | RU66: 0.01 | RV66: 0.01 | RX66: 0.01 | RY66: 0.01 | RZ66: 0.01 | SA66: 0.01 | SB66: 0.01 | SC66: 0.01 | SE66: 0.01 | SF66: 0.01 | SG66: 0.01 | SH66: 0.01 | SI66: 0.01 | SJ66: 0.01 | SP66: 0.01 | SQ66: 0.01 | SS66: 0 | TO66: 0.03 | TP66: 0.13 | TQ66: 0.13 | TR66: 0.13 | TS66: 0.11 | TU66: 0.03 | TV66: 0.03 | TW66: 0.03 | TX66: 0.03 | YT66: 0.01 | YU66: 0.04 | YV66: 0.04 | YX66: 0.04 | YY66: 0.04 | YZ66: 0.04 | ZA66: 0.04 | ZB66: 0.04 | ZC66: 0.03
A67: Pot Gate Valves Dia. 250 mm | E67: 3 | F67: 0.08 | G67: 21150 | H67: 21150 | I67: =F67 -> 0.08 | AF67: 0.01 | AG67: 0.01 | AH67: 0.01 | AK67: 0.01 | AL67: 0.01 | AM67: 0.01 | AN67: 0.01 | AO67: 0.01 | NN67: 0 | NP67: 0.01 | NQ67: 0.01 | NR67: 0.01 | NS67: 0.01 | NT67: 0.01 | NU67: 0.01 | NW67: 0.01 | NX67: 0.01 | NY67: 0.01 | NZ67: 0.01 | OA67: 0.01 | OB67: 0.01 | OD67: 0.01 | OE67: 0.01 | OF67: 0.01 | OG67: 0.01 | OH67: 0.01 | OI67: 0.01 | OL67: 0.01 | OM67: 0.01 | ON67: 0.01 | OO67: 0.01 | OP67: 0.01 | OR67: 0 | OS67: 0 | OT67: 0 | OU67: 0 | OV67: 0 | OW67: 0 | OY67: 0 | OZ67: 0 | PA67: 0 | PB67: 0 | PC67: 0 | PD67: 0 | PF67: 0 | PG67: 0 | PH67: 0 | PI67: 0 | PJ67: 0 | PK67: 0 | PM67: 0 | PN67: 0 | PO67: 0 | PP67: 0 | PQ67: 0 | PR67: 0 | PT67: 0 | PY67: 0.01 | QA67: 0.01 | QB67: 0.01 | QC67: 0.01 | QD67: 0.01 | QE67: 0.01 | QF67: 0.01 | QH67: 0.01 | QI67: 0.01 | QJ67: 0.01 | QK67: 0.01 | QL67: 0.01 | QM67: 0.01 | QO67: 0.01 | QP67: 0.01 | QQ67: 0.01 | QR67: 0.01 | QS67: 0.01 | QT67: 0.01 | QV67: 0.01 | QW67: 0.01 | QX67: 0.01 | QY67: 0.01 | QZ67: 0.01 | RA67: 0.01 | RC67: 0.01 | RD67: 0.01 | RE67: 0.01 | RF67: 0.01 | RG67: 0.01 | RH67: 0.01 | RJ67: 0.01 | RK67: 0.01 | RL67: 0.01 | RM67: 0.07 | RN67: 0.27 | RO67: 0.22 | RQ67: 0.07 | RR67: 0.06 | RS67: 0.01 | RT67: 0.01 | RU67: 0.01 | RV67: 0.01 | RX67: 0.01 | RY67: 0.01 | RZ67: 0.07 | SA67: 0.27 | SB67: 0.27 | SC67: 0.27 | SE67: 0.22 | SF67: 0.07 | SG67: 0.07 | SH67: 0.07 | SI67: 0.06 | SJ67: 0.01 | SP67: 0.01 | SQ67: 0.01 | SS67: 0 | YT67: 0.01 | YU67: 0.04 | YV67: 0.04 | YX67: 0.04 | YY67: 0.04 | YZ67: 0.04 | ZA67: 0.04 | ZB67: 0.04 | ZC67: 0.03
A68: Pot Gate Valves Dia. 280 mm | E68: 1 | F68: 0.03 | G68: 8225 | H68: 8225 | I68: =F68 -> 0.03 | AF68: 0 | AG68: 0 | AH68: 0 | AK68: 0 | AL68: 0 | AM68: 0 | AN68: 0 | AO68: 0 | NN68: 0 | NP68: 0 | NQ68: 0 | NR68: 0 | NS68: 0 | NT68: 0 | NU68: 0 | NW68: 0 | NX68: 0 | NY68: 0 | NZ68: 0 | OA68: 0 | OB68: 0 | OD68: 0 | OE68: 0 | OF68: 0 | OG68: 0 | OH68: 0 | OI68: 0 | OL68: 0 | OM68: 0 | ON68: 0 | OO68: 0 | OP68: 0 | OR68: 0 | OS68: 0 | OT68: 0 | OU68: 0 | OV68: 0 | OW68: 0 | OY68: 0 | OZ68: 0 | PA68: 0 | PB68: 0 | PC68: 0 | PD68: 0 | PF68: 0 | PG68: 0 | PH68: 0 | PI68: 0 | PJ68: 0 | PK68: 0 | PM68: 0 | PN68: 0 | PO68: 0 | PP68: 0 | PQ68: 0 | PR68: 0 | PT68: 0 | PY68: 0 | QA68: 0 | QB68: 0 | QC68: 0 | QD68: 0 | QE68: 0 | QF68: 0 | QH68: 0 | QI68: 0 | QJ68: 0 | QK68: 0 | QL68: 0 | QM68: 0 | QO68: 0 | QP68: 0 | QQ68: 0 | QR68: 0 | QS68: 0 | QT68: 0 | QV68: 0 | QW68: 0 | QX68: 0 | QY68: 0 | QZ68: 0 | RA68: 0 | RC68: 0 | RD68: 0 | RE68: 0 | RF68: 0 | RG68: 0 | RH68: 0 | RJ68: 0 | RK68: 0 | RL68: 0 | RM68: 0 | RN68: 0 | RO68: 0 | RQ68: 0 | RR68: 0 | RS68: 0 | RT68: 0 | RU68: 0 | RV68: 0 | RX68: 0 | RY68: 0 | RZ68: 0 | SA68: 0 | SB68: 0 | SC68: 0 | SE68: 0.04 | SF68: 0.14 | SG68: 0.14 | SH68: 0.14 | SI68: 0.11 | SJ68: 0.04 | SP68: 0.04 | SQ68: 0.04 | SS68: 0.03 | YT68: 0 | YU68: 0.01 | YV68: 0.01 | YX68: 0.01 | YY68: 0.01 | YZ68: 0.01 | ZA68: 0.01 | ZB68: 0.01 | ZC68: 0.01
A69: Pot HDPE 160mm 0.0 to 1.5m | E69: 300 | F69: 9 | G69: 96000 | H69: 96000 | I69: =F69 -> 9 | AB69: 1.13 | AD69: 1.13 | AE69: 1.13 | AF69: 1.13 | AG69: 1.13 | AH69: 1.13 | AK69: 1.13 | AL69: 1.13 | NP69: 0.33 | NQ69: 0.67 | NR69: 0.67 | NS69: 0.67 | NT69: 0.67 | NU69: 0.67 | NW69: 0.67 | NX69: 0.67 | NY69: 0.67 | NZ69: 0.67 | OA69: 0.67 | OB69: 0.67 | OD69: 0.67 | OE69: 0.67 | OF69: 0.67 | OG69: 0.67 | OH69: 0.67 | OI69: 0.67 | OL69: 0.67 | OM69: 0.67 | ON69: 0.67 | OO69: 0.67 | OP69: 0.67 | OR69: 0.5 | OS69: 0.5 | OT69: 0.5 | OU69: 0.5 | OV69: 0.5 | OW69: 0.5 | OY69: 0.5 | OZ69: 0.5 | PA69: 0.5 | PB69: 0.5 | PC69: 0.5 | PD69: 0.5 | PF69: 0.5 | PG69: 0.5 | PH69: 0.5 | PI69: 0.5 | PJ69: 0.5 | PK69: 0.5 | PM69: 0.5 | PN69: 0.5 | PO69: 0.5 | PP69: 0.5 | PQ69: 0.5 | PR69: 0.5 | PT69: 0.5 | PY69: 0.67 | QA69: 0.67 | QB69: 0.67 | QC69: 0.67 | QD69: 1.76 | QE69: 5.04 | QF69: 5.04 | QH69: 4.68 | QI69: 3.59 | QJ69: 3.59 | QK69: 5.04 | QL69: 9.42 | QM69: 9.42 | QO69: 9.42 | QP69: 9.42 | QQ69: 7.96 | QR69: 3.59 | QS69: 3.59 | QT69: 3.51 | QV69: 3.29 | QW69: 3.29 | QX69: 3.29 | QY69: 7.55 | QZ69: 15.4 | RA69: 0.67 | RC69: 0.67 | RD69: 2.08 | RE69: 6.34 | RF69: 12.01 | RG69: 29.03 | RH69: 23.36 | RJ69: 6.34 | RK69: 7.05 | RL69: 9.17 | RM69: 7.05 | RN69: 0.67 | RO69: 0.67 | RQ69: 0.67 | RR69: 0.67 | RS69: 0.67 | RT69: 0.67 | RU69: 0.67 | RV69: 0.67 | RX69: 0.67 | RY69: 0.67 | RZ69: 0.67 | SA69: 0.67 | SB69: 0.67 | SC69: 0.5 | YT69: 0.94 | YU69: 3.75 | YV69: 3.75 | YX69: 3.75 | YY69: 3.75 | YZ69: 3.75 | ZA69: 3.75 | ZB69: 3.75 | ZC69: 2.81
A70: Pot HDPE 160mm 1.5 to 3.0m | E70: 2300 | F70: 69 | G70: 1081000 | H70: 1081000 | I70: =F70 -> 69 | AB70: 8.63 | AD70: 8.63 | AE70: 8.63 | AF70: 8.63 | AG70: 8.63 | AH70: 8.63 | AK70: 8.63 | AL70: 8.63 | NP70: 2.56 | NQ70: 5.11 | NR70: 5.11 | NS70: 5.11 | NT70: 5.11 | NU70: 5.11 | NW70: 5.11 | NX70: 5.11 | NY70: 5.11 | NZ70: 5.11 | OA70: 5.11 | OB70: 5.11 | OD70: 5.11 | OE70: 5.11 | OF70: 5.11 | OG70: 5.11 | OH70: 5.11 | OI70: 5.11 | OL70: 5.11 | OM70: 5.11 | ON70: 5.11 | OO70: 5.11 | OP70: 5.11 | OR70: 3.83 | OS70: 3.83 | OT70: 3.83 | OU70: 3.83 | OV70: 3.83 | OW70: 3.83 | OY70: 3.83 | OZ70: 3.83 | PA70: 3.83 | PB70: 3.83 | PC70: 3.83 | PD70: 3.83 | PF70: 3.83 | PG70: 3.83 | PH70: 3.83 | PI70: 3.83 | PJ70: 3.83 | PK70: 3.83 | PM70: 3.83 | PN70: 3.83 | PO70: 3.83 | PP70: 3.83 | PQ70: 3.83 | PR70: 3.83 | PT70: 3.83 | PY70: 5.11 | QA70: 5.11 | QB70: 5.11 | QC70: 5.11 | QD70: 5.11 | QE70: 5.11 | QF70: 5.11 | QH70: 16.49 | QI70: 50.61 | QJ70: 50.61 | QK70: 46.82 | QL70: 35.45 | QM70: 35.45 | QO70: 50.62 | QP70: 96.12 | QQ70: 96.12 | QR70: 96.12 | QS70: 96.12 | QT70: 84.03 | QV70: 47.76 | QW70: 47.76 | QX70: 47 | QY70: 44.73 | QZ70: 49.34 | RA70: 63.19 | RC70: 63.19 | RD70: 56.36 | RE70: 31.27 | RF70: 17.43 | RG70: 16.19 | RH70: 12.5 | RJ70: 12.5 | RK70: 12.5 | RL70: 12.5 | RM70: 10.65 | RN70: 5.11 | RO70: 5.11 | RQ70: 5.11 | RR70: 5.11 | RS70: 5.11 | RT70: 5.11 | RU70: 5.11 | RV70: 5.11 | RX70: 5.11 | RY70: 5.11 | RZ70: 5.11 | SA70: 5.11 | SB70: 5.11 | SC70: 3.83 | SU70: 1.54 | SV70: 6.16 | SW70: 6.16 | SX70: 6.16 | SZ70: 5.65 | TA70: 4.11 | TB70: 4.11 | TC70: 4.11 | TD70: 6.51 | TE70: 13.69 | TG70: 13.69 | TH70: 13.69 | TI70: 13.69 | TJ70: 13.69 | TK70: 11.3 | TL70: 4.11 | TN70: 4.11 | TO70: 4.11 | TP70: 4.11 | TQ70: 4.11 | TR70: 4.11 | TS70: 4.11 | TU70: 4.11 | TV70: 4.11 | TW70: 3.08 | UE70: 2.75 | UF70: 11.02 | UG70: 11.02 | UI70: 13.77 | UJ70: 16.53 | UK70: 13.77 | UL70: 55.09 | UM70: 43.15 | UN70: 7.35 | UP70: 7.35 | UQ70: 7.58 | UR70: 8.26 | US70: 8.26 | UT70: 8.26 | UU70: 6.2 | YT70: 7.19 | YU70: 28.75 | YV70: 28.75 | YX70: 28.75 | YY70: 28.75 | YZ70: 28.75 | ZA70: 28.75 | ZB70: 28.75 | ZC70: 21.56
A71: Pot HDPE 200mm 1.5 to 3.0m | E71: 750 | F71: 22.5 | G71: 412500 | H71: 412500 | I71: =F71 -> 22.5 | AB71: 2.81 | AD71: 2.81 | AE71: 2.81 | AF71: 2.81 | AG71: 2.81 | AH71: 2.81 | AK71: 2.81 | AL71: 2.81 | NP71: 0.83 | NQ71: 1.67 | NR71: 1.67 | NS71: 1.67 | NT71: 1.67 | NU71: 1.67 | NW71: 1.67 | NX71: 1.67 | NY71: 1.67 | NZ71: 1.67 | OA71: 1.67 | OB71: 1.67 | OD71: 1.67 | OE71: 1.67 | OF71: 1.67 | OG71: 1.67 | OH71: 1.67 | OI71: 1.67 | OL71: 1.67 | OM71: 1.67 | ON71: 1.67 | OO71: 1.67 | OP71: 1.67 | OR71: 1.25 | OS71: 1.25 | OT71: 1.25 | OU71: 1.25 | OV71: 1.25 | OW71: 1.25 | OY71: 1.25 | OZ71: 1.25 | PA71: 1.25 | PB71: 1.25 | PC71: 1.25 | PD71: 1.25 | PF71: 1.25 | PG71: 1.25 | PH71: 1.25 | PI71: 1.25 | PJ71: 1.25 | PK71: 1.25 | PM71: 1.25 | PN71: 1.25 | PO71: 1.25 | PP71: 1.25 | PQ71: 1.25 | PR71: 1.25 | PT71: 1.25 | PY71: 1.67 | QA71: 1.67 | QB71: 1.67 | QC71: 1.67 | QD71: 1.67 | QE71: 1.67 | QF71: 1.67 | QH71: 1.67 | QI71: 1.67 | QJ71: 1.67 | QK71: 1.67 | QL71: 1.67 | QM71: 1.67 | QO71: 1.67 | QP71: 1.67 | QQ71: 1.67 | QR71: 1.67 | QS71: 1.67 | QT71: 1.67 | QV71: 1.67 | QW71: 1.67 | QX71: 5.33 | QY71: 16.31 | QZ71: 16.31 | RA71: 16.31 | RC71: 16.31 | RD71: 17.26 | RE71: 19.56 | RF71: 17.94 | RG71: 24.04 | RH71: 42.52 | RJ71: 43.06 | RK71: 43.78 | RL71: 45.94 | RM71: 45.22 | RN71: 36.96 | RO71: 18.75 | RQ71: 19.02 | RR71: 17.73 | RS71: 13.87 | RT71: 13.87 | RU71: 13.87 | RV71: 13.87 | RX71: 13.87 | RY71: 10.82 | RZ71: 1.67 | SA71: 1.67 | SB71: 1.67 | SC71: 1.25 | YT71: 2.34 | YU71: 9.38 | YV71: 9.38 | YX71: 9.38 | YY71: 9.38 | YZ71: 9.38 | ZA71: 9.38 | ZB71: 9.38 | ZC71: 7.03
A72: Pot HDPE 225mm 1.5 to 3.0m | E72: 550 | F72: 16.5 | G72: 324501.3 | H72: 324501.3 | I72: =F72 -> 16.5 | AB72: 2.06 | AD72: 2.06 | AE72: 2.06 | AF72: 2.06 | AG72: 2.06 | AH72: 2.06 | AK72: 2.06 | AL72: 2.06 | NP72: 0.61 | NQ72: 1.22 | NR72: 1.22 | NS72: 1.22 | NT72: 1.22 | NU72: 1.22 | NW72: 1.22 | NX72: 1.22 | NY72: 1.22 | NZ72: 1.22 | OA72: 1.22 | OB72: 1.22 | OD72: 1.22 | OE72: 1.22 | OF72: 1.22 | OG72: 1.22 | OH72: 1.22 | OI72: 1.22 | OL72: 1.22 | OM72: 1.22 | ON72: 1.22 | OO72: 1.22 | OP72: 1.22 | OR72: 0.92 | OS72: 0.92 | OT72: 0.92 | OU72: 0.92 | OV72: 0.92 | OW72: 0.92 | OY72: 0.92 | OZ72: 0.92 | PA72: 0.92 | PB72: 0.92 | PC72: 0.92 | PD72: 0.92 | PF72: 0.92 | PG72: 0.92 | PH72: 0.92 | PI72: 0.92 | PJ72: 0.92 | PK72: 0.92 | PM72: 0.92 | PN72: 0.92 | PO72: 0.92 | PP72: 0.92 | PQ72: 0.92 | PR72: 0.92 | PT72: 0.92 | PY72: 1.22 | QA72: 1.22 | QB72: 1.22 | QC72: 1.22 | QD72: 1.22 | QE72: 1.22 | QF72: 1.22 | QH72: 1.22 | QI72: 1.22 | QJ72: 1.22 | QK72: 1.22 | QL72: 1.22 | QM72: 1.22 | QO72: 1.22 | QP72: 1.22 | QQ72: 1.22 | QR72: 1.22 | QS72: 1.22 | QT72: 1.22 | QV72: 1.22 | QW72: 1.22 | QX72: 1.22 | QY72: 1.22 | QZ72: 1.22 | RA72: 1.22 | RC72: 1.22 | RD72: 1.22 | RE72: 1.22 | RF72: 1.22 | RG72: 1.22 | RH72: 1.22 | RJ72: 1.22 | RK72: 1.22 | RL72: 1.22 | RM72: 1.22 | RN72: 1.22 | RO72: 4.22 | RQ72: 13.2 | RR72: 13.2 | RS72: 13.2 | RT72: 14.19 | RU72: 17.19 | RV72: 33.15 | RX72: 81.05 | RY72: 65.08 | RZ72: 17.19 | SA72: 19.18 | SB72: 25.17 | SC72: 18.88 | SZ72: 0.46 | TA72: 1.84 | TB72: 1.84 | TC72: 1.84 | TD72: 1.79 | TE72: 1.64 | TG72: 1.64 | TH72: 2.46 | TI72: 4.92 | TJ72: 4.92 | TK72: 4.92 | TL72: 4.92 | TN72: 4.1 | TO72: 1.64 | TP72: 1.64 | TQ72: 1.6 | TR72: 1.48 | TS72: 1.48 | TU72: 1.48 | TV72: 1.48 | TW72: 1.11 | YT72: 1.72 | YU72: 6.88 | YV72: 6.88 | YX72: 6.88 | YY72: 6.88 | YZ72: 6.88 | ZA72: 6.88 | ZB72: 6.88 | ZC72: 5.16
A73: Pot HDPE 250mm 1.5 to 3.0m | E73: 850 | F73: 25.5 | G73: 552498.7 | H73: 552498.7 | I73: =F73 -> 25.5 | AB73: 3.19 | AD73: 3.19 | AE73: 3.19 | AF73: 3.19 | AG73: 3.19 | AH73: 3.19 | AK73: 3.19 | AL73: 3.19 | NP73: 0.94 | NQ73: 1.89 | NR73: 1.89 | NS73: 1.89 | NT73: 1.89 | NU73: 1.89 | NW73: 1.89 | NX73: 1.89 | NY73: 1.89 | NZ73: 1.89 | OA73: 1.89 | OB73: 1.89 | OD73: 1.89 | OE73: 1.89 | OF73: 1.89 | OG73: 1.89 | OH73: 1.89 | OI73: 1.89 | OL73: 1.89 | OM73: 1.89 | ON73: 1.89 | OO73: 1.89 | OP73: 1.89 | OR73: 1.42 | OS73: 1.42 | OT73: 1.42 | OU73: 1.42 | OV73: 1.42 | OW73: 1.42 | OY73: 1.42 | OZ73: 1.42 | PA73: 1.42 | PB73: 1.42 | PC73: 1.42 | PD73: 1.42 | PF73: 1.42 | PG73: 1.42 | PH73: 1.42 | PI73: 1.42 | PJ73: 1.42 | PK73: 1.42 | PM73: 1.42 | PN73: 1.42 | PO73: 1.42 | PP73: 1.42 | PQ73: 1.42 | PR73: 1.42 | PT73: 1.42 | PY73: 1.89 | QA73: 1.89 | QB73: 1.89 | QC73: 1.89 | QD73: 1.89 | QE73: 1.89 | QF73: 1.89 | QH73: 1.89 | QI73: 1.89 | QJ73: 1.89 | QK73: 1.89 | QL73: 1.89 | QM73: 1.89 | QO73: 1.89 | QP73: 1.89 | QQ73: 1.89 | QR73: 1.89 | QS73: 1.89 | QT73: 1.89 | QV73: 1.89 | QW73: 1.89 | QX73: 1.89 | QY73: 1.89 | QZ73: 1.89 | RA73: 1.89 | RC73: 1.89 | RD73: 5.23 | RE73: 15.25 | RF73: 15.25 | RG73: 15.25 | RH73: 15.25 | RJ73: 15.62 | RK73: 16.74 | RL73: 16.74 | RM73: 22.3 | RN73: 39.01 | RO73: 39.01 | RQ73: 39.01 | RR73: 39.01 | RS73: 39.01 | RT73: 36.46 | RU73: 28.81 | RV73: 23.25 | RX73: 6.54 | RY73: 10.27 | RZ73: 21.46 | SA73: 27.66 | SB73: 46.27 | SC73: 39.6 | SE73: 16.23 | SF73: 6.98 | SG73: 9.31 | SH73: 6.98 | YT73: 2.66 | YU73: 10.63 | YV73: 10.63 | YX73: 10.63 | YY73: 10.63 | YZ73: 10.63 | ZA73: 10.63 | ZB73: 10.63 | ZC73: 7.97
A74: Pot HDPE 280mm 1.5 to 3.0m | E74: 110 | F74: 3.3 | G74: 79200 | H74: 79200 | I74: =F74 -> 3.3 | AB74: 0.41 | AD74: 0.41 | AE74: 0.41 | AF74: 0.41 | AG74: 0.41 | AH74: 0.41 | AK74: 0.41 | AL74: 0.41 | NP74: 0.12 | NQ74: 0.24 | NR74: 0.24 | NS74: 0.24 | NT74: 0.24 | NU74: 0.24 | NW74: 0.24 | NX74: 0.24 | NY74: 0.24 | NZ74: 0.24 | OA74: 0.24 | OB74: 0.24 | OD74: 0.24 | OE74: 0.24 | OF74: 0.24 | OG74: 0.24 | OH74: 0.24 | OI74: 0.24 | OL74: 0.24 | OM74: 0.24 | ON74: 0.24 | OO74: 0.24 | OP74: 0.24 | OR74: 0.18 | OS74: 0.18 | OT74: 0.18 | OU74: 0.18 | OV74: 0.18 | OW74: 0.18 | OY74: 0.18 | OZ74: 0.18 | PA74: 0.18 | PB74: 0.18 | PC74: 0.18 | PD74: 0.18 | PF74: 0.18 | PG74: 0.18 | PH74: 0.18 | PI74: 0.18 | PJ74: 0.18 | PK74: 0.18 | PM74: 0.18 | PN74: 0.18 | PO74: 0.18 | PP74: 0.18 | PQ74: 0.18 | PR74: 0.18 | PT74: 0.18 | PY74: 0.24 | QA74: 0.24 | QB74: 0.24 | QC74: 0.24 | QD74: 0.24 | QE74: 0.24 | QF74: 0.24 | QH74: 0.24 | QI74: 0.24 | QJ74: 0.24 | QK74: 0.24 | QL74: 0.24 | QM74: 0.24 | QO74: 0.24 | QP74: 0.24 | QQ74: 0.24 | QR74: 0.24 | QS74: 0.24 | QT74: 0.24 | QV74: 0.24 | QW74: 0.24 | QX74: 0.24 | QY74: 0.24 | QZ74: 0.24 | RA74: 0.24 | RC74: 0.24 | RD74: 0.24 | RE74: 0.24 | RF74: 0.24 | RG74: 0.24 | RH74: 0.24 | RJ74: 1.63 | RK74: 5.77 | RL74: 5.31 | RM74: 3.93 | RN74: 7.61 | RO74: 18.67 | RQ74: 14.98 | RR74: 3.93 | RS74: 4.39 | RT74: 5.77 | RU74: 4.39 | RV74: 0.24 | RX74: 0.24 | RY74: 0.24 | RZ74: 0.24 | SA74: 0.24 | SB74: 0.24 | SC74: 0.18 | YT74: 0.34 | YU74: 1.38 | YV74: 1.38 | YX74: 1.38 | YY74: 1.38 | YZ74: 1.38 | ZA74: 1.38 | ZB74: 1.38 | ZC74: 1.03
A75: Pot HDPE 315mm 0.0 to 1.5m | E75: 175 | F75: 5.25 | G75: 112000 | H75: 112000 | I75: =F75 -> 5.25 | AB75: 0.66 | AD75: 0.66 | AE75: 0.66 | AF75: 0.66 | AG75: 0.66 | AH75: 0.66 | AK75: 0.66 | AL75: 0.66 | NP75: 0.19 | NQ75: 0.39 | NR75: 0.39 | NS75: 0.39 | NT75: 0.39 | NU75: 0.39 | NW75: 0.39 | NX75: 0.39 | NY75: 0.39 | NZ75: 0.39 | OA75: 0.39 | OB75: 0.39 | OD75: 0.39 | OE75: 0.39 | OF75: 0.39 | OG75: 0.39 | OH75: 0.39 | OI75: 0.39 | OL75: 0.39 | OM75: 0.39 | ON75: 0.39 | OO75: 0.39 | OP75: 0.39 | OR75: 0.29 | OS75: 0.29 | OT75: 0.29 | OU75: 0.29 | OV75: 0.29 | OW75: 0.29 | OY75: 0.29 | OZ75: 0.29 | PA75: 0.29 | PB75: 0.29 | PC75: 0.29 | PD75: 0.29 | PF75: 0.29 | PG75: 0.29 | PH75: 0.29 | PI75: 0.29 | PJ75: 0.29 | PK75: 0.29 | PM75: 0.29 | PN75: 0.29 | PO75: 0.29 | PP75: 0.29 | PQ75: 0.29 | PR75: 0.29 | PT75: 0.29 | PY75: 0.39 | QA75: 0.39 | QB75: 0.39 | QC75: 0.39 | QD75: 0.39 | QE75: 0.39 | QF75: 0.39 | QH75: 0.39 | QI75: 0.39 | QJ75: 0.39 | QK75: 0.39 | QL75: 0.39 | QM75: 0.39 | QO75: 0.39 | QP75: 0.39 | QQ75: 0.39 | QR75: 0.39 | QS75: 0.39 | QT75: 0.39 | QV75: 0.39 | QW75: 0.39 | QX75: 0.39 | QY75: 0.39 | QZ75: 0.39 | RA75: 0.39 | RC75: 0.39 | RD75: 0.39 | RE75: 0.39 | RF75: 0.39 | RG75: 0.39 | RH75: 0.39 | RJ75: 0.39 | RK75: 0.39 | RL75: 0.39 | RM75: 0.39 | RN75: 0.39 | RO75: 0.39 | RQ75: 0.39 | RR75: 0.39 | RS75: 0.39 | RT75: 0.39 | RU75: 0.39 | RV75: 0.39 | RX75: 0.39 | RY75: 0.39 | RZ75: 0.39 | SA75: 0.39 | SB75: 0.39 | SC75: 0.29 | TD75: 1.1 | TE75: 4.4 | TG75: 4.4 | TH75: 4.4 | TI75: 4.76 | TJ75: 5.86 | TK75: 9.28 | TL75: 19.54 | TN75: 19.54 | TO75: 16.12 | TP75: 5.86 | TQ75: 4.4 | TW75: 1.47 | TX75: 5.86 | TY75: 5.86 | TZ75: 4.4 | YT75: 0.55 | YU75: 2.19 | YV75: 2.19 | YX75: 2.19 | YY75: 2.19 | YZ75: 2.19 | ZA75: 2.19 | ZB75: 2.19 | ZC75: 1.64
A76: Pot Wash out valve with dia (160) mm | E76: 2 | F76: 0.05 | G76: 6200 | H76: 6200 | I76: =F76 -> 0.05 | AF76: 0.01 | AG76: 0.01 | AH76: 0.01 | AK76: 0.01 | AL76: 0.01 | AM76: 0.01 | AN76: 0.01 | AO76: 0.01 | NN76: 0 | NP76: 0 | NQ76: 0 | NR76: 0 | NS76: 0 | NT76: 0 | NU76: 0 | NW76: 0 | NX76: 0 | NY76: 0 | NZ76: 0 | OA76: 0 | OB76: 0 | OD76: 0 | OE76: 0 | OF76: 0 | OG76: 0 | OH76: 0 | OI76: 0 | OL76: 0 | OM76: 0 | ON76: 0 | OO76: 0 | OP76: 0 | OR76: 0 | OS76: 0 | OT76: 0 | OU76: 0 | OV76: 0 | OW76: 0 | OY76: 0 | OZ76: 0 | PA76: 0 | PB76: 0 | PC76: 0 | PD76: 0 | PF76: 0 | PG76: 0 | PH76: 0 | PI76: 0 | PJ76: 0 | PK76: 0 | PM76: 0 | PN76: 0 | PO76: 0 | PP76: 0 | PQ76: 0 | PR76: 0 | PT76: 0 | PY76: 0 | QA76: 0 | QB76: 0 | QC76: 0 | QD76: 0 | QE76: 0 | QF76: 0 | QH76: 0 | QI76: 0 | QJ76: 0 | QK76: 0 | QL76: 0 | QM76: 0.04 | QO76: 0.1 | QP76: 0 | QQ76: 0 | QR76: 0 | QS76: 0 | QT76: 0.02 | QV76: 0.05 | QW76: 0.05 | QX76: 0.05 | QY76: 0.05 | QZ76: 0.05 | RA76: 0.05 | RC76: 0.05 | RD76: 0.05 | RE76: 0.05 | RF76: 0.05 | RG76: 0.05 | RH76: 0.04 | RJ76: 0.03 | RK76: 0.03 | RL76: 0.03 | RM76: 0.03 | RN76: 0.03 | RO76: 0.05 | RQ76: 0.14 | RR76: 0.14 | RS76: 0.14 | RT76: 0.1 | RU76: 0 | RV76: 0 | RX76: 0 | RY76: 0 | RZ76: 0 | SA76: 0 | SB76: 0 | SC76: 0 | SE76: 0 | SF76: 0 | SG76: 0 | SH76: 0 | SI76: 0 | SJ76: 0 | SP76: 0 | SQ76: 0 | SS76: 0 | YT76: 0.01 | YU76: 0.03 | YV76: 0.03 | YX76: 0.03 | YY76: 0.03 | YZ76: 0.03 | ZA76: 0.03 | ZB76: 0.03 | ZC76: 0.02
A77: Pot Wash out valve with dia (200) mm | E77: 1 | F77: 0.03 | G77: 4580 | H77: 4580 | I77: =F77 -> 0.03 | AF77: 0 | AG77: 0 | AH77: 0 | AK77: 0 | AL77: 0 | AM77: 0 | AN77: 0 | AO77: 0 | NN77: 0 | NP77: 0 | NQ77: 0 | NR77: 0 | NS77: 0 | NT77: 0 | NU77: 0 | NW77: 0 | NX77: 0 | NY77: 0 | NZ77: 0 | OA77: 0 | OB77: 0 | OD77: 0 | OE77: 0 | OF77: 0 | OG77: 0 | OH77: 0 | OI77: 0 | OL77: 0 | OM77: 0 | ON77: 0 | OO77: 0 | OP77: 0 | OR77: 0 | OS77: 0 | OT77: 0 | OU77: 0 | OV77: 0 | OW77: 0 | OY77: 0 | OZ77: 0 | PA77: 0 | PB77: 0 | PC77: 0 | PD77: 0 | PF77: 0 | PG77: 0 | PH77: 0 | PI77: 0 | PJ77: 0 | PK77: 0 | PM77: 0 | PN77: 0 | PO77: 0 | PP77: 0 | PQ77: 0 | PR77: 0 | PT77: 0 | PY77: 0 | QA77: 0 | QB77: 0 | QC77: 0 | QD77: 0 | QE77: 0 | QF77: 0 | QH77: 0 | QI77: 0 | QJ77: 0 | QK77: 0 | QL77: 0 | QM77: 0 | QO77: 0 | QP77: 0 | QQ77: 0 | QR77: 0 | QS77: 0 | QT77: 0 | QV77: 0 | QW77: 0 | QX77: 0 | QY77: 0 | QZ77: 0 | RA77: 0 | RC77: 0 | RD77: 0 | RE77: 0 | RF77: 0 | RG77: 0 | RH77: 0 | RJ77: 0 | RK77: 0 | RL77: 0 | RM77: 0 | RN77: 0 | RO77: 0 | RQ77: 0 | RR77: 0 | RS77: 0 | RT77: 0 | RU77: 0.01 | RV77: 0.04 | RX77: 0.04 | RY77: 0.07 | RZ77: 0.07 | SA77: 0.07 | SB77: 0.06 | SC77: 0.04 | SE77: 0.04 | SF77: 0.07 | SG77: 0.07 | SH77: 0.07 | SI77: 0.05 | SJ77: 0 | SP77: 0 | SQ77: 0 | SS77: 0 | YT77: 0 | YU77: 0.01 | YV77: 0.01 | YX77: 0.01 | YY77: 0.01 | YZ77: 0.01 | ZA77: 0.01 | ZB77: 0.01 | ZC77: 0.01
A78: Pot Wash out valve with dia (250) mm | E78: 3 | F78: 0.08 | G78: 21510 | H78: 21510 | I78: =F78 -> 0.08 | AF78: 0.01 | AG78: 0.01 | AH78: 0.01 | AK78: 0.01 | AL78: 0.01 | AM78: 0.01 | AN78: 0.01 | AO78: 0.01 | NN78: 0 | NP78: 0.01 | NQ78: 0.01 | NR78: 0.01 | NS78: 0.01 | NT78: 0.01 | NU78: 0.01 | NW78: 0.01 | NX78: 0.01 | NY78: 0.01 | NZ78: 0.01 | OA78: 0.01 | OB78: 0.01 | OD78: 0.01 | OE78: 0.01 | OF78: 0.01 | OG78: 0.01 | OH78: 0.01 | OI78: 0.01 | OL78: 0.01 | OM78: 0.01 | ON78: 0.01 | OO78: 0.01 | OP78: 0.01 | OR78: 0 | OS78: 0 | OT78: 0 | OU78: 0 | OV78: 0 | OW78: 0 | OY78: 0 | OZ78: 0 | PA78: 0 | PB78: 0 | PC78: 0 | PD78: 0 | PF78: 0 | PG78: 0 | PH78: 0 | PI78: 0 | PJ78: 0 | PK78: 0 | PM78: 0 | PN78: 0 | PO78: 0 | PP78: 0 | PQ78: 0 | PR78: 0 | PT78: 0 | PY78: 0.01 | QA78: 0.01 | QB78: 0.01 | QC78: 0.01 | QD78: 0.01 | QE78: 0.01 | QF78: 0.01 | QH78: 0.01 | QI78: 0.01 | QJ78: 0.01 | QK78: 0.01 | QL78: 0.01 | QM78: 0.01 | QO78: 0.01 | QP78: 0.01 | QQ78: 0.01 | QR78: 0.01 | QS78: 0.01 | QT78: 0.01 | QV78: 0.01 | QW78: 0.01 | QX78: 0.01 | QY78: 0.01 | QZ78: 0.01 | RA78: 0.01 | RC78: 0.01 | RD78: 0.01 | RE78: 0.01 | RF78: 0.01 | RG78: 0.01 | RH78: 0.01 | RJ78: 0.01 | RK78: 0.01 | RL78: 0.01 | RM78: 0.01 | RN78: 0.01 | RO78: 0.01 | RQ78: 0.03 | RR78: 0.03 | RS78: 0.04 | RT78: 0.07 | RU78: 0.07 | RV78: 0.07 | RX78: 0.07 | RY78: 0.07 | RZ78: 0.09 | SA78: 0.17 | SB78: 0.13 | SC78: 0.06 | SE78: 0.14 | SF78: 0.14 | SG78: 0.14 | SH78: 0.12 | SI78: 0.07 | SJ78: 0.12 | SP78: 0.27 | SQ78: 0.21 | SS78: 0 | YT78: 0.01 | YU78: 0.04 | YV78: 0.04 | YX78: 0.04 | YY78: 0.04 | YZ78: 0.04 | ZA78: 0.04 | ZB78: 0.04 | ZC78: 0.03
A79: Riprap | E79: 5000 | F79: 0 | G79: 1300000 | H79: 1300000 | I79: =F79 -> 0 | HE79: 178.57 | HF79: 357.14 | HG79: 357.14 | HH79: 357.14 | HI79: 357.14 | HK79: 357.14 | HL79: 357.14 | HM79: 357.14 | HN79: 357.14 | HO79: 357.14 | HP79: 357.14 | HR79: 357.14 | HS79: 357.14 | HT79: 357.14 | HU79: 178.57
A80: Sewer Dia 200 mm; Depth : 1.5m - 2.5m | E80: 600 | F80: 18 | G80: 282000 | H80: 282000 | I80: =F80 -> 18 | AF80: 2.25 | AG80: 2.25 | AH80: 2.25 | AK80: 2.25 | AL80: 2.25 | AM80: 2.25 | AN80: 2.25 | AO80: 2.25 | JO80: 0.67 | JP80: 1.33 | JQ80: 1.33 | JR80: 1.33 | JS80: 1.33 | JT80: 1.33 | JV80: 1.33 | JW80: 1.33 | JX80: 1.33 | JY80: 1.33 | JZ80: 1.33 | KA80: 1.33 | KC80: 1.33 | KD80: 1.33 | KE80: 1.33 | KF80: 1.33 | KG80: 1.33 | KH80: 1.33 | KJ80: 1.33 | KK80: 1.33 | KL80: 1.33 | KM80: 1.33 | KN80: 1.33 | KO80: 1.33 | KQ80: 1.33 | KR80: 1.33 | KS80: 1.93 | KT80: 2.54 | KU80: 2.54 | KV80: 2.54 | KX80: 2.54 | KY80: 2.54 | KZ80: 2.23 | LA80: 1.93 | LB80: 1.93 | LC80: 1.93 | LE80: 1.93 | LF80: 1.93 | LG80: 2.83 | LH80: 3.74 | LI80: 3.74 | LJ80: 3.74 | LL80: 3.74 | LM80: 3.74 | LN80: 2.53 | LO80: 1.33 | LP80: 1.33 | LQ80: 1.33 | LS80: 1.33 | LT80: 1.33 | LU80: 1.33 | LV80: 1.33 | LW80: 1.33 | LX80: 1.33 | LZ80: 1.33 | MA80: 1.63 | MB80: 1.93 | MC80: 1.93 | MD80: 1.93 | ME80: 1.93 | MG80: 1.93 | MH80: 2.23 | MI80: 2.54 | MJ80: 2.54 | MK80: 2.54 | ML80: 2.54 | MN80: 2.54 | MO80: 1.93 | MP80: 1.33 | MQ80: 1.33 | MR80: 1.33 | MS80: 1.33 | MU80: 1.33 | MV80: 1.33 | MW80: 1.33 | MX80: 1.33 | MY80: 1.33 | MZ80: 1.33 | NB80: 1.33 | NC80: 1.33 | ND80: 1.33 | NE80: 1.33 | NF80: 1.33 | NG80: 1.33 | NI80: 1.33 | NJ80: 1.33 | NK80: 1.33 | NL80: 1.33 | NM80: 1.33 | NN80: 1.33 | NP80: 4.73 | NQ80: 8.13 | NR80: 8.13 | NS80: 8.13 | NT80: 8.13 | NU80: 8.13 | NW80: 8.13 | NX80: 8.13 | NY80: 8.13 | NZ80: 7.12 | OA80: 6.1 | OB80: 6.1 | OD80: 6.1 | OE80: 6.1 | OF80: 6.1 | OG80: 13.51 | OH80: 20.91 | OI80: 20.91 | OL80: 20.91 | OM80: 20.91 | ON80: 20.91 | OO80: 20.91 | OP80: 10.46 | PC80: 4.58 | PD80: 4.58 | PF80: 4.58 | PG80: 4.58 | PH80: 4.58 | PI80: 4.58 | PJ80: 4.58 | PK80: 4.58 | PM80: 7.84 | PN80: 7.84 | PO80: 7.84 | PP80: 7.84 | PQ80: 7.84 | PR80: 7.84 | PT80: 7.84 | PY80: 10.46 | QA80: 7.84 | YK80: 1.88 | YL80: 7.5 | YM80: 7.5 | YN80: 7.5 | YO80: 7.5 | YQ80: 7.5 | YR80: 7.5 | YS80: 7.5 | YT80: 5.63
A81: Sewer Dia 250 mm; Depth : 1.5m - 2.5m | E81: 715 | F81: 21.45 | G81: 357500 | H81: 357500 | I81: =F81 -> 21.45 | AF81: 2.68 | AG81: 2.68 | AH81: 2.68 | AK81: 2.68 | AL81: 2.68 | AM81: 2.68 | AN81: 2.68 | AO81: 2.68 | JO81: 0.79 | JP81: 1.59 | JQ81: 1.59 | JR81: 1.59 | JS81: 1.59 | JT81: 1.59 | JV81: 1.59 | JW81: 1.59 | JX81: 1.59 | JY81: 1.59 | JZ81: 1.59 | KA81: 1.59 | KC81: 1.59 | KD81: 1.59 | KE81: 1.59 | KF81: 1.59 | KG81: 1.59 | KH81: 1.59 | KJ81: 1.59 | KK81: 1.59 | KL81: 1.59 | KM81: 1.59 | KN81: 1.59 | KO81: 1.59 | KQ81: 1.59 | KR81: 1.59 | KS81: 1.59 | KT81: 1.59 | KU81: 1.59 | KV81: 1.59 | KX81: 1.59 | KY81: 1.59 | KZ81: 1.59 | LA81: 1.59 | LB81: 1.59 | LC81: 1.59 | LE81: 1.59 | LF81: 1.59 | LG81: 1.59 | LH81: 2.69 | LI81: 3.79 | LJ81: 3.79 | LL81: 3.79 | LM81: 3.79 | LN81: 3.79 | LO81: 3.36 | LP81: 2.93 | LQ81: 2.93 | LS81: 2.93 | LT81: 2.93 | LU81: 4.17 | LV81: 5.41 | LW81: 5.41 | LX81: 5.41 | LZ81: 5.41 | MA81: 5.41 | MB81: 5.41 | MC81: 3.5 | MD81: 1.59 | ME81: 1.59 | MG81: 1.59 | MH81: 1.59 | MI81: 1.59 | MJ81: 1.59 | MK81: 2.07 | ML81: 2.54 | MN81: 2.54 | MO81: 2.54 | MP81: 2.54 | MQ81: 2.54 | MR81: 2.54 | MS81: 2.07 | MU81: 1.59 | MV81: 1.59 | MW81: 1.59 | MX81: 2.69 | MY81: 3.79 | MZ81: 3.79 | NB81: 3.79 | NC81: 3.79 | ND81: 3.79 | NE81: 2.69 | NF81: 1.59 | NG81: 1.59 | NI81: 1.59 | NJ81: 1.59 | NK81: 1.59 | NL81: 1.59 | NM81: 1.59 | NN81: 1.59 | NP81: 0.79 | NZ81: 4.59 | OA81: 9.17 | OB81: 9.17 | OD81: 9.17 | OE81: 9.17 | OF81: 9.17 | OG81: 9.17 | OH81: 9.17 | OI81: 9.17 | OL81: 8.02 | OM81: 6.87 | ON81: 6.87 | OO81: 6.87 | OP81: 6.87 | OR81: 5.15 | OS81: 5.15 | OT81: 17.69 | OU81: 17.69 | OV81: 17.69 | OW81: 17.69 | OY81: 17.69 | OZ81: 17.69 | PA81: 17.69 | PB81: 17.69 | PC81: 17.69 | PD81: 10.02 | PF81: 6.18 | PG81: 6.18 | PH81: 6.18 | PI81: 6.18 | PJ81: 6.18 | PK81: 6.18 | PM81: 8.84 | PN81: 8.84 | PO81: 8.84 | PP81: 8.84 | PQ81: 8.84 | PR81: 8.84 | PT81: 8.84 | PY81: 11.79 | QA81: 8.84 | YK81: 2.23 | YL81: 8.94 | YM81: 8.94 | YN81: 8.94 | YO81: 8.94 | YQ81: 8.94 | YR81: 8.94 | YS81: 8.94 | YT81: 6.7
A82: Sewer Dia 315 mm; Depth : 2.5m - 3.5m | E82: 950 | F82: 28.5 | G82: 631750 | H82: 631750 | I82: =F82 -> 28.5 | AF82: 3.56 | AG82: 3.56 | AH82: 3.56 | AK82: 3.56 | AL82: 3.56 | AM82: 3.56 | AN82: 3.56 | AO82: 3.56 | JF82: 1.9 | JH82: 3.81 | JI82: 3.81 | JJ82: 3.81 | JK82: 3.81 | JL82: 3.81 | JM82: 3.81 | JO82: 4.86 | JP82: 5.92 | JQ82: 5.92 | JR82: 5.92 | JS82: 5.18 | JT82: 4.44 | JV82: 4.44 | JW82: 4.44 | JX82: 4.44 | JY82: 4.44 | JZ82: 4.44 | KA82: 4.44 | KC82: 4.44 | KD82: 9.25 | KE82: 14.07 | KF82: 14.07 | KG82: 14.07 | KH82: 14.07 | KJ82: 14.07 | KK82: 14.07 | KL82: 8.09 | KM82: 2.11 | KN82: 2.11 | KO82: 2.11 | KQ82: 2.11 | KR82: 2.11 | KS82: 2.11 | KT82: 2.11 | KU82: 2.11 | KV82: 2.11 | KX82: 2.11 | KY82: 2.11 | KZ82: 4.2 | LA82: 6.3 | LB82: 6.3 | LC82: 6.3 | LE82: 6.3 | LF82: 6.3 | LG82: 7.46 | LH82: 7.75 | LI82: 6.88 | LJ82: 6.88 | LL82: 6.88 | LM82: 6.88 | LN82: 6.88 | LO82: 11.44 | LP82: 16 | LQ82: 16.74 | LS82: 17.48 | LT82: 17.48 | LU82: 17.48 | LV82: 12.59 | LW82: 7.34 | LX82: 6.96 | LZ82: 6.96 | MA82: 6.96 | MB82: 6.96 | MC82: 6.96 | MD82: 6.63 | ME82: 6.3 | MG82: 6.3 | MH82: 6.3 | MI82: 7.52 | MJ82: 8.74 | MK82: 6.65 | ML82: 4.55 | MN82: 4.55 | MO82: 4.55 | MP82: 5.42 | MQ82: 6.3 | MR82: 6.3 | MS82: 6.3 | MU82: 6.3 | MV82: 6.3 | MW82: 6.3 | MX82: 4.2 | MY82: 2.63 | MZ82: 3.16 | NB82: 3.16 | NC82: 3.16 | ND82: 3.16 | NE82: 3.16 | NF82: 3.53 | NG82: 3.91 | NI82: 3.91 | NJ82: 3.91 | NK82: 3.91 | NL82: 3.91 | NM82: 3.91 | NN82: 3.01 | NP82: 1.06 | OL82: 2.72 | OM82: 5.45 | ON82: 5.45 | OO82: 5.45 | OP82: 5.45 | OR82: 4.09 | OS82: 4.09 | OT82: 4.09 | OU82: 4.09 | OV82: 3.81 | OW82: 3.27 | OY82: 3.27 | OZ82: 3.27 | PA82: 3.27 | PB82: 3.27 | PC82: 3.27 | PD82: 8.35 | PF82: 10.9 | PG82: 10.9 | PH82: 10.9 | PI82: 10.9 | PJ82: 10.9 | PK82: 10.9 | PM82: 10.9 | PN82: 5.81 | PO82: 3.27 | PP82: 3.27 | PQ82: 3.27 | PR82: 3.27 | PT82: 3.27 | PY82: 5.08 | QA82: 7.27 | QB82: 7.27 | QC82: 7.27 | QD82: 7.27 | QE82: 7.27 | QF82: 5.45 | YK82: 2.97 | YL82: 11.88 | YM82: 11.88 | YN82: 11.88 | YO82: 11.88 | YQ82: 11.88 | YR82: 11.88 | YS82: 11.88 | YT82: 8.91
A83: Sewer Dia 315 mm; Depth : 3.5m - 4.5m | E83: 1150 | F83: 34.5 | G83: 920000 | H83: 920000 | I83: =F83 -> 34.5 | AF83: 4.31 | AG83: 4.31 | AH83: 4.31 | AK83: 4.31 | AL83: 4.31 | AM83: 4.31 | AN83: 4.31 | AO83: 4.31 | JO83: 1.28 | JP83: 2.56 | JQ83: 2.56 | JR83: 2.56 | JS83: 8.06 | JT83: 13.56 | JV83: 13.56 | JW83: 13.56 | JX83: 13.56 | JY83: 13.56 | JZ83: 13.56 | KA83: 13.56 | KC83: 13.56 | KD83: 13.56 | KE83: 13.56 | KF83: 13.56 | KG83: 13.56 | KH83: 13.56 | KJ83: 12.87 | KK83: 12.19 | KL83: 12.19 | KM83: 12.19 | KN83: 12.19 | KO83: 12.19 | KQ83: 12.19 | KR83: 12.19 | KS83: 24.49 | KT83: 36.8 | KU83: 36.8 | KV83: 36.8 | KX83: 36.8 | KY83: 36.8 | KZ83: 36.8 | LA83: 36.8 | LB83: 36.8 | LC83: 19.68 | LE83: 2.56 | LF83: 2.56 | LG83: 6.84 | LH83: 11.12 | LI83: 11.12 | LJ83: 11.12 | LL83: 11.12 | LM83: 11.12 | LN83: 11.12 | LO83: 11.12 | LP83: 11.12 | LQ83: 13.84 | LS83: 16.56 | LT83: 16.56 | LU83: 16.56 | LV83: 16.56 | LW83: 16.56 | LX83: 16.56 | LZ83: 16.56 | MA83: 16.56 | MB83: 16.56 | MC83: 16.56 | MD83: 9.56 | ME83: 2.56 | MG83: 2.56 | MH83: 2.56 | MI83: 2.56 | MJ83: 2.56 | MK83: 2.56 | ML83: 2.56 | MN83: 2.56 | MO83: 2.56 | MP83: 2.56 | MQ83: 2.56 | MR83: 2.56 | MS83: 2.56 | MU83: 2.56 | MV83: 2.56 | MW83: 2.56 | MX83: 2.56 | MY83: 2.56 | MZ83: 2.56 | NB83: 2.56 | NC83: 2.56 | ND83: 2.56 | NE83: 2.56 | NF83: 2.56 | NG83: 2.56 | NI83: 2.56 | NJ83: 2.56 | NK83: 2.56 | NL83: 2.56 | NM83: 2.56 | NN83: 2.56 | NP83: 1.28 | YK83: 3.59 | YL83: 14.38 | YM83: 14.38 | YN83: 14.38 | YO83: 14.38 | YQ83: 14.38 | YR83: 14.38 | YS83: 14.38 | YT83: 10.78
A84: Sewer Dia 315 mm; Depth : 4.5m - 5.5m | E84: 15 | F84: 0.45 | G84: 13725 | H84: 13725 | I84: =F84 -> 0.45 | AF84: 0.06 | AG84: 0.06 | AH84: 0.06 | AK84: 0.06 | AL84: 0.06 | AM84: 0.06 | AN84: 0.06 | AO84: 0.06 | JO84: 0.02 | JP84: 0.03 | JQ84: 0.03 | JR84: 0.03 | JS84: 0.03 | JT84: 0.03 | JV84: 0.03 | JW84: 0.03 | JX84: 0.03 | JY84: 0.03 | JZ84: 0.03 | KA84: 0.03 | KC84: 0.03 | KD84: 0.03 | KE84: 0.03 | KF84: 0.03 | KG84: 0.03 | KH84: 0.03 | KJ84: 0.16 | KK84: 0.28 | KL84: 0.28 | KM84: 0.28 | KN84: 0.28 | KO84: 0.28 | KQ84: 0.28 | KR84: 0.28 | KS84: 0.24 | KT84: 0.2 | KU84: 0.2 | KV84: 0.2 | KX84: 0.2 | KY84: 0.2 | KZ84: 0.37 | LA84: 0.54 | LB84: 0.54 | LC84: 0.54 | LE84: 0.54 | LF84: 0.54 | LG84: 0.54 | LH84: 0.54 | LI84: 0.36 | LJ84: 0.18 | LL84: 0.18 | LM84: 0.18 | LN84: 0.18 | LO84: 0.18 | LP84: 0.18 | LQ84: 0.25 | LS84: 0.32 | LT84: 0.32 | LU84: 0.32 | LV84: 0.32 | LW84: 0.32 | LX84: 0.32 | LZ84: 0.18 | MA84: 0.03 | MB84: 0.03 | MC84: 0.03 | MD84: 0.03 | ME84: 0.03 | MG84: 0.03 | MH84: 0.03 | MI84: 0.03 | MJ84: 0.03 | MK84: 0.03 | ML84: 0.03 | MN84: 0.03 | MO84: 0.03 | MP84: 0.03 | MQ84: 0.03 | MR84: 0.03 | MS84: 0.03 | MU84: 0.03 | MV84: 0.03 | MW84: 0.03 | MX84: 0.03 | MY84: 0.03 | MZ84: 0.03 | NB84: 0.03 | NC84: 0.03 | ND84: 0.03 | NE84: 0.03 | NF84: 0.03 | NG84: 0.03 | NI84: 0.03 | NJ84: 0.03 | NK84: 0.03 | NL84: 0.03 | NM84: 0.03 | NN84: 0.03 | NP84: 0.02 | YK84: 0.05 | YL84: 0.19 | YM84: 0.19 | YN84: 0.19 | YO84: 0.19 | YQ84: 0.19 | YR84: 0.19 | YS84: 0.19 | YT84: 0.14
A85: Sewer Dia 400 mm; Depth : 3.5m - 4.5m | E85: 420 | F85: 12.6 | G85: 390600 | H85: 390600 | I85: =F85 -> 12.6 | AF85: 1.58 | AG85: 1.58 | AH85: 1.58 | AK85: 1.58 | AL85: 1.58 | AM85: 1.58 | AN85: 1.58 | AO85: 1.58 | JO85: 0.47 | JP85: 0.93 | JQ85: 0.93 | JR85: 0.93 | JS85: 0.93 | JT85: 0.93 | JV85: 0.93 | JW85: 0.93 | JX85: 0.93 | JY85: 0.93 | JZ85: 0.93 | KA85: 0.93 | KC85: 0.93 | KD85: 0.93 | KE85: 0.93 | KF85: 0.93 | KG85: 0.93 | KH85: 0.93 | KJ85: 0.93 | KK85: 0.93 | KL85: 0.93 | KM85: 0.93 | KN85: 0.93 | KO85: 0.93 | KQ85: 0.93 | KR85: 0.93 | KS85: 3.28 | KT85: 5.62 | KU85: 5.62 | KV85: 5.62 | KX85: 5.62 | KY85: 5.62 | KZ85: 5.62 | LA85: 5.62 | LB85: 5.62 | LC85: 5.62 | LE85: 5.62 | LF85: 5.62 | LG85: 5.62 | LH85: 5.62 | LI85: 5.62 | LJ85: 5.62 | LL85: 5.62 | LM85: 5.62 | LN85: 11.32 | LO85: 17.01 | LP85: 17.01 | LQ85: 17.01 | LS85: 17.01 | LT85: 17.01 | LU85: 17.01 | LV85: 10.73 | LW85: 4.45 | LX85: 4.45 | LZ85: 4.45 | MA85: 4.45 | MB85: 4.45 | MC85: 4.45 | MD85: 4.45 | ME85: 5.82 | MG85: 7.19 | MH85: 7.19 | MI85: 7.19 | MJ85: 7.19 | MK85: 7.19 | ML85: 7.19 | MN85: 7.19 | MO85: 7.19 | MP85: 4.06 | MQ85: 0.93 | MR85: 0.93 | MS85: 0.93 | MU85: 0.93 | MV85: 0.93 | MW85: 0.93 | MX85: 0.93 | MY85: 0.93 | MZ85: 0.93 | NB85: 0.93 | NC85: 0.93 | ND85: 0.93 | NE85: 0.93 | NF85: 0.93 | NG85: 0.93 | NI85: 0.93 | NJ85: 0.93 | NK85: 0.93 | NL85: 0.93 | NM85: 0.93 | NN85: 0.93 | NP85: 0.47 | YK85: 1.31 | YL85: 5.25 | YM85: 5.25 | YN85: 5.25 | YO85: 5.25 | YQ85: 5.25 | YR85: 5.25 | YS85: 5.25 | YT85: 3.94
A86: Sewer Dia 400 mm; Depth : 4.5m - 5.5m | E86: 375 | F86: 11.25 | G86: 397500 | H86: 397500 | I86: =F86 -> 11.25 | AF86: 1.41 | AG86: 1.41 | AH86: 1.41 | AK86: 1.41 | AL86: 1.41 | AM86: 1.41 | AN86: 1.41 | AO86: 1.41 | JO86: 0.42 | JP86: 0.83 | JQ86: 0.83 | JR86: 0.83 | JS86: 0.83 | JT86: 0.83 | JV86: 0.83 | JW86: 0.83 | JX86: 0.83 | JY86: 0.83 | JZ86: 0.83 | KA86: 0.83 | KC86: 0.83 | KD86: 0.83 | KE86: 0.83 | KF86: 0.83 | KG86: 0.83 | KH86: 0.83 | KJ86: 0.83 | KK86: 0.83 | KL86: 0.83 | KM86: 0.83 | KN86: 0.83 | KO86: 0.83 | KQ86: 0.83 | KR86: 0.83 | KS86: 0.83 | KT86: 0.83 | KU86: 0.83 | KV86: 0.83 | KX86: 0.83 | KY86: 0.83 | KZ86: 0.83 | LA86: 0.83 | LB86: 0.83 | LC86: 0.83 | LE86: 0.83 | LF86: 0.83 | LG86: 0.83 | LH86: 0.83 | LI86: 0.83 | LJ86: 0.83 | LL86: 0.83 | LM86: 0.83 | LN86: 0.83 | LO86: 0.83 | LP86: 0.83 | LQ86: 0.83 | LS86: 0.83 | LT86: 0.83 | LU86: 0.83 | LV86: 0.83 | LW86: 0.83 | LX86: 0.83 | LZ86: 0.83 | MA86: 0.83 | MB86: 0.83 | MC86: 0.83 | MD86: 0.83 | ME86: 0.83 | MG86: 0.83 | MH86: 0.83 | MI86: 0.83 | MJ86: 0.83 | MK86: 0.83 | ML86: 0.83 | MN86: 0.83 | MO86: 0.83 | MP86: 0.83 | MQ86: 0.83 | MR86: 0.83 | MS86: 0.83 | MU86: 0.83 | MV86: 0.83 | MW86: 0.83 | MX86: 0.83 | MY86: 0.83 | MZ86: 2.93 | NB86: 5.02 | NC86: 5.02 | ND86: 5.02 | NE86: 5.02 | NF86: 5.02 | NG86: 5.02 | NI86: 5.02 | NJ86: 5.02 | NK86: 5.02 | NL86: 5.02 | NM86: 5.02 | NN86: 4.72 | NP86: 4.01 | NQ86: 3.59 | NR86: 3.59 | NS86: 3.59 | NT86: 3.59 | NU86: 3.59 | NW86: 8.97 | NX86: 14.36 | NY86: 14.36 | NZ86: 14.36 | OA86: 14.36 | OB86: 14.36 | OD86: 14.36 | OE86: 7.18 | PA86: 0.79 | PB86: 2.36 | PC86: 2.36 | PD86: 2.36 | PF86: 2.36 | PG86: 2.36 | PH86: 2.36 | PI86: 2.36 | PJ86: 2.36 | PK86: 2.36 | PM86: 2.36 | PN86: 3.58 | PO86: 4.19 | PP86: 4.19 | PQ86: 4.19 | PR86: 4.19 | PT86: 4.19 | PY86: 5.58 | QA86: 5.58 | QB86: 5.58 | QC86: 5.58 | QD86: 4.19 | YK86: 1.17 | YL86: 4.69 | YM86: 4.69 | YN86: 4.69 | YO86: 4.69 | YQ86: 4.69 | YR86: 4.69 | YS86: 4.69 | YT86: 3.52
A87: Sewer Manhole Dia 1200 mm, Depth: 1.5 - 2.5m | E87: 22 | F87: 0 | G87: 325600 | H87: 325600 | I87: =F87 -> 0 | AK87: 0.08 | AL87: 0.08 | AM87: 0.08 | AN87: 0.08 | AO87: 0.08 | AP87: 0.08 | AR87: 0.08 | AS87: 0.08 | KC87: 0.11 | KD87: 0.22 | KE87: 0.22 | KF87: 0.22 | KG87: 0.22 | KH87: 0.22 | KJ87: 0.22 | KK87: 0.22 | KL87: 0.22 | KM87: 0.22 | KN87: 0.22 | KO87: 0.22 | KQ87: 0.22 | KR87: 0.22 | KS87: 0.22 | KT87: 0.22 | KU87: 0.22 | KV87: 0.22 | KX87: 0.35 | KY87: 0.48 | KZ87: 0.48 | LA87: 0.48 | LB87: 0.48 | LC87: 0.48 | LE87: 0.48 | LF87: 0.48 | LG87: 0.48 | LH87: 0.32 | LI87: 0.16 | LJ87: 0.16 | LL87: 0.16 | LM87: 0.16 | LN87: 0.16 | LO87: 0.16 | LP87: 0.16 | LQ87: 0.16 | LS87: 0.15 | LT87: 0.14 | LU87: 0.14 | LV87: 0.14 | LW87: 0.14 | LX87: 0.14 | LZ87: 0.14 | MA87: 0.14 | MB87: 0.14 | MC87: 0.14 | MD87: 0.14 | ME87: 0.09 | MG87: 0.05 | MH87: 0.05 | MI87: 0.05 | MJ87: 0.05 | MK87: 0.05 | ML87: 0.05 | MN87: 0.05 | MO87: 0.05 | MP87: 0.05 | MQ87: 0.05 | MR87: 0.05 | MS87: 0.05 | MU87: 0.05 | MV87: 0.05 | MW87: 0.05 | MX87: 0.05 | MY87: 0.05 | MZ87: 0.05 | NB87: 0.05 | NC87: 0.05 | ND87: 0.05 | NE87: 0.05 | NF87: 0.05 | NG87: 0.05 | NI87: 0.05 | NJ87: 0.05 | NK87: 0.05 | NL87: 0.05 | NM87: 0.05 | NN87: 0.05 | NP87: 0.05 | NQ87: 0.05 | NR87: 0.05 | NS87: 0.05 | NT87: 0.05 | NU87: 0.05 | NW87: 0.05 | NX87: 0.05 | NY87: 0.05 | NZ87: 0.05 | OA87: 0.05 | OB87: 0.05 | OD87: 0.05 | OE87: 0.05 | OF87: 0.05 | OG87: 0.05 | OH87: 0.12 | OI87: 0.19 | OL87: 0.19 | OM87: 0.19 | ON87: 0.19 | OO87: 0.19 | OP87: 0.19 | OR87: 0.16 | OS87: 0.19 | OT87: 0.19 | OU87: 0.19 | OV87: 0.19 | OW87: 0.19 | OY87: 0.19 | OZ87: 0.29 | PA87: 0.34 | PB87: 0.34 | PC87: 0.3 | PD87: 0.3 | PF87: 0.3 | PG87: 0.3 | PH87: 0.08 | PI87: 0.08 | PJ87: 0.08 | PK87: 0.08 | PM87: 0.08 | PN87: 0.08 | PO87: 0.08 | PP87: 0.08 | PQ87: 0.08 | PR87: 0.08 | PT87: 0.08 | PY87: 0.1 | QA87: 0.08 | YK87: 0.07 | YL87: 0.28 | YM87: 0.28 | YN87: 0.28 | YO87: 0.28 | YQ87: 0.28 | YR87: 0.28 | YS87: 0.28 | YT87: 0.21
A88: Sewer Manhole Dia 1200 mm, Depth: 2.5 - 3.5m | E88: 27 | F88: 0 | G88: 617760 | H88: 617760 | I88: =F88 -> 0 | AK88: 0.1 | AL88: 0.1 | AM88: 0.1 | AN88: 0.1 | AO88: 0.1 | AP88: 0.1 | AR88: 0.1 | AS88: 0.1 | KM88: 0.04 | KN88: 0.09 | KO88: 0.09 | KQ88: 0.09 | KR88: 0.09 | KS88: 0.09 | KT88: 0.09 | KU88: 0.09 | KV88: 0.09 | KX88: 0.12 | KY88: 0.16 | KZ88: 0.16 | LA88: 0.16 | LB88: 0.16 | LC88: 0.16 | LE88: 0.16 | LF88: 0.16 | LG88: 0.22 | LH88: 0.3 | LI88: 0.32 | LJ88: 0.32 | LL88: 0.32 | LM88: 0.32 | LN88: 0.32 | LO88: 0.25 | LP88: 0.2 | LQ88: 0.2 | LS88: 0.2 | LT88: 0.2 | LU88: 0.2 | LV88: 0.23 | LW88: 0.26 | LX88: 0.26 | LZ88: 0.26 | MA88: 0.26 | MB88: 0.22 | MC88: 0.18 | MD88: 0.21 | ME88: 0.23 | MG88: 0.2 | MH88: 0.17 | MI88: 0.17 | MJ88: 0.17 | MK88: 0.14 | ML88: 0.1 | MN88: 0.09 | MO88: 0.09 | MP88: 0.09 | MQ88: 0.08 | MR88: 0.08 | MS88: 0.08 | MU88: 0.08 | MV88: 0.08 | MW88: 0.08 | MX88: 0.07 | MY88: 0.06 | MZ88: 0.06 | NB88: 0.06 | NC88: 0.06 | ND88: 0.06 | NE88: 0.06 | NF88: 0.06 | NG88: 0.06 | NI88: 0.06 | NJ88: 0.06 | NK88: 0.06 | NL88: 0.06 | NM88: 0.06 | NN88: 0.06 | NP88: 0.06 | NQ88: 0.06 | NR88: 0.06 | NS88: 0.06 | NT88: 0.06 | NU88: 0.06 | NW88: 0.06 | NX88: 0.06 | NY88: 0.06 | NZ88: 0.06 | OA88: 0.06 | OB88: 0.06 | OD88: 0.06 | OE88: 0.06 | OF88: 0.06 | OG88: 0.06 | OH88: 0.06 | OI88: 0.06 | OL88: 0.06 | OM88: 0.06 | ON88: 0.06 | OO88: 0.06 | OP88: 0.06 | OR88: 0.05 | OS88: 0.05 | OT88: 0.05 | OU88: 0.05 | OV88: 0.05 | OW88: 0.05 | OY88: 0.05 | OZ88: 0.05 | PA88: 0.05 | PB88: 0.05 | PC88: 0.22 | PD88: 0.22 | PF88: 0.22 | PG88: 0.22 | PH88: 0.22 | PI88: 0.22 | PJ88: 0.22 | PK88: 0.22 | PM88: 0.22 | PN88: 0.22 | PO88: 0.26 | PP88: 0.35 | PQ88: 0.35 | PR88: 0.35 | PT88: 0.35 | PY88: 0.47 | QA88: 0.58 | QB88: 0.93 | QC88: 0.93 | QD88: 0.93 | QE88: 0.93 | QF88: 0.74 | QH88: 0.17 | QI88: 0.17 | QJ88: 0.17 | QK88: 0.17 | QL88: 0.17 | QM88: 0.17 | QO88: 0.18 | QP88: 0.23 | QQ88: 0.23 | QR88: 0.23 | QS88: 0.23 | QT88: 0.17 | YK88: 0.08 | YL88: 0.34 | YM88: 0.34 | YN88: 0.34 | YO88: 0.34 | YQ88: 0.34 | YR88: 0.34 | YS88: 0.34 | YT88: 0.25
A89: Sewer Manhole Dia 1200 mm, Depth: 3.5 - 4.5m | E89: 7 | F89: 0 | G89: 226800 | H89: 226800 | I89: =F89 -> 0 | AK89: 0.03 | AL89: 0.03 | AM89: 0.03 | AN89: 0.03 | AO89: 0.03 | AP89: 0.03 | AR89: 0.03 | AS89: 0.03 | KX89: 0.06 | KY89: 0.12 | KZ89: 0.12 | LA89: 0.12 | LB89: 0.12 | LC89: 0.12 | LE89: 0.12 | LF89: 0.12 | LG89: 0.12 | LH89: 0.12 | LI89: 0.12 | LJ89: 0.12 | LL89: 0.12 | LM89: 0.12 | LN89: 0.12 | LO89: 0.12 | LP89: 0.12 | LQ89: 0.12 | LS89: 0.2 | LT89: 0.28 | LU89: 0.28 | LV89: 0.28 | LW89: 0.28 | LX89: 0.28 | LZ89: 0.28 | MA89: 0.18 | MB89: 0.08 | MC89: 0.08 | MD89: 0.08 | ME89: 0.08 | MG89: 0.08 | MH89: 0.08 | MI89: 0.08 | MJ89: 0.07 | MK89: 0.07 | ML89: 0.07 | MN89: 0.07 | MO89: 0.07 | MP89: 0.07 | MQ89: 0.07 | MR89: 0.04 | MS89: 0.02 | MU89: 0.02 | MV89: 0.02 | MW89: 0.02 | MX89: 0.02 | MY89: 0.02 | MZ89: 0.02 | NB89: 0.02 | NC89: 0.02 | ND89: 0.02 | NE89: 0.02 | NF89: 0.02 | NG89: 0.02 | NI89: 0.02 | NJ89: 0.02 | NK89: 0.02 | NL89: 0.02 | NM89: 0.02 | NN89: 0.02 | NP89: 0.02 | NQ89: 0.02 | NR89: 0.02 | NS89: 0.02 | NT89: 0.02 | NU89: 0.02 | NW89: 0.02 | NX89: 0.02 | NY89: 0.02 | NZ89: 0.02 | OA89: 0.02 | OB89: 0.02 | OD89: 0.02 | OE89: 0.02 | OF89: 0.02 | OG89: 0.02 | OH89: 0.02 | OI89: 0.02 | OL89: 0.02 | OM89: 0.02 | ON89: 0.02 | OO89: 0.02 | OP89: 0.02 | OR89: 0.01 | OS89: 0.01 | OT89: 0.01 | OU89: 0.01 | OV89: 0.01 | OW89: 0.01 | OY89: 0.01 | OZ89: 0.01 | PA89: 0.01 | PB89: 0.01 | YK89: 0.02 | YL89: 0.09 | YM89: 0.09 | YN89: 0.09 | YO89: 0.09 | YQ89: 0.09 | YR89: 0.09 | YS89: 0.09 | YT89: 0.07
